Workbook

Sheet 실적
A1: 기업명 | B1: 티커 | C1: 최근 분기 종료일 | D1: 매출 Q0 (백만$) | E1: 매출 Q-1 (백만$) | F1: 매출 Q-2 (백만$) | G1: 매출 Q-3 (백만$) | H1: 매출 Q-4 (백만$) | I1: 영업이익 Q0 (백만$) | J1: 영업이익 Q-1 (백만$) | K1: 영업이익 Q-2 (백만$) | L1: 영업이익 Q-3 (백만$) | M1: 영업이익 Q-4 (백만$) | N1: 매출성장률(YoY) | O1: 영업이익성장률(YoY) | P1: 매출 QoQ(Q0) | Q1: 매출 QoQ(Q-1) | R1: 매출 QoQ(Q-2) | S1: 매출 QoQ(Q-3) | T1: 선정 기준 | U1: 주요 사업 | V1: GICS 섹터 | W1: 주가 2025-09-24 ($) | X1: 주가 2026-09-23 ($) | Y1: 1년 주가수익률 | Z1: 1년 총수익률(배당 포함) | AA1: 1년 전 매출성장률(YoY, 2025-09-24 시점) | AB1: 1년 전 선정 기준 (2025-09-24 시점) | AC1: 매출 YoY 변화(%p, 현재-1년 전)
A2: CDW Corporation | B2: CDW | C2: 2026-06-30 | D2: 6572.2 | E2: 5679.8 | F2: 5511 | G2: 5737.4 | H2: 5976.6 | I2: 428.6 | J2: 376 | K2: 430.7 | L2: 443.3 | M2: 420.2 | N2: 0.099655322 | O2: 0.019990481 | P2: 0.15711821 | Q2: 0.03062965 | R2: -0.039460383 | S2: -0.040022755 | T2: QoQ 가속 + 최근 QoQ≥10% | U2: 기업·공공기관 대상 IT 하드웨어·소프트웨어 유통 및 솔루션 | V2: Information Technology | W2: 160.47 | X2: 146.16 | Y2: =IF(AND(ISNUMBER(W2),ISNUMBER(X2)),X2/W2-1,"") -> -0.089175547 | Z2: -0.070628869 | AA2: 0.10200243 | AB2: 최근 QoQ≥10% | AC2: =IF(AND(ISNUMBER(N2),ISNUMBER(AA2)),N2-AA2,"") -> -0.0023471115
A3: Applied Materials | B3: AMAT | C3: 2026-07-31 | D3: 9115 | E3: 7910 | F3: 7012 | G3: 6800 | H3: 7302 | I3: 3075 | J3: 2523 | K3: 2096 | L3: 1893 | M3: 2233 | N3: 0.24828814 | O3: 0.3770712 | P3: 0.15233881 | Q3: 0.12806617 | R3: 0.031176471 | S3: -0.068748288 | T3: QoQ 가속 + 최근 QoQ≥10% | U3: 반도체·디스플레이 제조 장비 | V3: Information Technology | W3: 201.44 | X3: 474.38 | Y3: =IF(AND(ISNUMBER(W3),ISNUMBER(X3)),X3/W3-1,"") -> 1.3549444 | Z3: 1.3679697 | AA3: 0.077308941 | AC3: =IF(AND(ISNUMBER(N3),ISNUMBER(AA3)),N3-AA3,"") -> 0.1709792
A4: Home Depot (The) | B4: HD | C4: 2026-07-31 | D4: 47861 | E4: 41765 | F4: 38198 | G4: 41352 | H4: 45277 | I4: 6839 | J4: 4981 | K4: 3849 | L4: 5353 | M4: 6555 | N4: 0.057070919 | O4: 0.043325706 | P4: 0.14595954 | Q4: 0.093381852 | R4: -0.076272006 | S4: -0.086688606 | T4: QoQ 가속 + 최근 QoQ≥10% | U4: 주택개량 자재·용품 소매 | V4: Consumer Discretionary | W4: 409.77 | X4: 296.72 | Y4: =IF(AND(ISNUMBER(W4),ISNUMBER(X4)),X4/W4-1,"") -> -0.27588647 | Z4: -0.25538046 | AA4: 0.048685582 | AB4: QoQ 가속 + 최근 QoQ≥10% | AC4: =IF(AND(ISNUMBER(N4),ISNUMBER(AA4)),N4-AA4,"") -> 0.0083853371
A5: Eaton Corporation | B5: ETN | C5: 2026-06-30 | D5: 8531 | E5: 7451 | F5: 7055 | G5: 6988 | H5: 7028 | I5: 1392 | J5: 1172 | K5: 1386 | L5: 1367 | M5: 1256 | N5: 0.21385885 | O5: 0.10828025 | P5: 0.14494699 | Q5: 0.056130404 | R5: 0.0095878649 | S5: -0.0056915196 | T5: QoQ 가속 + 최근 QoQ≥10% | U5: 전력관리 장비 (데이터센터·전기·항공) | V5: Industrials | W5: 372.21 | X5: 438.76 | Y5: =IF(AND(ISNUMBER(W5),ISNUMBER(X5)),X5/W5-1,"") -> 0.17879692 | Z5: 0.19193964 | AA5: 0.10677165 | AB5: 최근 QoQ≥10% | AC5: =IF(AND(ISNUMBER(N5),ISNUMBER(AA5)),N5-AA5,"") -> 0.1070872
A6: Cboe Global Markets | B6: CBOE | C6: 2026-06-30 | D6: 1442.8 | E6: 1272.8 | F6: 1204 | G6: 1141.7 | H6: 1173.5 | I6: 476 | J6: 505.6 | K6: 428.8 | L6: 375 | M6: 356.2 | N6: 0.22948445 | O6: 0.33632791 | P6: 0.1335638 | Q6: 0.057142857 | R6: 0.05456775 | S6: -0.027098424 | T6: QoQ 가속 + 최근 QoQ≥10% | U6: 옵션·주식·선물 거래소 운영 | V6: Financials | W6: 243.19 | X6: 268.87 | Y6: =IF(AND(ISNUMBER(W6),ISNUMBER(X6)),X6/W6-1,"") -> 0.10559645 | Z6: 0.11373477 | AA6: 0.20482546 | AC6: =IF(AND(ISNUMBER(N6),ISNUMBER(AA6)),N6-AA6,"") -> 0.024658986
A7: Marvell Technology | B7: MRVL | C7: 2026-07-31 | D7: 2739.3 | E7: 2417.8 | F7: 2218.7 | G7: 2074.5 | H7: 2006.1 | I7: 456.9 | J7: 350.1 | K7: 413.9 | L7: 367.4 | M7: 298.8 | N7: 0.36548527 | O7: 0.52911647 | P7: 0.13297212 | Q7: 0.089737234 | R7: 0.069510725 | S7: 0.034096007 | T7: QoQ 가속 + 최근 QoQ≥10% | U7: 데이터센터용 맞춤형 AI 칩·광통신·네트워크 반도체 | V7: Information Technology | W7: 80.09 | X7: 260.9 | Y7: =IF(AND(ISNUMBER(W7),ISNUMBER(X7)),X7/W7-1,"") -> 2.2575852 | Z7: 2.2645257 | AA7: 0.57600754 | AC7: =IF(AND(ISNUMBER(N7),ISNUMBER(AA7)),N7-AA7,"") -> -0.21052227
A8: Coherent Corp. | B8: COHR | C8: 2026-06-30 | D8: 2045.533 | E8: 1805.641 | F8: 1685.629 | G8: 1581.378 | H8: 1529.436 | I8: 304.338 | J8: 226.321 | K8: 198.624 | L8: 172.239 | M8: 144.978 | N8: 0.33744269 | O8: 1.0992013 | P8: 0.13285697 | Q8: 0.071197161 | R8: 0.06592415 | S8: 0.033961539 | T8: QoQ 가속 + 최근 QoQ≥10% | U8: 레이저·광트랜시버 등 광학·광전자 부품 | V8: Information Technology | W8: 106.52 | X8: 300.6 | Y8: =IF(AND(ISNUMBER(W8),ISNUMBER(X8)),X8/W8-1,"") -> 1.8220053 | Z8: 1.8220054 | AA8: 0.16363376 | AC8: =IF(AND(ISNUMBER(N8),ISNUMBER(AA8)),N8-AA8,"") -> 0.17380893
A9: Lowe's | B9: LOW | C9: 2026-07-31 | D9: 25956 | E9: 23078 | F9: 20585 | G9: 20813 | H9: 23959 | I9: 3549 | J9: 2554 | K9: 1708 | L9: 2481 | M9: 3469 | N9: 0.083350724 | O9: 0.023061401 | P9: 0.12470751 | Q9: 0.1211076 | R9: -0.010954692 | S9: -0.13130765 | T9: QoQ 가속 + 최근 QoQ≥10% | U9: 주택개량 자재·용품 소매 | V9: Consumer Discretionary | W9: 257.33 | X9: 191.36 | Y9: =IF(AND(ISNUMBER(W9),ISNUMBER(X9)),X9/W9-1,"") -> -0.25636342 | Z9: -0.2410864 | AA9: 0.015814466 | AB9: QoQ 가속 + 최근 QoQ≥10% | AC9: =IF(AND(ISNUMBER(N9),ISNUMBER(AA9)),N9-AA9,"") -> 0.067536258
A10: Arista Networks | B10: ANET | C10: 2026-06-30 | D10: 3035.7 | E10: 2709 | F10: 2487.8 | G10: 2308.3 | H10: 2204.8 | I10: 1378 | J10: 1157.8 | K10: 1032.9 | L10: 978.2 | M10: 986.2 | N10: 0.37685958 | O10: 0.3972825 | P10: 0.12059801 | Q10: 0.0889139 | R10: 0.077762856 | S10: 0.046943033 | T10: QoQ 가속 + 최근 QoQ≥10% | U10: 데이터센터·AI 클러스터용 고속 네트워크 스위치 | V10: Information Technology | W10: 142.64 | X10: 203.47 | Y10: =IF(AND(ISNUMBER(W10),ISNUMBER(X10)),X10/W10-1,"") -> 0.42645822 | Z10: 0.42645823 | AA10: 0.30430667 | AC10: =IF(AND(ISNUMBER(N10),ISNUMBER(AA10)),N10-AA10,"") -> 0.072552906
A11: Darden Restaurants | B11: DRI | C11: 2026-05-31 | D11: 3718.8 | E11: 3345.3 | F11: 3102.1 | G11: 3044.7 | H11: 3271.7 | I11: 537.6 | J11: 440.3 | K11: 325.6 | L11: 303.1 | M11: 455.7 | N11: 0.13665678 | O11: 0.1797235 | P11: 0.11164918 | Q11: 0.078398504 | R11: 0.018852432 | S11: -0.06938289 | T11: QoQ 가속 + 최근 QoQ≥10% | U11: 올리브가든 등 캐주얼 다이닝 레스토랑 체인 | V11: Consumer Discretionary | W11: 186.61 | X11: 213.69 | Y11: =IF(AND(ISNUMBER(W11),ISNUMBER(X11)),X11/W11-1,"") -> 0.14511548 | Z11: 0.1814377 | AA11: 0.10631319 | AC11: =IF(AND(ISNUMBER(N11),ISNUMBER(AA11)),N11-AA11,"") -> 0.030343593
A12: Howmet Aerospace | B12: HWM | C12: 2026-06-30 | D12: 2547 | E12: 2313 | F12: 2168 | G12: 2089 | H12: 2053 | I12: 711 | J12: 660 | K12: 577 | L12: 542 | M12: 521 | N12: 0.24062348 | O12: 0.3646833 | P12: 0.10116732 | Q12: 0.066881919 | R12: 0.037817137 | S12: 0.017535314 | T12: QoQ 가속 + 최근 QoQ≥10% | U12: 항공기 엔진 부품·체결재 및 단조 휠 | V12: Industrials | W12: 190.22 | X12: 228.78 | Y12: =IF(AND(ISNUMBER(W12),ISNUMBER(X12)),X12/W12-1,"") -> 0.20271265 | Z12: 0.2052166 | AA12: 0.092021277 | AC12: =IF(AND(ISNUMBER(N12),ISNUMBER(AA12)),N12-AA12,"") -> 0.1486022
A13: Apollo Global Management | B13: APO | C13: 2026-06-30 | D13: 11153 | E13: 5057 | F13: 9864 | G13: 9823 | H13: 6814 | I13: 2850 | J13: 794 | K13: 2105 | L13: 3172 | M13: 1448 | N13: 0.63677722 | O13: 0.96823204 | P13: 1.2054578 | Q13: -0.48732766 | R13: 0.0041738776 | S13: 0.44159084 | T13: 최근 QoQ≥10% | U13: 사모신용·사모펀드 대체자산 운용 및 은퇴보험(Athene) | V13: Financials | W13: 137.16 | X13: 124.36 | Y13: =IF(AND(ISNUMBER(W13),ISNUMBER(X13)),X13/W13-1,"") -> -0.093321668 | Z13: -0.078318099 | AA13: 0.13226986 | AB13: 최근 QoQ≥10% | AC13: =IF(AND(ISNUMBER(N13),ISNUMBER(AA13)),N13-AA13,"") -> 0.50450737
A14: Live Nation Entertainment | B14: LYV | C14: 2026-06-30 | D14: 7666.858 | E14: 3793.029 | F14: 6313.505 | G14: 8499.143 | H14: 7006.641 | I14: 513.401 | J14: -376.538 | K14: -143.275 | L14: 777.6 | M14: 485.797 | N14: 0.094227319 | O14: 0.056822088 | P14: 1.0213022 | Q14: -0.39921977 | R14: -0.25715981 | S14: 0.21301248 | T14: 최근 QoQ≥10% | U14: 공연 기획·프로모션 및 티켓 판매(티켓마스터) | V14: Communication Services | W14: 162.08 | X14: 169.03 | Y14: =IF(AND(ISNUMBER(W14),ISNUMBER(X14)),X14/W14-1,"") -> 0.042880059 | Z14: 0.04288004 | AA14: 0.16323379 | AB14: 최근 QoQ≥10% | AC14: =IF(AND(ISNUMBER(N14),ISNUMBER(AA14)),N14-AA14,"") -> -0.069006467
A15: Devon Energy | B15: DVN | C15: 2026-06-30 | D15: 7417 | E15: 3807 | F15: 4121 | G15: 4331 | H15: 4284 | I15: 2543 | J15: 312 | K15: 841 | L15: 982 | M15: 981 | N15: 0.73132586 | O15: 1.5922528 | P15: 0.94825322 | Q15: -0.076195098 | R15: -0.048487647 | S15: 0.010971055 | T15: 최근 QoQ≥10% | U15: 미국 셰일 원유·천연가스 탐사·생산 | V15: Energy | W15: 35.21 | X15: 48.04 | Y15: =IF(AND(ISNUMBER(W15),ISNUMBER(X15)),X15/W15-1,"") -> 0.36438512 | Z15: 0.39916213 | AA15: 0.093694154 | AC15: =IF(AND(ISNUMBER(N15),ISNUMBER(AA15)),N15-AA15,"") -> 0.63763171
A16: Keurig Dr Pepper | B16: KDP | C16: 2026-06-30 | D16: 7309 | E16: 3976 | F16: 4499 | G16: 4306 | H16: 4163 | I16: 628 | J16: 756 | K16: 959 | L16: 995 | M16: 898 | N16: 0.75570502 | O16: -0.30066815 | P16: 0.83827968 | Q16: -0.11624806 | R16: 0.04482118 | S16: 0.034350228 | T16: 최근 QoQ≥10% | U16: 커피(큐리그)·음료 브랜드 제조 및 유통 | V16: Consumer Staples | W16: 26.25 | X16: 31.76 | Y16: =IF(AND(ISNUMBER(W16),ISNUMBER(X16)),X16/W16-1,"") -> 0.20990476 | Z16: 0.25063386 | AA16: 0.061448241 | AB16: 최근 QoQ≥10% | AC16: =IF(AND(ISNUMBER(N16),ISNUMBER(AA16)),N16-AA16,"") -> 0.69425678
A17: Micron Technology | B17: MU | C17: 2026-05-31 | D17: 41456 | E17: 23860 | F17: 13643 | G17: 11315 | H17: 9301 | I17: 33318 | J17: 16135 | K17: 6136 | L17: 3693 | M17: 2169 | N17: 3.4571551 | O17: 14.360996 | P17: 0.73746857 | Q17: 0.74888221 | R17: 0.20574459 | S17: 0.21653586 | T17: 최근 QoQ≥10% | U17: D램·낸드 메모리 반도체 제조 (AI 서버용 HBM 포함) | V17: Information Technology | W17: 161.71 | X17: 1071.88 | Y17: =IF(AND(ISNUMBER(W17),ISNUMBER(X17)),X17/W17-1,"") -> 5.6284089 | Z17: 5.6390471 | AA17: 0.36558508 | AB17: 최근 QoQ≥10% | AC17: =IF(AND(ISNUMBER(N17),ISNUMBER(AA17)),N17-AA17,"") -> 3.0915701
A18: Phillips 66 | B18: PSX | C18: 2026-06-30 | D18: 51004 | E18: 32540 | F18: 34108 | G18: 34515 | H18: 33323 | I18: 4280 | J18: 114 | K18: 1621 | L18: 965 | M18: 1190 | N18: 0.53059448 | O18: 2.5966387 | P18: 0.56742471 | Q18: -0.04597162 | R18: -0.011791975 | S18: 0.035771089 | T18: 최근 QoQ≥10% | U18: 석유 정제·화학·미드스트림·마케팅 | V18: Energy | W18: 136.59 | X18: 256.48 | Y18: =IF(AND(ISNUMBER(W18),ISNUMBER(X18)),X18/W18-1,"") -> 0.87773629 | Z18: 0.93334039 | AA18: -0.12604579 | AC18: =IF(AND(ISNUMBER(N18),ISNUMBER(AA18)),N18-AA18,"") -> 0.65664028
A19: Occidental Petroleum | B19: OXY | C19: 2026-06-30 | D19: 8065 | E19: 5230 | F19: 1752 | G19: 6624 | H19: 5258 | I19: 3665 | J19: 927 | K19: 117 | L19: 1174 | M19: 798 | N19: 0.53385318 | O19: 3.5927318 | P19: 0.54206501 | Q19: 1.9851598 | R19: -0.73550725 | S19: 0.2597946 | T19: 최근 QoQ≥10% | U19: 원유·가스 탐사·생산 및 화학(OxyChem) | V19: Energy | W19: 46.89 | X19: 57.36 | Y19: =IF(AND(ISNUMBER(W19),ISNUMBER(X19)),X19/W19-1,"") -> 0.22328855 | Z19: 0.24764654 | AA19: -0.059116914 | AC19: =IF(AND(ISNUMBER(N19),ISNUMBER(AA19)),N19-AA19,"") -> 0.59297009
A20: Marathon Petroleum | B20: MPC | C20: 2026-06-30 | D20: 51994 | E20: 34200 | F20: 32574 | G20: 34809 | H20: 33799 | I20: 6979 | J20: 1036 | K20: 1846 | L20: 1673 | M20: 1895 | N20: 0.53832954 | O20: 2.6828496 | P20: 0.5202924 | Q20: 0.049917112 | R20: -0.064207533 | S20: 0.029882541 | T20: 최근 QoQ≥10% | U20: 석유 정제·마케팅 및 미드스트림(MPLX) | V20: Energy | W20: 193.1 | X20: 388.38 | Y20: =IF(AND(ISNUMBER(W20),ISNUMBER(X20)),X20/W20-1,"") -> 1.0112895 | Z20: 1.0448839 | AA20: -0.10853511 | AB20: QoQ 가속 | AC20: =IF(AND(ISNUMBER(N20),ISNUMBER(AA20)),N20-AA20,"") -> 0.64686464
A21: Sandisk | B21: SNDK | C21: 2026-06-30 | D21: 8965 | E21: 5950 | F21: 3025 | G21: 2308 | H21: 1901 | I21: 7037 | J21: 4164 | K21: 1075 | L21: 192 | M21: 51 | N21: 3.715939 | O21: 136.98039 | P21: 0.50672269 | Q21: 0.96694215 | R21: 0.31065858 | S21: 0.21409784 | T21: 최근 QoQ≥10% | U21: 낸드 플래시 메모리·SSD 등 데이터 저장장치 제조 (WD에서 분사) | V21: Information Technology | W21: 99.83 | X21: 1816.5699 | Y21: =IF(AND(ISNUMBER(W21),ISNUMBER(X21)),X21/W21-1,"") -> 17.196633 | Z21: 17.196633 | AA21: 0.11495601 | AB21: 최근 QoQ≥10% | AC21: =IF(AND(ISNUMBER(N21),ISNUMBER(AA21)),N21-AA21,"") -> 3.600983
A22: CRH plc | B22: CRH | C22: 2026-06-30 | D22: 10777 | E22: 7370 | F22: 9416 | G22: 11069 | H22: 10206 | I22: 2027 | J22: -12 | K22: 1442 | L22: 1971 | M22: 1906 | N22: 0.055947482 | O22: 0.063483736 | P22: 0.46227951 | Q22: -0.21728972 | R22: -0.14933598 | S22: 0.084558103 | T22: 최근 QoQ≥10% | U22: 골재·시멘트·아스팔트 등 건설자재 | V22: Materials | W22: 112.6 | X22: 85.23 | Y22: =IF(AND(ISNUMBER(W22),ISNUMBER(X22)),X22/W22-1,"") -> -0.24307282 | Z22: -0.23458858 | AA22: 0.057178372 | AB22: 최근 QoQ≥10% | AC22: =IF(AND(ISNUMBER(N22),ISNUMBER(AA22)),N22-AA22,"") -> -0.0012308898
A23: Martin Marietta Materials | B23: MLM | C23: 2026-06-30 | D23: 1947 | E23: 1362 | F23: 1533 | G23: 1846 | H23: 1609 | I23: 390 | J23: 167 | K23: 350 | L23: 510 | M23: 415 | N23: 0.21006837 | O23: -0.060240964 | P23: 0.42951542 | Q23: -0.11154599 | R23: -0.1695558 | S23: 0.14729646 | T23: 최근 QoQ≥10% | U23: 골재·시멘트 등 건설자재 | V23: Materials | W23: 606.8 | X23: 490.45 | Y23: =IF(AND(ISNUMBER(W23),ISNUMBER(X23)),X23/W23-1,"") -> -0.19174357 | Z23: -0.18719733 | AA23: 0.026643991 | AB23: 최근 QoQ≥10% | AC23: =IF(AND(ISNUMBER(N23),ISNUMBER(AA23)),N23-AA23,"") -> 0.18342437
A24: Bloom Energy | B24: BE | C24: 2026-06-30 | D24: 1065.365 | E24: 751.054 | F24: 777.683 | G24: 519.048 | H24: 401.242 | I24: 182.237 | J24: 72.19 | K24: 87.529 | L24: 7.846 | M24: -3.503 | N24: 1.6551682 | O24: 흑자전환 | P24: 0.41849321 | Q24: -0.034241458 | R24: 0.49828725 | S24: 0.29360336 | T24: 최근 QoQ≥10% | U24: 고체산화물 연료전지 기반 현장 발전 시스템 (데이터센터 전력 공급) | V24: Industrials | W24: 69.18 | X24: 275.19 | Y24: =IF(AND(ISNUMBER(W24),ISNUMBER(X24)),X24/W24-1,"") -> 2.9778838 | Z24: 2.9778838 | AA24: 0.1950013 | AB24: 최근 QoQ≥10% | AC24: =IF(AND(ISNUMBER(N24),ISNUMBER(AA24)),N24-AA24,"") -> 1.4601669
A25: Chevron Corporation | B25: CVX | C25: 2026-06-30 | D25: 67199 | E25: 47556 | F25: 45787 | G25: 48169 | H25: 44375 | I25: 14276 | J25: 3222 | K25: 4023 | L25: 4297 | M25: 4057 | N25: 0.51434366 | O25: 2.5188563 | P25: 0.41304988 | Q25: 0.038635421 | R25: -0.049450892 | S25: 0.085498592 | T25: 최근 QoQ≥10% | U25: 석유·가스 탐사·생산 및 정제 통합 에너지 | V25: Energy | W25: 159.18 | X25: 205.51 | Y25: =IF(AND(ISNUMBER(W25),ISNUMBER(X25)),X25/W25-1,"") -> 0.29105415 | Z25: 0.34192784 | AA25: -0.12424533 | AC25: =IF(AND(ISNUMBER(N25),ISNUMBER(AA25)),N25-AA25,"") -> 0.63858899
A26: Blackstone Inc. | B26: BX | C26: 2026-06-30 | D26: 4187.932 | E26: 3002.779 | F26: 3736.455 | G26: 2685.881 | H26: 3161.236 | N26: 0.32477676 | P26: 0.39468539 | Q26: -0.19635617 | R26: 0.39114689 | S26: -0.15036998 | T26: 최근 QoQ≥10% | U26: 사모펀드·부동산·신용 대체자산 운용 | V26: Financials | W26: 178.08 | X26: 119.27 | Y26: =IF(AND(ISNUMBER(W26),ISNUMBER(X26)),X26/W26-1,"") -> -0.33024483 | Z26: -0.3030762 | AA26: 0.32739423 | AB26: 최근 QoQ≥10% | AC26: =IF(AND(ISNUMBER(N26),ISNUMBER(AA26)),N26-AA26,"") -> -0.0026174639
A27: ExxonMobil | B27: XOM | C27: 2026-06-30 | D27: 114529 | E27: 83161 | F27: 80039 | G27: 83331 | H27: 79477 | I27: 18195 | J27: 5347 | K27: 6003 | L27: 9178 | M27: 8911 | N27: 0.44103325 | O27: 1.0418584 | P27: 0.37719604 | Q27: 0.039005985 | R27: -0.039505106 | S27: 0.048492017 | T27: 최근 QoQ≥10% | U27: 석유·가스 탐사·생산·정제·화학 통합 에너지 | V27: Energy | W27: 114.56 | X27: 161.23 | Y27: =IF(AND(ISNUMBER(W27),ISNUMBER(X27)),X27/W27-1,"") -> 0.40738478 | Z27: 0.44817457 | AA27: -0.12415646 | AC27: =IF(AND(ISNUMBER(N27),ISNUMBER(AA27)),N27-AA27,"") -> 0.56518971
A28: Valero Energy | B28: VLO | C28: 2026-06-30 | D28: 44476 | E28: 32381 | F28: 30372 | G28: 32168 | H28: 29889 | I28: 5196 | J28: 1731 | K28: 1575 | L28: 1509 | M28: 997 | N28: 0.48803908 | O28: 4.2116349 | P28: 0.37352151 | Q28: 0.066146451 | R28: -0.055831883 | S28: 0.076248787 | T28: 최근 QoQ≥10% | U28: 석유 정제 및 재생연료(에탄올·재생디젤) 생산 | V28: Energy | W28: 170.83 | X28: 375.84 | Y28: =IF(AND(ISNUMBER(W28),ISNUMBER(X28)),X28/W28-1,"") -> 1.200082 | Z28: 1.2467278 | AA28: -0.13340099 | AC28: =IF(AND(ISNUMBER(N28),ISNUMBER(AA28)),N28-AA28,"") -> 0.62144006
A29: Lennox International | B29: LII | C29: 2026-06-30 | D29: 1545.3 | E29: 1135.1 | F29: 1195 | G29: 1426.8 | H29: 1500.9 | I29: 356.4 | J29: 166.1 | K29: 239.6 | L29: 307 | M29: 344.2 | N29: 0.029582251 | O29: 0.035444509 | P29: 0.36137785 | Q29: -0.050125523 | R29: -0.16246145 | S29: -0.049370378 | T29: 최근 QoQ≥10% | U29: 주거·상업용 냉난방공조(HVAC) 설비 | V29: Industrials | W29: 522.44 | X29: 372.34 | Y29: =IF(AND(ISNUMBER(W29),ISNUMBER(X29)),X29/W29-1,"") -> -0.28730572 | Z29: -0.279811 | AA29: 0.034318793 | AB29: 최근 QoQ≥10% | AC29: =IF(AND(ISNUMBER(N29),ISNUMBER(AA29)),N29-AA29,"") -> -0.004736542
A30: Airbnb | B30: ABNB | C30: 2026-06-30 | D30: 3608 | E30: 2678 | F30: 2778 | G30: 4095 | H30: 3096 | I30: 758 | J30: 86 | K30: 269 | L30: 1625 | M30: 612 | N30: 0.16537468 | O30: 0.23856209 | P30: 0.34727409 | Q30: -0.03599712 | R30: -0.32161172 | S30: 0.32267442 | T30: 최근 QoQ≥10% | U30: 숙박 공유·체험 예약 플랫폼 | V30: Consumer Discretionary | W30: 123.08 | X30: 149.58 | Y30: =IF(AND(ISNUMBER(W30),ISNUMBER(X30)),X30/W30-1,"") -> 0.21530712 | Z30: 0.21530711 | AA30: 0.12663755 | AB30: 최근 QoQ≥10% | AC30: =IF(AND(ISNUMBER(N30),ISNUMBER(AA30)),N30-AA30,"") -> 0.038737122
A31: Eversource Energy | B31: ES | C31: 2026-03-31 | D31: 4504.4 | E31: 3370.244 | F31: 3220.6 | G31: 2838.1 | H31: 4118.4 | I31: 1076.185 | J31: 710.512 | K31: 688.657 | L31: 663.081 | M31: 926.439 | N31: 0.093725719 | O31: 0.16163611 | P31: 0.33652044 | Q31: 0.046464634 | R31: 0.13477326 | S31: -0.31087315 | T31: 최근 QoQ≥10% | U31: 뉴잉글랜드 지역 전력·가스·수도 유틸리티 | V31: Utilities | W31: 69.1 | X31: 64.91 | Y31: =IF(AND(ISNUMBER(W31),ISNUMBER(X31)),X31/W31-1,"") -> -0.060636758 | Z31: -0.017227062 | AA31: 0.12020657 | AC31: =IF(AND(ISNUMBER(N31),ISNUMBER(AA31)),N31-AA31,"") -> -0.026480855
A32: Broadcom | B32: AVGO | C32: 2026-07-31 | D32: 29591 | E32: 22187 | F32: 19311 | G32: 18015 | H32: 15952 | I32: 16058 | J32: 10859 | K32: 8666 | L32: 7654 | M32: 6074 | N32: 0.85500251 | O32: 1.6437274 | P32: 0.33370893 | Q32: 0.14893066 | R32: 0.07194005 | S32: 0.12932548 | T32: 최근 QoQ≥10% | U32: 네트워크·맞춤형 AI 반도체 및 인프라 소프트웨어(VMware) | V32: Information Technology | W32: 339.31 | X32: 354.99 | Y32: =IF(AND(ISNUMBER(W32),ISNUMBER(X32)),X32/W32-1,"") -> 0.046211429 | Z32: 0.053990273 | AA32: 0.22031824 | AC32: =IF(AND(ISNUMBER(N32),ISNUMBER(AA32)),N32-AA32,"") -> 0.63468427
A33: KKR & Co. | B33: KKR | C33: 2026-06-30 | D33: 5657.34 | E33: 4252.726 | F33: 5685.044 | G33: 5464.926 | H33: 5002.879 | I33: 325.714 | J33: 456.472 | K33: 356.903 | L33: 512.719 | M33: 327.265 | N33: 0.13081688 | O33: -0.0047392786 | P33: 0.33028556 | Q33: -0.25194493 | R33: 0.040278313 | S33: 0.092356221 | T33: 최근 QoQ≥10% | U33: 사모펀드·인프라·신용 대체자산 운용 및 보험 | V33: Financials | W33: 137.94 | X33: 97.21 | Y33: =IF(AND(ISNUMBER(W33),ISNUMBER(X33)),X33/W33-1,"") -> -0.29527331 | Z33: -0.29016473 | AA33: 0.21978734 | AB33: 최근 QoQ≥10% | AC33: =IF(AND(ISNUMBER(N33),ISNUMBER(AA33)),N33-AA33,"") -> -0.088970464
A34: Booking Holdings | B34: BKNG | C34: 2026-06-30 | D34: 7352 | E34: 5532 | F34: 6349 | G34: 9008 | H34: 6798 | I34: 2500 | J34: 1271 | K34: 2030 | L34: 3940 | M34: 2250 | N34: 0.081494557 | O34: 0.11111111 | P34: 0.32899494 | Q34: -0.12868168 | R34: -0.29518206 | S34: 0.32509562 | T34: 최근 QoQ≥10% | U34: 온라인 숙박·여행 예약 (Booking.com·Priceline) | V34: Consumer Discretionary | W34: 221.024 | X34: 155.9 | Y34: =IF(AND(ISNUMBER(W34),ISNUMBER(X34)),X34/W34-1,"") -> -0.29464674 | Z34: -0.28818948 | AA34: 0.16026626 | AB34: 최근 QoQ≥10% | AC34: =IF(AND(ISNUMBER(N34),ISNUMBER(AA34)),N34-AA34,"") -> -0.0787717
A35: Incyte | B35: INCY | C35: 2026-06-30 | D35: 1674.039 | E35: 1272.676 | F35: 1506.835 | G35: 1365.98 | H35: 1215.529 | I35: 700.389 | J35: 324.173 | K35: 383.963 | L35: 431.296 | M35: 310.812 | N35: 0.37721025 | O35: 1.2534169 | P35: 0.31536935 | Q35: -0.1553979 | R35: 0.10311644 | S35: 0.12377409 | T35: 최근 QoQ≥10% | U35: 항암·면역·피부질환 치료제 바이오제약 | V35: Health Care | W35: 84.16 | X35: 124.64 | Y35: =IF(AND(ISNUMBER(W35),ISNUMBER(X35)),X35/W35-1,"") -> 0.48098859 | Z35: 0.48098852 | AA35: 0.16456864 | AB35: 최근 QoQ≥10% | AC35: =IF(AND(ISNUMBER(N35),ISNUMBER(AA35)),N35-AA35,"") -> 0.21264161
A36: Diamondback Energy | B36: FANG | C36: 2026-06-30 | D36: 5525 | E36: 4210 | F36: 3341 | G36: 3906 | H36: 3651 | I36: 2512 | J36: 1516 | K36: 776 | L36: 1253 | M36: 1139 | N36: 0.51328403 | O36: 1.2054434 | P36: 0.31235154 | Q36: 0.26010177 | R36: -0.14464926 | S36: 0.069843878 | T36: 최근 QoQ≥10% | U36: 퍼미안 분지 원유·천연가스 탐사·생산 | V36: Energy | W36: 144.61 | X36: 185.65 | Y36: =IF(AND(ISNUMBER(W36),ISNUMBER(X36)),X36/W36-1,"") -> 0.2837978 | Z36: 0.31472056 | AA36: 0.48127265 | AC36: =IF(AND(ISNUMBER(N36),ISNUMBER(AA36)),N36-AA36,"") -> 0.032011378
A37: Waters Corporation | B37: WAT | C37: 2026-06-30 | D37: 1645 | E37: 1267 | F37: 932.362 | G37: 799.887 | H37: 771 | I37: -37 | J37: -47 | K37: 270.516 | L37: 192.114 | M37: 191 | N37: 1.1335927 | O37: 적자전환 | P37: 0.29834254 | Q37: 0.35891424 | R37: 0.16561714 | S37: 0.037466926 | T37: 최근 QoQ≥10% | U37: 액체크로마토그래피·질량분석 등 분석기기 및 소프트웨어 | V37: Health Care | W37: 292.65 | X37: 420.57 | Y37: =IF(AND(ISNUMBER(W37),ISNUMBER(X37)),X37/W37-1,"") -> 0.43710917 | Z37: 0.43710923 | AA37: 0.041911104 | AB37: 최근 QoQ≥10% | AC37: =IF(AND(ISNUMBER(N37),ISNUMBER(AA37)),N37-AA37,"") -> 1.0916816
A38: Berkshire Hathaway | B38: BRK-B | C38: 2026-06-30 | D38: 117885 | E38: 92070 | F38: 111442 | G38: 98879 | H38: 83290 | N38: 0.41535599 | P38: 0.28038449 | Q38: -0.17383033 | R38: 0.12705428 | S38: 0.18716533 | T38: 최근 QoQ≥10% | U38: 보험·철도·에너지 유틸리티 등 복합 지주회사 | V38: Financials | W38: 497.09 | X38: 507.17 | Y38: =IF(AND(ISNUMBER(W38),ISNUMBER(X38)),X38/W38-1,"") -> 0.020278018 | Z38: 0.020278053 | AA38: -0.012151239 | AC38: =IF(AND(ISNUMBER(N38),ISNUMBER(AA38)),N38-AA38,"") -> 0.42750722
A39: Trane Technologies | B39: TT | C39: 2026-06-30 | D39: 6353.5 | E39: 4969.4 | F39: 5144.5 | G39: 5742.5 | H39: 5746.4 | I39: 1224.3 | J39: 776.1 | K39: 819 | L39: 1165.3 | M39: 1164.2 | N39: 0.10564875 | O39: 0.051623432 | P39: 0.27852457 | Q39: -0.034036349 | R39: -0.10413583 | S39: -0.00067868579 | T39: 최근 QoQ≥10% | U39: 상업·주거용 냉난방공조(HVAC) 및 운송 냉장 | V39: Industrials | W39: 404.09 | X39: 437.09 | Y39: =IF(AND(ISNUMBER(W39),ISNUMBER(X39)),X39/W39-1,"") -> 0.081664976 | Z39: 0.089303631 | AA39: 0.0827147 | AB39: 최근 QoQ≥10% | AC39: =IF(AND(ISNUMBER(N39),ISNUMBER(AA39)),N39-AA39,"") -> 0.022934054
A40: LyondellBasell | B40: LYB | C40: 2026-06-30 | D40: 9177 | E40: 7197 | F40: 7091 | G40: 7727 | H40: 7658 | I40: 1617 | J40: 254 | K40: -71 | L40: 471 | M40: 317 | N40: 0.19835466 | O40: 4.1009464 | P40: 0.27511463 | Q40: 0.014948526 | R40: -0.082308787 | S40: 0.0090101854 | T40: 최근 QoQ≥10% | U40: 폴리올레핀 등 석유화학 제품 | V40: Materials | W40: 51.37 | X40: 59.97 | Y40: =IF(AND(ISNUMBER(W40),ISNUMBER(X40)),X40/W40-1,"") -> 0.16741289 | Z40: 0.2409767 | AA40: -0.1175386 | AC40: =IF(AND(ISNUMBER(N40),ISNUMBER(AA40)),N40-AA40,"") -> 0.31589327
A41: Constellation Brands | B41: STZ | C41: 2026-05-31 | D41: 2432.7 | E41: 1920.2 | F41: 2222.8 | G41: 2481 | H41: 2515 | I41: 863.6 | J41: 531.2 | K41: 692 | L41: 874 | M41: 765.9 | N41: -0.032723658 | O41: 0.12756234 | P41: 0.26689928 | Q41: -0.13613461 | R41: -0.10407094 | S41: -0.013518887 | T41: 최근 QoQ≥10% | U41: 수입 맥주(코로나·모델로)·와인·증류주 | V41: Consumer Staples | W41: 133.39 | X41: 116.57 | Y41: =IF(AND(ISNUMBER(W41),ISNUMBER(X41)),X41/W41-1,"") -> -0.12609641 | Z41: -0.10055817 | AA41: -0.05515065 | AB41: 최근 QoQ≥10% | AC41: =IF(AND(ISNUMBER(N41),ISNUMBER(AA41)),N41-AA41,"") -> 0.022426992
A42: Pinnacle West Capital | B42: PNW | C42: 2026-06-30 | D42: 1455.749 | E42: 1149.597 | F42: 1128.167 | G42: 1820.741 | H42: 1358.751 | I42: 305.672 | J42: 131.174 | K42: 121.01 | L42: 581.846 | M42: 307.552 | N42: 0.07138762 | O42: -0.0061127874 | P42: 0.26631246 | Q42: 0.018995415 | R42: -0.3803803 | S42: 0.34001079 | T42: 최근 QoQ≥10% | U42: 애리조나주 전력 유틸리티 | V42: Utilities | W42: 87.14 | X42: 92.05 | Y42: =IF(AND(ISNUMBER(W42),ISNUMBER(X42)),X42/W42-1,"") -> 0.05634611 | Z42: 0.097245232 | AA42: 0.038011633 | AB42: 최근 QoQ≥10% | AC42: =IF(AND(ISNUMBER(N42),ISNUMBER(AA42)),N42-AA42,"") -> 0.033375987
A43: Tractor Supply | B43: TSCO | C43: 2026-06-30 | D43: 4541.314 | E43: 3592.046 | F43: 3898.32 | G43: 3719.044 | H43: 4439.729 | I43: 529.862 | J43: 233.431 | K43: 297.731 | L43: 342.709 | M43: 577.812 | N43: 0.022880901 | O43: -0.082985469 | P43: 0.26426944 | Q43: -0.078565639 | R43: 0.048204861 | S43: -0.16232635 | T43: 최근 QoQ≥10% | U43: 농촌 생활용품·반려동물·가축용품 소매 | V43: Consumer Discretionary | W43: 57.35 | X43: 32.29 | Y43: =IF(AND(ISNUMBER(W43),ISNUMBER(X43)),X43/W43-1,"") -> -0.436966 | Z43: -0.42341071 | AA43: 0.045473084 | AB43: 최근 QoQ≥10% | AC43: =IF(AND(ISNUMBER(N43),ISNUMBER(AA43)),N43-AA43,"") -> -0.022592183
A44: Tesla, Inc. | B44: TSLA | C44: 2026-06-30 | D44: 28236 | E44: 22387 | F44: 24901 | G44: 28095 | H44: 22496 | I44: 398 | J44: 941 | K44: 1571 | L44: 1862 | M44: 923 | N44: 0.25515647 | O44: -0.5687974 | P44: 0.2612677 | Q44: -0.1009598 | R44: -0.11368571 | S44: 0.24888869 | T44: 최근 QoQ≥10% | U44: 전기차 및 에너지 저장장치(ESS)·태양광 | V44: Consumer Discretionary | W44: 442.79 | X44: 380.12 | Y44: =IF(AND(ISNUMBER(W44),ISNUMBER(X44)),X44/W44-1,"") -> -0.14153436 | Z44: -0.14153439 | AA44: -0.11780392 | AB44: 최근 QoQ≥10% | AC44: =IF(AND(ISNUMBER(N44),ISNUMBER(AA44)),N44-AA44,"") -> 0.37296039
A45: Expedia Group | B45: EXPE | C45: 2026-06-30 | D45: 4315 | E45: 3426 | F45: 3547 | G45: 4412 | H45: 3786 | I45: 819 | J45: 243 | K45: 548 | L45: 1128 | M45: 531 | N45: 0.1397253 | O45: 0.54237288 | P45: 0.25948628 | Q45: -0.034113335 | R45: -0.19605621 | S45: 0.16534601 | T45: 최근 QoQ≥10% | U45: 온라인 여행 예약 플랫폼 | V45: Consumer Discretionary | W45: 217.83 | X45: 259.04 | Y45: =IF(AND(ISNUMBER(W45),ISNUMBER(X45)),X45/W45-1,"") -> 0.18918423 | Z45: 0.19801286 | AA45: 0.064080944 | AB45: 최근 QoQ≥10% | AC45: =IF(AND(ISNUMBER(N45),ISNUMBER(AA45)),N45-AA45,"") -> 0.075644359
A46: Expeditors International | B46: EXPD | C46: 2026-06-30 | D46: 3502.335 | E46: 2782.962 | F46: 2855.954 | G46: 2894.751 | H46: 2651.885 | I46: 349.618 | J46: 294.828 | K46: 250.91 | L46: 288.042 | M46: 247.736 | N46: 0.32069641 | O46: 0.4112523 | P46: 0.25849185 | Q46: -0.025557835 | R46: -0.013402534 | S46: 0.091582403 | T46: 최근 QoQ≥10% | U46: 항공·해상 화물 포워딩 및 통관 물류 | V46: Industrials | W46: 120.98 | X46: 188.03 | Y46: =IF(AND(ISNUMBER(W46),ISNUMBER(X46)),X46/W46-1,"") -> 0.55422384 | Z46: 0.57046504 | AA46: 0.087283277 | AC46: =IF(AND(ISNUMBER(N46),ISNUMBER(AA46)),N46-AA46,"") -> 0.23341313
A47: EOG Resources | B47: EOG | C47: 2026-06-30 | D47: 8494 | E47: 6758 | F47: 5653 | G47: 5732 | H47: 5355 | I47: 3449 | J47: 2493 | K47: 1667 | L47: 1809 | M47: 1679 | N47: 0.58618114 | O47: 1.0541989 | P47: 0.25688073 | Q47: 0.19547143 | R47: -0.013782275 | S47: 0.070401494 | T47: 최근 QoQ≥10% | U47: 미국 원유·천연가스 탐사·생산 | V47: Energy | W47: 116.7 | X47: 141.84 | Y47: =IF(AND(ISNUMBER(W47),ISNUMBER(X47)),X47/W47-1,"") -> 0.21542416 | Z47: 0.2576754 | AA47: -0.090788382 | AC47: =IF(AND(ISNUMBER(N47),ISNUMBER(AA47)),N47-AA47,"") -> 0.67696952
A48: Corteva | B48: CTVA | C48: 2026-03-31 | D48: 4905 | E48: 3910 | F48: 2618 | G48: 6456 | H48: 4417 | I48: 1155 | J48: 242 | K48: -270 | L48: 1832 | M48: 827 | N48: 0.11048223 | O48: 0.39661427 | P48: 0.2544757 | Q48: 0.49350649 | R48: -0.59448575 | S48: 0.46162554 | T48: 최근 QoQ≥10% | U48: 종자 및 작물보호제(농약) | V48: Materials | W48: 69.61 | X48: 80.42 | Y48: =IF(AND(ISNUMBER(W48),ISNUMBER(X48)),X48/W48-1,"") -> 0.15529378 | Z48: 0.16614858 | AA48: 0.056282723 | AB48: 최근 QoQ≥10% | AC48: =IF(AND(ISNUMBER(N48),ISNUMBER(AA48)),N48-AA48,"") -> 0.054199505
A49: Oneok | B49: OKE | C49: 2026-06-30 | D49: 12049 | E49: 9618 | F49: 9065 | G49: 8634 | H49: 7887 | I49: 1597 | J49: 1435 | K49: 1539 | L49: 1568 | M49: 1453 | N49: 0.52770382 | O49: 0.099105299 | P49: 0.25275525 | Q49: 0.061003861 | R49: 0.049918925 | S49: 0.094712819 | T49: 최근 QoQ≥10% | U49: 천연가스·NGL 수집·처리·수송 미드스트림 | V49: Energy | W49: 73.67 | X49: 90.54 | Y49: =IF(AND(ISNUMBER(W49),ISNUMBER(X49)),X49/W49-1,"") -> 0.22899416 | Z49: 0.29570846 | AA49: 0.61156518 | AC49: =IF(AND(ISNUMBER(N49),ISNUMBER(AA49)),N49-AA49,"") -> -0.083861365
A50: Delta Air Lines | B50: DAL | C50: 2026-06-30 | D50: 19757 | E50: 15854 | F50: 16003 | G50: 16673 | H50: 16648 | I50: 1864 | J50: 501 | K50: 1467 | L50: 1684 | M50: 2102 | N50: 0.18674916 | O50: -0.1132255 | P50: 0.24618393 | Q50: -0.0093107542 | R50: -0.04018473 | S50: 0.0015016819 | T50: 최근 QoQ≥10% | U50: 미국 대형 항공사 (여객·화물) | V50: Industrials | W50: 57.71 | X50: 81.75 | Y50: =IF(AND(ISNUMBER(W50),ISNUMBER(X50)),X50/W50-1,"") -> 0.41656559 | Z50: 0.43206294 | AA50: -0.00060031216 | AB50: 최근 QoQ≥10% | AC50: =IF(AND(ISNUMBER(N50),ISNUMBER(AA50)),N50-AA50,"") -> 0.18734947
A51: Lumentum | B51: LITE | C51: 2026-06-30 | D51: 1006.3 | E51: 808.4 | F51: 665.5 | G51: 533.8 | H51: 480.7 | I51: 281.7 | J51: 175.6 | K51: 63.9 | L51: 15 | M51: -3.2 | N51: 1.0934055 | O51: 흑자전환 | P51: 0.24480455 | Q51: 0.21472577 | R51: 0.24672162 | S51: 0.11046391 | T51: 최근 QoQ≥10% | U51: 광통신 부품·레이저 (데이터센터용 광트랜시버) | V51: Information Technology | W51: 152.75 | X51: 937 | Y51: =IF(AND(ISNUMBER(W51),ISNUMBER(X51)),X51/W51-1,"") -> 5.1342062 | Z51: 5.1342062 | AA51: 0.55919559 | AB51: 최근 QoQ≥10% | AC51: =IF(AND(ISNUMBER(N51),ISNUMBER(AA51)),N51-AA51,"") -> 0.53420986
A52: PepsiCo | B52: PEP | C52: 2026-06-30 | D52: 24181 | E52: 19443 | F52: 29343 | G52: 23937 | H52: 22726 | I52: 4023 | J52: 3213 | K52: 3557 | L52: 3702 | M52: 3649 | N52: 0.064023585 | O52: 0.10249383 | P52: 0.24368667 | Q52: -0.33738882 | R52: 0.22584284 | S52: 0.053286984 | T52: 최근 QoQ≥10% | U52: 음료(펩시) 및 스낵(프리토레이) 식품 | V52: Consumer Staples | W52: 142.17 | X52: 130.18 | Y52: =IF(AND(ISNUMBER(W52),ISNUMBER(X52)),X52/W52-1,"") -> -0.084335654 | Z52: -0.047233306 | AA52: 0.0099995556 | AB52: 최근 QoQ≥10% | AC52: =IF(AND(ISNUMBER(N52),ISNUMBER(AA52)),N52-AA52,"") -> 0.05402403
A53: Casey's | B53: CASY | C53: 2026-07-31 | D53: 5678.336 | E53: 4571.779 | F53: 3916.132 | G53: 4506.084 | H53: 4567.106 | I53: 369.089 | J53: 234.839 | K53: 194.828 | L53: 298.683 | M53: 305.307 | N53: 0.24331163 | O53: 0.20891103 | P53: 0.24204079 | Q53: 0.16742209 | R53: -0.13092344 | S53: -0.013361196 | T53: 최근 QoQ≥10% | U53: 미국 중서부 편의점·주유소 체인 | V53: Consumer Staples | W53: 547.05 | X53: 597.31 | Y53: =IF(AND(ISNUMBER(W53),ISNUMBER(X53)),X53/W53-1,"") -> 0.0918746 | Z53: 0.095676354 | AA53: 0.11454347 | AB53: QoQ 가속 + 최근 QoQ≥10% | AC53: =IF(AND(ISNUMBER(N53),ISNUMBER(AA53)),N53-AA53,"") -> 0.12876816
A54: NVR, Inc. | B54: NVR | C54: 2026-06-30 | D54: 2330.339 | E54: 1884.692 | F54: 2717.314 | G54: 2614.386 | H54: 2603.307 | I54: 312.248 | J54: 230.055 | K54: 452.081 | L54: 427.855 | M54: 427.729 | N54: -0.10485433 | O54: -0.26998637 | P54: 0.23645614 | Q54: -0.30641361 | R54: 0.039369856 | S54: 0.0042557409 | T54: 최근 QoQ≥10% | U54: 미국 주택건설업체 및 모기지 금융 | V54: Consumer Discretionary | W54: 8036.6299 | X54: 6241.6099 | Y54: =IF(AND(ISNUMBER(W54),ISNUMBER(X54)),X54/W54-1,"") -> -0.22335482 | Z54: -0.22335482 | AA54: -0.0052222869 | AC54: =IF(AND(ISNUMBER(N54),ISNUMBER(AA54)),N54-AA54,"") -> -0.099632039
A55: Vertiv | B55: VRT | C55: 2026-06-30 | D55: 3274.3 | E55: 2649.5 | F55: 2880 | G55: 2675.8 | H55: 2638.1 | I55: 637.9 | J55: 433.6 | K55: 606.9 | L55: 548.3 | M55: 446.6 | N55: 0.24115841 | O55: 0.42834751 | P55: 0.23581808 | Q55: -0.080034722 | R55: 0.076313626 | S55: 0.014290588 | T55: 최근 QoQ≥10% | U55: 데이터센터 전력·냉각 인프라 장비 | V55: Industrials | W55: 141.62 | X55: 248.78 | Y55: =IF(AND(ISNUMBER(W55),ISNUMBER(X55)),X55/W55-1,"") -> 0.75667279 | Z55: 0.75854332 | AA55: 0.350932 | AB55: 최근 QoQ≥10% | AC55: =IF(AND(ISNUMBER(N55),ISNUMBER(AA55)),N55-AA55,"") -> -0.10977359
A56: Dow Inc. | B56: DOW | C56: 2026-06-30 | D56: 12092 | E56: 9794 | F56: 9460 | G56: 9973 | H56: 10104 | I56: 1385 | J56: -4 | K56: -10 | L56: 154 | M56: -15 | N56: 0.19675376 | O56: 흑자전환 | P56: 0.23463345 | Q56: 0.035306554 | R56: -0.051438885 | S56: -0.012965162 | T56: 최근 QoQ≥10% | U56: 플라스틱·산업용 중간재 등 소재화학 | V56: Materials | W56: 23.13 | X56: 28.65 | Y56: =IF(AND(ISNUMBER(W56),ISNUMBER(X56)),X56/W56-1,"") -> 0.2386511 | Z56: 0.29978556 | AA56: -0.07430142 | AC56: =IF(AND(ISNUMBER(N56),ISNUMBER(AA56)),N56-AA56,"") -> 0.27105518
A57: Vulcan Materials Company | B57: VMC | C57: 2026-06-30 | D57: 2155.8 | E57: 1755.9 | F57: 1912.6 | G57: 2291.5 | H57: 2102.4 | I57: 466.8 | J57: 265.7 | K57: 335.7 | L57: 542.6 | M57: 469.8 | N57: 0.025399543 | O57: -0.006385696 | P57: 0.22774645 | Q57: -0.081930357 | R57: -0.16535021 | S57: 0.089944825 | T57: 최근 QoQ≥10% | U57: 골재 등 건설자재 (미국 최대 골재 생산) | V57: Materials | W57: 293.81 | X57: 244.4 | Y57: =IF(AND(ISNUMBER(W57),ISNUMBER(X57)),X57/W57-1,"") -> -0.16816991 | Z57: -0.1619563 | AA57: 0.043685465 | AB57: 최근 QoQ≥10% | AC57: =IF(AND(ISNUMBER(N57),ISNUMBER(AA57)),N57-AA57,"") -> -0.018285921
A58: Robinhood Markets | B58: HOOD | C58: 2026-06-30 | D58: 1308 | E58: 1067 | F58: 1283 | G58: 1274 | H58: 989 | I58: 574 | J58: 411 | K58: 650 | L58: 635 | M58: 439 | N58: 0.32254803 | O58: 0.30751708 | P58: 0.22586692 | Q58: -0.16835542 | R58: 0.0070643642 | S58: 0.28816987 | T58: 최근 QoQ≥10% | U58: 모바일 주식·옵션·암호화폐 거래 플랫폼 | V58: Financials | W58: 126.8 | X58: 122.7 | Y58: =IF(AND(ISNUMBER(W58),ISNUMBER(X58)),X58/W58-1,"") -> -0.032334385 | Z58: -0.032334432 | AA58: 0.45014663 | AC58: =IF(AND(ISNUMBER(N58),ISNUMBER(AA58)),N58-AA58,"") -> -0.1275986
A59: Ameren | B59: AEE | C59: 2026-03-31 | D59: 2176 | E59: 1782 | F59: 2699 | G59: 2221 | H59: 2097 | I59: 532 | J59: 360 | K59: 825 | L59: 411 | M59: 430 | N59: 0.037672866 | O59: 0.2372093 | P59: 0.22109989 | Q59: -0.33975546 | R59: 0.21521837 | S59: 0.059132093 | T59: 최근 QoQ≥10% | U59: 미주리·일리노이 전력·가스 유틸리티 | V59: Utilities | W59: 100.85 | X59: 99.74 | Y59: =IF(AND(ISNUMBER(W59),ISNUMBER(X59)),X59/W59-1,"") -> -0.011006445 | Z59: 0.017114804 | AA59: 0.31187242 | AC59: =IF(AND(ISNUMBER(N59),ISNUMBER(AA59)),N59-AA59,"") -> -0.27419955
A60: D. R. Horton | B60: DHI | C60: 2026-06-30 | D60: 9227.1 | E60: 7558.1 | F60: 6886.9 | G60: 9677.8 | H60: 9225.7 | I60: 1155 | J60: 800 | K60: 729.6 | L60: 1125.8 | M60: 1264.9 | N60: 0.00015175 | O60: -0.086884339 | P60: 0.22082269 | Q60: 0.097460396 | R60: -0.28838166 | S60: 0.049004412 | T60: 최근 QoQ≥10% | U60: 미국 최대 주택건설업체 | V60: Consumer Discretionary | W60: 167.45 | X60: 140.17 | Y60: =IF(AND(ISNUMBER(W60),ISNUMBER(X60)),X60/W60-1,"") -> -0.1629143 | Z60: -0.15286681 | AA60: -0.074254694 | AB60: 최근 QoQ≥10% | AC60: =IF(AND(ISNUMBER(N60),ISNUMBER(AA60)),N60-AA60,"") -> 0.074406444
A61: Albemarle Corporation | B61: ALB | C61: 2026-06-30 | D61: 1743.313 | E61: 1428.731 | F61: 1428.031 | G61: 1307.829 | H61: 1329.992 | I61: 460.281 | J61: 354.39 | K61: 30.253 | L61: -33.641 | M61: 51.975 | N61: 0.31076954 | O61: 7.8558153 | P61: 0.22018281 | Q61: 0.00049018544 | R61: 0.091909569 | S61: -0.01666401 | T61: 최근 QoQ≥10% | U61: 리튬 등 배터리 소재 및 특수화학 | V61: Materials | W61: 81.58 | X61: 113.47 | Y61: =IF(AND(ISNUMBER(W61),ISNUMBER(X61)),X61/W61-1,"") -> 0.39090463 | Z61: 0.40685254 | AA61: -0.070185999 | AB61: 최근 QoQ≥10% | AC61: =IF(AND(ISNUMBER(N61),ISNUMBER(AA61)),N61-AA61,"") -> 0.38095554
A62: Monolithic Power Systems | B62: MPWR | C62: 2026-06-30 | D62: 980.642 | E62: 804.185 | F62: 751.155 | G62: 737.176 | H62: 664.574 | I62: 303.894 | J62: 241.152 | K62: 199.936 | L62: 195.183 | M62: 164.758 | N62: 0.47559489 | O62: 0.84448707 | P62: 0.21942339 | Q62: 0.070597946 | R62: 0.018962907 | S62: 0.10924592 | T62: 최근 QoQ≥10% | U62: 전력관리 반도체(전원 IC) 설계 | V62: Information Technology | W62: 908.45 | X62: 1355.47 | Y62: =IF(AND(ISNUMBER(W62),ISNUMBER(X62)),X62/W62-1,"") -> 0.49206891 | Z62: 0.50250937 | AA62: 0.30968348 | AC62: =IF(AND(ISNUMBER(N62),ISNUMBER(AA62)),N62-AA62,"") -> 0.16591141
A63: ConocoPhillips | B63: COP | C63: 2026-06-30 | D63: 19161 | E63: 15761 | F63: 13392 | G63: 15031 | H63: 14004 | I63: 5979 | J63: 3387 | K63: 1760 | L63: 2758 | M63: 2606 | N63: 0.36825193 | O63: 1.2943208 | P63: 0.21572235 | Q63: 0.17689665 | R63: -0.10904131 | S63: 0.07333619 | T63: 최근 QoQ≥10% | U63: 원유·천연가스·LNG 탐사·생산 | V63: Energy | W63: 95.63 | X63: 128.09 | Y63: =IF(AND(ISNUMBER(W63),ISNUMBER(X63)),X63/W63-1,"") -> 0.33943323 | Z63: 0.3816609 | AA63: 0.028193833 | AC63: =IF(AND(ISNUMBER(N63),ISNUMBER(AA63)),N63-AA63,"") -> 0.3400581
A64: Quanta Services | B64: PWR | C64: 2026-06-30 | D64: 9556.997 | E64: 7874.787 | F64: 7841.948 | G64: 7631.408 | H64: 6773.007 | I64: 689.731 | J64: 334.222 | K64: 480.238 | L64: 510.289 | M64: 366.041 | N64: 0.41104195 | O64: 0.88429985 | P64: 0.21361975 | Q64: 0.0041876075 | R64: 0.027588618 | S64: 0.12673854 | T64: 최근 QoQ≥10% | U64: 전력망·통신·가스 인프라 설계·시공 | V64: Industrials | W64: 402.87 | X64: 634.9 | Y64: =IF(AND(ISNUMBER(W64),ISNUMBER(X64)),X64/W64-1,"") -> 0.57594261 | Z64: 0.57728469 | AA64: 0.21067903 | AC64: =IF(AND(ISNUMBER(N64),ISNUMBER(AA64)),N64-AA64,"") -> 0.20036292
A65: Reddit | B65: RDDT | C65: 2026-06-30 | D65: 804.905 | E65: 663.411 | F65: 725.607 | G65: 584.911 | H65: 499.627 | I65: 231.716 | J65: 182.912 | K65: 231.828 | L65: 138.542 | M65: 67.711 | N65: 0.61101181 | O65: 2.4221323 | P65: 0.21328257 | Q65: -0.085715821 | R65: 0.24054258 | S65: 0.17069534 | T65: 최근 QoQ≥10% | U65: 온라인 커뮤니티 플랫폼 레딧 운영 (광고·데이터 라이선스) | V65: Communication Services | W65: 235.69 | X65: 151.98 | Y65: =IF(AND(ISNUMBER(W65),ISNUMBER(X65)),X65/W65-1,"") -> -0.35516993 | Z65: -0.35516995 | AA65: 0.77686853 | AB65: 최근 QoQ≥10% | AC65: =IF(AND(ISNUMBER(N65),ISNUMBER(AA65)),N65-AA65,"") -> -0.16585671
A66: United Airlines Holdings | B66: UAL | C66: 2026-06-30 | D66: 17672 | E66: 14608 | F66: 15396 | G66: 15225 | H66: 15236 | I66: 951 | J66: 608 | K66: 1376 | L66: 1321 | M66: 1772 | N66: 0.15988448 | O66: -0.46331828 | P66: 0.20974808 | Q66: -0.051182125 | R66: 0.011231527 | S66: -0.00072197427 | T66: 최근 QoQ≥10% | U66: 미국 대형 항공사 (국제선 중심) | V66: Industrials | W66: 101.39 | X66: 110.72 | Y66: =IF(AND(ISNUMBER(W66),ISNUMBER(X66)),X66/W66-1,"") -> 0.092020909 | Z66: 0.092020928 | AA66: 0.016682237 | AB66: 최근 QoQ≥10% | AC66: =IF(AND(ISNUMBER(N66),ISNUMBER(AA66)),N66-AA66,"") -> 0.14320225
A67: Lennar | B67: LEN | C67: 2026-05-31 | D67: 7939.872 | E67: 6619.476 | F67: 9367.609 | G67: 8810.278 | H67: 8377.502 | I67: 418.815 | J67: 233.064 | K67: 666.959 | L67: 721.198 | M67: 648.577 | N67: -0.052238722 | O67: -0.35425555 | P67: 0.19947138 | Q67: -0.29336547 | R67: 0.063259184 | S67: 0.051659313 | T67: 최근 QoQ≥10% | U67: 미국 주택건설업체 | V67: Consumer Discretionary | W67: 125.69 | X67: 81.52 | Y67: =IF(AND(ISNUMBER(W67),ISNUMBER(X67)),X67/W67-1,"") -> -0.35142016 | Z67: -0.33836058 | AA67: -0.044274249 | AC67: =IF(AND(ISNUMBER(N67),ISNUMBER(AA67)),N67-AA67,"") -> -0.0079644736
A68: Sherwin-Williams | B68: SHW | C68: 2026-06-30 | D68: 6789.3 | E68: 5666.9 | F68: 5595.9 | G68: 6358.2 | H68: 6314.5 | I68: 1231 | J68: 802.7 | K68: 789.7 | L68: 1153.6 | M68: 1099.1 | N68: 0.075192018 | O68: 0.12000728 | P68: 0.19806243 | Q68: 0.012687861 | R68: -0.11989242 | S68: 0.0069205796 | T68: 최근 QoQ≥10% | U68: 페인트·코팅 제조 및 직영 매장 판매 | V68: Materials | W68: 342.96 | X68: 326.46 | Y68: =IF(AND(ISNUMBER(W68),ISNUMBER(X68)),X68/W68-1,"") -> -0.048110567 | Z68: -0.03908103 | AA68: 0.0068564139 | AB68: 최근 QoQ≥10% | AC68: =IF(AND(ISNUMBER(N68),ISNUMBER(AA68)),N68-AA68,"") -> 0.068335604
A69: Regeneron Pharmaceuticals | B69: REGN | C69: 2026-06-30 | D69: 4290.7 | E69: 3605.4 | F69: 3884.3 | G69: 3754.3 | H69: 3675.6 | I69: 1420.5 | J69: 744.8 | K69: 898.6 | L69: 1109.9 | M69: 1079.5 | N69: 0.16734683 | O69: 0.31588698 | P69: 0.190076 | Q69: -0.071801869 | R69: 0.034626961 | S69: 0.02141147 | T69: 최근 QoQ≥10% | U69: 안과·면역질환 항체의약품 바이오제약 | V69: Health Care | W69: 576.98 | X69: 801.82 | Y69: =IF(AND(ISNUMBER(W69),ISNUMBER(X69)),X69/W69-1,"") -> 0.38968422 | Z69: 0.3968103 | AA69: 0.036226777 | AB69: 최근 QoQ≥10% | AC69: =IF(AND(ISNUMBER(N69),ISNUMBER(AA69)),N69-AA69,"") -> 0.13112005
A70: Rollins, Inc. | B70: ROL | C70: 2026-06-30 | D70: 1078.576 | E70: 906.424 | F70: 912.913 | G70: 1026.106 | H70: 999.527 | I70: 201.359 | J70: 145.486 | K70: 160.066 | L70: 225.021 | M70: 198.333 | N70: 0.079086408 | O70: 0.015257168 | P70: 0.18992436 | Q70: -0.0071080158 | R70: -0.11031316 | S70: 0.026591578 | T70: 최근 QoQ≥10% | U70: 해충방제 서비스 (Orkin) | V70: Industrials | W70: 56.11 | X70: 32.49 | Y70: =IF(AND(ISNUMBER(W70),ISNUMBER(X70)),X70/W70-1,"") -> -0.42095883 | Z70: -0.41254722 | AA70: 0.12064647 | AB70: 최근 QoQ≥10% | AC70: =IF(AND(ISNUMBER(N70),ISNUMBER(AA70)),N70-AA70,"") -> -0.041560063
A71: GE Vernova | B71: GEV | C71: 2026-06-30 | D71: 11104 | E71: 9338 | F71: 10956 | G71: 9969 | H71: 9111 | I71: 655 | J71: 179 | K71: 602 | L71: 367 | M71: 379 | N71: 0.21874657 | O71: 0.72823219 | P71: 0.18911973 | Q71: -0.14768164 | R71: 0.099006921 | S71: 0.09417188 | T71: 최근 QoQ≥10% | U71: 가스터빈·풍력·전력망 장비 (GE에서 분사) | V71: Industrials | W71: 628.97 | X71: 951.82 | Y71: =IF(AND(ISNUMBER(W71),ISNUMBER(X71)),X71/W71-1,"") -> 0.51329952 | Z71: 0.51673576 | AA71: 0.11055583 | AB71: 최근 QoQ≥10% | AC71: =IF(AND(ISNUMBER(N71),ISNUMBER(AA71)),N71-AA71,"") -> 0.10819074
A72: Carrier Global | B72: CARR | C72: 2026-06-30 | D72: 6351 | E72: 5341 | F72: 4837 | G72: 5579 | H72: 6113 | I72: 770 | J72: 240 | K72: 54 | L72: 495 | M72: 795 | N72: 0.038933421 | O72: -0.031446541 | P72: 0.18910316 | Q72: 0.10419682 | R72: -0.13299875 | S72: -0.087354818 | T72: 최근 QoQ≥10% | U72: 냉난방공조(HVAC)·냉장 설비 | V72: Industrials | W72: 58.99 | X72: 55.1 | Y72: =IF(AND(ISNUMBER(W72),ISNUMBER(X72)),X72/W72-1,"") -> -0.06594338 | Z72: -0.051577326 | AA72: 0.03016515 | AB72: 최근 QoQ≥10% | AC72: =IF(AND(ISNUMBER(N72),ISNUMBER(AA72)),N72-AA72,"") -> 0.0087682706
A73: Intel | B73: INTC | C73: 2026-06-30 | D73: 16128 | E73: 13577 | F73: 13674 | G73: 13653 | H73: 12859 | I73: 1966 | J73: 934 | K73: 550 | L73: 858 | M73: -1286 | N73: 0.25421884 | O73: 흑자전환 | P73: 0.18789129 | Q73: -0.0070937546 | R73: 0.0015381235 | S73: 0.061746637 | T73: 최근 QoQ≥10% | U73: PC·서버용 CPU 반도체 및 파운드리 | V73: Information Technology | W73: 31.22 | X73: 122.6 | Y73: =IF(AND(ISNUMBER(W73),ISNUMBER(X73)),X73/W73-1,"") -> 2.9269699 | Z73: 2.9269699 | AA73: 0.0020260267 | AC73: =IF(AND(ISNUMBER(N73),ISNUMBER(AA73)),N73-AA73,"") -> 0.25219281
A74: Palantir Technologies | B74: PLTR | C74: 2026-06-30 | D74: 1935.464 | E74: 1632.583 | F74: 1406.802 | G74: 1181.092 | H74: 1003.697 | I74: 912.004 | J74: 753.998 | K74: 575.394 | L74: 393.256 | M74: 269.317 | N74: 0.92833495 | O74: 2.3863588 | P74: 0.18552257 | Q74: 0.16049238 | R74: 0.19110281 | S74: 0.17674159 | T74: 최근 QoQ≥10% | U74: 정부·기업용 빅데이터 분석 및 AI 소프트웨어 플랫폼 | V74: Information Technology | W74: 179.56 | X74: 191.79 | Y74: =IF(AND(ISNUMBER(W74),ISNUMBER(X74)),X74/W74-1,"") -> 0.068110938 | Z74: 0.068110915 | AA74: 0.48008653 | AB74: 최근 QoQ≥10% | AC74: =IF(AND(ISNUMBER(N74),ISNUMBER(AA74)),N74-AA74,"") -> 0.44824841
A75: Nasdaq, Inc. | B75: NDAQ | C75: 2026-06-30 | D75: 2532 | E75: 2137 | F75: 2124 | G75: 1958 | H75: 2101 | I75: 731 | J75: 672 | K75: 651 | L75: 607 | M75: 597 | N75: 0.20514041 | O75: 0.22445561 | P75: 0.18483856 | Q75: 0.0061205273 | R75: 0.084780388 | S75: -0.068062827 | T75: 최근 QoQ≥10% | U75: 나스닥 거래소 운영 및 금융 소프트웨어·데이터 | V75: Financials | W75: 87.15 | X75: 95.44 | Y75: =IF(AND(ISNUMBER(W75),ISNUMBER(X75)),X75/W75-1,"") -> 0.095123351 | Z75: 0.109577 | AA75: 0.16629464 | AC75: =IF(AND(ISNUMBER(N75),ISNUMBER(AA75)),N75-AA75,"") -> 0.038845766
A76: Amphenol | B76: APH | C76: 2026-03-31 | D76: 7620.1 | E76: 6439 | F76: 6194.4 | G76: 5650.3 | H76: 4811 | I76: 1948.7 | J76: 1770.1 | K76: 1702.3 | L76: 1430.8 | M76: 1068.8 | N76: 0.58389108 | O76: 0.82325973 | P76: 0.1834291 | Q76: 0.039487279 | R76: 0.096295772 | S76: 0.17445438 | T76: 최근 QoQ≥10% | U76: 커넥터·케이블·센서 등 전자 연결 부품 | V76: Information Technology | W76: 61.565 | X76: 82.19 | Y76: =IF(AND(ISNUMBER(W76),ISNUMBER(X76)),X76/W76-1,"") -> 0.33501178 | Z76: 0.34433353 | AA76: 0.56531014 | AB76: 최근 QoQ≥10% | AC76: =IF(AND(ISNUMBER(N76),ISNUMBER(AA76)),N76-AA76,"") -> 0.018580946
A77: Goldman Sachs | B77: GS | C77: 2026-06-30 | D77: 20338 | E77: 17227 | F77: 13454 | G77: 15184 | H77: 14583 | N77: 0.39463759 | P77: 0.18058861 | Q77: 0.28043704 | R77: -0.11393572 | S77: 0.041212371 | T77: 최근 QoQ≥10% | U77: 투자은행·트레이딩·자산운용 | V77: Financials | W77: 792.43 | X77: 936.36 | Y77: =IF(AND(ISNUMBER(W77),ISNUMBER(X77)),X77/W77-1,"") -> 0.18163119 | Z77: 0.20487201 | AA77: 0.14547168 | AC77: =IF(AND(ISNUMBER(N77),ISNUMBER(AA77)),N77-AA77,"") -> 0.24916591
A78: Caterpillar Inc. | B78: CAT | C78: 2026-06-30 | D78: 20543 | E78: 17415 | F78: 19133 | G78: 17638 | H78: 16569 | I78: 4295 | J78: 3085 | K78: 2660 | L78: 3052 | M78: 2860 | N78: 0.23984549 | O78: 0.50174825 | P78: 0.17961527 | Q78: -0.089792505 | R78: 0.084760177 | S78: 0.064518076 | T78: 최근 QoQ≥10% | U78: 건설·광산 장비 및 엔진·발전 터빈 | V78: Industrials | W78: 469.79 | X78: 812.02 | Y78: =IF(AND(ISNUMBER(W78),ISNUMBER(X78)),X78/W78-1,"") -> 0.72847442 | Z78: 0.74403357 | AA78: -0.0071903649 | AB78: 최근 QoQ≥10% | AC78: =IF(AND(ISNUMBER(N78),ISNUMBER(AA78)),N78-AA78,"") -> 0.24703586
A79: Nvidia | B79: NVDA | C79: 2026-07-31 | D79: 96221 | E79: 81615 | F79: 68127 | G79: 57006 | H79: 46743 | I79: 63734 | J79: 53536 | K79: 44299 | L79: 36010 | M79: 28440 | N79: 1.0585114 | O79: 1.2409986 | P79: 0.1789622 | Q79: 0.19798318 | R79: 0.19508473 | S79: 0.21956229 | T79: 최근 QoQ≥10% | U79: AI 가속기(GPU)·데이터센터 플랫폼 및 게이밍 GPU | V79: Information Technology | W79: 176.97 | X79: 225.51 | Y79: =IF(AND(ISNUMBER(W79),ISNUMBER(X79)),X79/W79-1,"") -> 0.27428378 | Z79: 0.27733668 | AA79: 0.5560253 | AC79: =IF(AND(ISNUMBER(N79),ISNUMBER(AA79)),N79-AA79,"") -> 0.50248614
A80: Ferguson Enterprises | B80: FERG | C80: 2026-06-30 | D80: 8751 | E80: 7472 | F80: 8169 | G80: 8497 | H80: 7621 | I80: 895 | J80: 614 | K80: 771 | L80: 932 | M80: 676 | N80: 0.1482745 | O80: 0.3239645 | P80: 0.17117238 | Q80: -0.085322561 | R80: -0.038601859 | S80: 0.11494555 | T80: 최근 QoQ≥10% | U80: 배관·HVAC 자재 유통 | V80: Industrials | W80: 226.44 | X80: 221.17 | Y80: =IF(AND(ISNUMBER(W80),ISNUMBER(X80)),X80/W80-1,"") -> -0.023273273 | Z80: -0.0045573244 | AA80: 0.042829776 | AB80: 최근 QoQ≥10% | AC80: =IF(AND(ISNUMBER(N80),ISNUMBER(AA80)),N80-AA80,"") -> 0.10544473
A81: Steel Dynamics | B81: STLD | C81: 2026-06-30 | D81: 6091.557 | E81: 5204.858 | F81: 4414.048 | G81: 4828.215 | H81: 4565.123 | I81: 757.793 | J81: 580.202 | K81: 337.426 | L81: 550.146 | M81: 413.561 | N81: 0.33436865 | O81: 0.83236089 | P81: 0.17035988 | Q81: 0.17915754 | R81: -0.085780563 | S81: 0.057630868 | T81: 최근 QoQ≥10% | U81: 전기로 제강 및 금속 재활용 (알루미늄 진출) | V81: Materials | W81: 136.37 | X81: 234.29 | Y81: =IF(AND(ISNUMBER(W81),ISNUMBER(X81)),X81/W81-1,"") -> 0.71804649 | Z81: 0.73859592 | AA81: -0.014572919 | AC81: =IF(AND(ISNUMBER(N81),ISNUMBER(AA81)),N81-AA81,"") -> 0.34894157
A82: PulteGroup | B82: PHM | C82: 2026-06-30 | D82: 3982.957 | E82: 3408.572 | F82: 4610.748 | G82: 4404.799 | H82: 4403.755 | I82: 613.143 | J82: 440.36 | K82: 739.912 | L82: 761.31 | M82: 805.452 | N82: -0.095554362 | O82: -0.23875911 | P82: 0.16851192 | Q82: -0.2607334 | R82: 0.046755595 | S82: 0.00023707041 | T82: 최근 QoQ≥10% | U82: 미국 주택건설업체 | V82: Consumer Discretionary | W82: 130.9 | X82: 118.71 | Y82: =IF(AND(ISNUMBER(W82),ISNUMBER(X82)),X82/W82-1,"") -> -0.093124523 | Z82: -0.085387879 | AB82: 최근 QoQ≥10% | AC82: =IF(AND(ISNUMBER(N82),ISNUMBER(AA82)),N82-AA82,"")
A83: Amgen | B83: AMGN | C83: 2026-06-30 | D83: 10054 | E83: 8618 | F83: 9866 | G83: 9557 | H83: 9179 | I83: 3514 | J83: 2666 | K83: 2720 | L83: 2526 | M83: 2656 | N83: 0.095326288 | O83: 0.32304217 | P83: 0.16662799 | Q83: -0.12649503 | R83: 0.032332322 | S83: 0.041180957 | T83: 최근 QoQ≥10% | U83: 항암·골다공증·심혈관 바이오의약품 | V83: Health Care | W83: 279.22 | X83: 406.09 | Y83: =IF(AND(ISNUMBER(W83),ISNUMBER(X83)),X83/W83-1,"") -> 0.4543729 | Z83: 0.49471751 | AA83: 0.094301383 | AB83: 최근 QoQ≥10% | AC83: =IF(AND(ISNUMBER(N83),ISNUMBER(AA83)),N83-AA83,"") -> 0.0010249053
A84: Clorox | B84: CLX | C84: 2026-06-30 | D84: 1948 | E84: 1670 | F84: 1673 | G84: 1429 | H84: 1988 | I84: 246 | J84: 284 | K84: 236 | L84: 120 | M84: 420 | N84: -0.020120724 | O84: -0.41428571 | P84: 0.16646707 | Q84: -0.0017931859 | R84: 0.17074878 | S84: -0.28118712 | T84: 최근 QoQ≥10% | U84: 표백제·세제·생활용품 브랜드 | V84: Consumer Staples | W84: 123.08 | X84: 83.94 | Y84: =IF(AND(ISNUMBER(W84),ISNUMBER(X84)),X84/W84-1,"") -> -0.31800455 | Z84: -0.28621886 | AA84: 0.044666316 | AB84: QoQ 가속 + 최근 QoQ≥10% | AC84: =IF(AND(ISNUMBER(N84),ISNUMBER(AA84)),N84-AA84,"") -> -0.064787041
A85: Seagate Technology | B85: STX | C85: 2026-06-30 | D85: 3629 | E85: 3112 | F85: 2825 | G85: 2629 | H85: 2444 | I85: 1563 | J85: 1110 | K85: 846 | L85: 707 | M85: 581 | N85: 0.48486088 | O85: 1.6901893 | P85: 0.16613111 | Q85: 0.10159292 | R85: 0.074553062 | S85: 0.075695581 | T85: 최근 QoQ≥10% | U85: 하드디스크(HDD) 등 데이터 저장장치 | V85: Information Technology | W85: 223.7 | X85: 923.86 | Y85: =IF(AND(ISNUMBER(W85),ISNUMBER(X85)),X85/W85-1,"") -> 3.1299061 | Z85: 3.164006 | AA85: 0.29517753 | AB85: 최근 QoQ≥10% | AC85: =IF(AND(ISNUMBER(N85),ISNUMBER(AA85)),N85-AA85,"") -> 0.18968335
A86: Old Dominion | B86: ODFL | C86: 2026-06-30 | D86: 1554.004 | E86: 1334.696 | F86: 1307.296 | G86: 1406.511 | H86: 1407.724 | I86: 465.301 | J86: 317.341 | K86: 304.251 | L86: 360.844 | M86: 357.895 | N86: 0.10391241 | O86: 0.30010478 | P86: 0.16431307 | Q86: 0.020959293 | R86: -0.070539797 | S86: -0.00086167459 | T86: 최근 QoQ≥10% | U86: 미국 소량화물(LTL) 트럭 운송 | V86: Industrials | W86: 141.06 | X86: 177.72 | Y86: =IF(AND(ISNUMBER(W86),ISNUMBER(X86)),X86/W86-1,"") -> 0.25988941 | Z86: 0.26771941 | AA86: -0.060701396 | AC86: =IF(AND(ISNUMBER(N86),ISNUMBER(AA86)),N86-AA86,"") -> 0.16461381
A87: Southwest Airlines | B87: LUV | C87: 2026-06-30 | D87: 8432 | E87: 7249 | F87: 7442 | G87: 6949 | H87: 7244 | I87: 285 | J87: 330 | K87: 391 | L87: 35 | M87: 225 | N87: 0.16399779 | O87: 0.26666667 | P87: 0.16319492 | Q87: -0.025933889 | R87: 0.07094546 | S87: -0.040723357 | T87: 최근 QoQ≥10% | U87: 미국 저비용 항공사 | V87: Industrials | W87: 33.06 | X87: 41.04 | Y87: =IF(AND(ISNUMBER(W87),ISNUMBER(X87)),X87/W87-1,"") -> 0.24137931 | Z87: 0.26353378 | AA87: -0.014957846 | AB87: 최근 QoQ≥10% | AC87: =IF(AND(ISNUMBER(N87),ISNUMBER(AA87)),N87-AA87,"") -> 0.17895564
A88: DTE Energy | B88: DTE | C88: 2026-03-31 | D88: 5141 | E88: 4428 | F88: 3527 | G88: 3419 | H88: 4440 | I88: 414 | J88: 810 | K88: 669 | L88: 448 | M88: 623 | N88: 0.15788288 | O88: -0.33547352 | P88: 0.16102078 | Q88: 0.2554579 | R88: 0.031588184 | S88: -0.22995495 | T88: 최근 QoQ≥10% | U88: 미시간주 전력·가스 유틸리티 | V88: Utilities | W88: 138.76 | X88: 122.89 | Y88: =IF(AND(ISNUMBER(W88),ISNUMBER(X88)),X88/W88-1,"") -> -0.11437014 | Z88: -0.083861974 | AA88: 0.18921739 | AC88: =IF(AND(ISNUMBER(N88),ISNUMBER(AA88)),N88-AA88,"") -> -0.031334508
A89: Lilly (Eli) | B89: LLY | C89: 2026-06-30 | D89: 22974 | E89: 19799 | F89: 19292 | G89: 17600.8 | H89: 15558 | I89: 12457 | J89: 9778 | K89: 8987.4 | L89: 8386.1 | M89: 7021 | N89: 0.47666795 | O89: 0.77424868 | P89: 0.16036163 | Q89: 0.026280323 | R89: 0.096086542 | S89: 0.13130222 | T89: 최근 QoQ≥10% | U89: 비만·당뇨 치료제(GLP-1) 등 전문의약품 | V89: Health Care | W89: 741.85 | X89: 1150.99 | Y89: =IF(AND(ISNUMBER(W89),ISNUMBER(X89)),X89/W89-1,"") -> 0.55151311 | Z89: 0.56129831 | AA89: 0.37644654 | AB89: 최근 QoQ≥10% | AC89: =IF(AND(ISNUMBER(N89),ISNUMBER(AA89)),N89-AA89,"") -> 0.10022141
A90: Norfolk Southern | B90: NSC | C90: 2026-06-30 | D90: 3465 | E90: 2998 | F90: 2974 | G90: 3103 | H90: 3110 | I90: 1266 | J90: 992 | K90: 1158 | L90: 1189 | M90: 1231 | N90: 0.11414791 | O90: 0.028432169 | P90: 0.15577051 | Q90: 0.0080699395 | R90: -0.041572672 | S90: -0.0022508039 | T90: 최근 QoQ≥10% | U90: 미국 동부 화물 철도 | V90: Industrials | W90: 293.32 | X90: 315.01 | Y90: =IF(AND(ISNUMBER(W90),ISNUMBER(X90)),X90/W90-1,"") -> 0.073946543 | Z90: 0.0928758 | AA90: 0.021681997 | AC90: =IF(AND(ISNUMBER(N90),ISNUMBER(AA90)),N90-AA90,"") -> 0.092465913
A91: Motorola Solutions | B91: MSI | C91: 2026-06-30 | D91: 3133 | E91: 2714 | F91: 3380 | G91: 3009 | H91: 2765 | I91: 827 | J91: 581 | K91: 905 | L91: 766 | M91: 693 | N91: 0.13309222 | O91: 0.19336219 | P91: 0.15438467 | Q91: -0.19704142 | R91: 0.12329678 | S91: 0.088245931 | T91: 최근 QoQ≥10% | U91: 공공안전 무선통신·영상보안 솔루션 | V91: Information Technology | W91: 455.13 | X91: 460.44 | Y91: =IF(AND(ISNUMBER(W91),ISNUMBER(X91)),X91/W91-1,"") -> 0.011666996 | Z91: 0.023406344 | AA91: 0.052130898 | AC91: =IF(AND(ISNUMBER(N91),ISNUMBER(AA91)),N91-AA91,"") -> 0.080961326
A92: Garmin | B92: GRMN | C92: 2026-06-30 | D92: 2022.092 | E92: 1753.489 | F92: 2124.955 | G92: 1770.901 | H92: 1814.564 | I92: 615.508 | J92: 431.665 | K92: 614.154 | L92: 456.803 | M92: 472.295 | N92: 0.11436797 | O92: 0.30322786 | P92: 0.15318203 | Q92: -0.17481123 | R92: 0.19992874 | S92: -0.02406253 | T92: 최근 QoQ≥10% | U92: GPS 기반 웨어러블·항공·해양·차량용 기기 | V92: Consumer Discretionary | W92: 236.44 | X92: 287.58 | Y92: =IF(AND(ISNUMBER(W92),ISNUMBER(X92)),X92/W92-1,"") -> 0.21629166 | Z92: 0.23638904 | AA92: 0.20435317 | AB92: 최근 QoQ≥10% | AC92: =IF(AND(ISNUMBER(N92),ISNUMBER(AA92)),N92-AA92,"") -> -0.089985204
A93: Lam Research | B93: LRCX | C93: 2026-06-30 | D93: 6722.238 | E93: 5841.488 | F93: 5344.791 | G93: 5324.173 | H93: 5171.393 | I93: 2513.488 | J93: 2047.016 | K93: 1810.203 | L93: 1829.088 | M93: 1741.128 | N93: 0.29988922 | O93: 0.44359748 | P93: 0.15077494 | Q93: 0.092931043 | R93: 0.0038725263 | S93: 0.029543297 | T93: 최근 QoQ≥10% | U93: 반도체 식각·증착 장비 | V93: Information Technology | W93: 128.32 | X93: 307.28 | Y93: =IF(AND(ISNUMBER(W93),ISNUMBER(X93)),X93/W93-1,"") -> 1.3946384 | Z93: 1.4056989 | AA93: 0.33575711 | AC93: =IF(AND(ISNUMBER(N93),ISNUMBER(AA93)),N93-AA93,"") -> -0.035867892
A94: Fifth Third Bancorp | B94: FITB | C94: 2026-06-30 | D94: 3209 | E94: 2795 | F94: 2209 | G94: 2279 | H94: 2223 | N94: 0.44354476 | P94: 0.14812165 | Q94: 0.26527841 | R94: -0.030715226 | S94: 0.025191183 | T94: 최근 QoQ≥10% | U94: 미국 중서부·남동부 지역은행 | V94: Financials | W94: 45.17 | X94: 51.69 | Y94: =IF(AND(ISNUMBER(W94),ISNUMBER(X94)),X94/W94-1,"") -> 0.14434359 | Z94: 0.18316705 | AA94: 0.078290106 | AC94: =IF(AND(ISNUMBER(N94),ISNUMBER(AA94)),N94-AA94,"") -> 0.36525465
A95: Carvana | B95: CVNA | C95: 2026-06-30 | D95: 7376 | E95: 6432 | F95: 5603 | G95: 5647 | H95: 4840 | I95: 680 | J95: 581 | K95: 424 | L95: 552 | M95: 511 | N95: 0.52396694 | O95: 0.33072407 | P95: 0.14676617 | Q95: 0.14795645 | R95: -0.0077917478 | S95: 0.16673554 | T95: 최근 QoQ≥10% | U95: 온라인 중고차 매매 플랫폼 | V95: Consumer Discretionary | W95: 74.962 | X95: 63.95 | Y95: =IF(AND(ISNUMBER(W95),ISNUMBER(X95)),X95/W95-1,"") -> -0.1469011 | Z95: -0.14690106 | AA95: 0.41935484 | AB95: 최근 QoQ≥10% | AC95: =IF(AND(ISNUMBER(N95),ISNUMBER(AA95)),N95-AA95,"") -> 0.1046121
A96: PPG Industries | B96: PPG | C96: 2026-06-30 | D96: 4495 | E96: 3930 | F96: 3914 | G96: 4082 | H96: 4195 | I96: 636 | J96: 525 | K96: 450 | L96: 588 | M96: 650 | N96: 0.071513707 | O96: -0.021538462 | P96: 0.1437659 | Q96: 0.0040878896 | R96: -0.041156296 | S96: -0.02693683 | T96: 최근 QoQ≥10% | U96: 페인트·코팅 및 특수소재 | V96: Materials | W96: 105.48 | X96: 107.2 | Y96: =IF(AND(ISNUMBER(W96),ISNUMBER(X96)),X96/W96-1,"") -> 0.016306409 | Z96: 0.042903199 | AA96: -0.0094451004 | AB96: 최근 QoQ≥10% | AC96: =IF(AND(ISNUMBER(N96),ISNUMBER(AA96)),N96-AA96,"") -> 0.080958807
A97: Hewlett Packard Enterprise | B97: HPE | C97: 2026-07-31 | D97: 12213 | E97: 10678 | F97: 9301 | G97: 9679 | H97: 9136 | I97: 1464 | J97: 825 | K97: 587 | L97: 408 | M97: 428 | N97: 0.33679947 | O97: 2.4205607 | P97: 0.14375351 | Q97: 0.1480486 | R97: -0.039053621 | S97: 0.059435201 | T97: 최근 QoQ≥10% | U97: 서버·스토리지·네트워크(주니퍼) 기업 IT 인프라 | V97: Information Technology | W97: 24.46 | X97: 62.33 | Y97: =IF(AND(ISNUMBER(W97),ISNUMBER(X97)),X97/W97-1,"") -> 1.548242 | Z97: 1.5941917 | AA97: 0.1849546 | AB97: 최근 QoQ≥10% | AC97: =IF(AND(ISNUMBER(N97),ISNUMBER(AA97)),N97-AA97,"") -> 0.15184487
A98: J.B. Hunt | B98: JBHT | C98: 2026-06-30 | D98: 3495.296 | E98: 3056.491 | F98: 3096.626 | G98: 3052.897 | H98: 2928.181 | I98: 259.452 | J98: 207.048 | K98: 246.457 | L98: 242.657 | M98: 197.274 | N98: 0.19367484 | O98: 0.31518598 | P98: 0.14356496 | Q98: -0.012960881 | R98: 0.014323772 | S98: 0.042591629 | T98: 최근 QoQ≥10% | U98: 트럭·철도 복합운송 및 전용 물류 | V98: Industrials | W98: 132.87 | X98: 234.63 | Y98: =IF(AND(ISNUMBER(W98),ISNUMBER(X98)),X98/W98-1,"") -> 0.76586137 | Z98: 0.78031434 | AA98: -0.00017209089 | AC98: =IF(AND(ISNUMBER(N98),ISNUMBER(AA98)),N98-AA98,"") -> 0.19384694
A99: Comfort Systems USA | B99: FIX | C99: 2026-06-30 | D99: 3265.656 | E99: 2865.332 | F99: 2646.067 | G99: 2450.969 | H99: 2173.319 | I99: 557.181 | J99: 485.416 | K99: 426.35 | L99: 378.292 | M99: 299.431 | N99: 0.50261236 | O99: 0.86079932 | P99: 0.13971295 | Q99: 0.082864493 | R99: 0.079600354 | S99: 0.12775391 | T99: 최근 QoQ≥10% | U99: 기계·전기 설비(HVAC) 시공 및 유지보수 | V99: Industrials | W99: 791.46 | X99: 1625.9 | Y99: =IF(AND(ISNUMBER(W99),ISNUMBER(X99)),X99/W99-1,"") -> 1.0543047 | Z99: 1.0585115 | AA99: 0.20053638 | AB99: 최근 QoQ≥10% | AC99: =IF(AND(ISNUMBER(N99),ISNUMBER(AA99)),N99-AA99,"") -> 0.30207599
A100: Hasbro | B100: HAS | C100: 2026-06-30 | D100: 1139.6 | E100: 1000.2 | F100: 1445.9 | G100: 1387.5 | H100: 980.8 | I100: 252.5 | J100: 270.3 | K100: 297.5 | L100: 341.1 | M100: 223.7 | N100: 0.16190865 | O100: 0.12874385 | P100: 0.13937213 | Q100: -0.30825092 | R100: 0.04209009 | S100: 0.4146615 | T100: 최근 QoQ≥10% | U100: 완구·보드게임 및 디지털 게임(Wizards of the Coast) | V100: Consumer Discretionary | W100: 75.23 | X100: 86.52 | Y100: =IF(AND(ISNUMBER(W100),ISNUMBER(X100)),X100/W100-1,"") -> 0.15007311 | Z100: 0.18717524 | AA100: -0.0072666783 | AB100: 최근 QoQ≥10% | AC100: =IF(AND(ISNUMBER(N100),ISNUMBER(AA100)),N100-AA100,"") -> 0.16917532
...

Sheet 수익률 분석
A1: S&P 500 최근 1년 주가수익률 분석 (2025-09-24 종가 → 2026-09-23 종가)
A3: 항목 | B3: 값 | C3: 설명
A4: 수익률 계산 종목 수 | B4: =COUNT(실적!$Y$2:$Y$504) -> 500 | C4: 시작일 이전 상장 종목 (이후 상장·분사 종목 제외)
A5: S&P 500 지수 수익률 (^GSPC) | B5: 0.16090153 | C5: 지수 종가 6,637.97 → 7,706.03 (Yahoo)
A6: 종목 수익률 평균 (동일가중) | B6: =AVERAGE(실적!$Y$2:$Y$504) -> 0.20442869
A7: 종목 수익률 중앙값 | B7: =MEDIAN(실적!$Y$2:$Y$504) -> 0.057288509
A8: 상승 종목 비율 | B8: =COUNTIF(실적!$Y$2:$Y$504,">0")/COUNT(실적!$Y$2:$Y$504) -> 0.57
A9: +50% 이상 종목 수 | B9: =COUNTIF(실적!$Y$2:$Y$504,">=0.5") -> 60
A10: +100% 이상 종목 수 | B10: =COUNTIF(실적!$Y$2:$Y$504,">=1") -> 24
A13: 섹터별 수익률
A14: GICS 섹터 | B14: 종목 수 | C14: 평균 수익률 | D14: 중앙값 수익률 | E14: +50% 이상 종목 수 | F14: +50% 이상 비율 | G14: 중앙값 매출 YoY(현재)
A15: Communication Services | B15: =COUNTIFS(실적!$V$2:$V$504,A15,실적!$Y$2:$Y$504,">-100") -> 23 | C15: =IFERROR(AVERAGEIFS(실적!$Y$2:$Y$504,실적!$V$2:$V$504,A15),"") -> -0.071589283 | D15: {=IFERROR(MEDIAN(IF((실적!$V$2:$V$504=A15)*ISNUMBER(실적!$Y$2:$Y$504),실적!$Y$2:$Y$504)),"")} -> -0.069798214 | E15: =COUNTIFS(실적!$V$2:$V$504,A15,실적!$Y$2:$Y$504,">=0.5") -> 1 | F15: =IFERROR(E15/B15,"") -> 0.043478261 | G15: {=IFERROR(MEDIAN(IF((실적!$V$2:$V$504=A15)*ISNUMBER(실적!$N$2:$N$504),실적!$N$2:$N$504)),"")} -> 0.10810811
A16: Consumer Discretionary | B16: =COUNTIFS(실적!$V$2:$V$504,A16,실적!$Y$2:$Y$504,">-100") -> 47 | C16: =IFERROR(AVERAGEIFS(실적!$Y$2:$Y$504,실적!$V$2:$V$504,A16),"") -> -0.082986304 | D16: {=IFERROR(MEDIAN(IF((실적!$V$2:$V$504=A16)*ISNUMBER(실적!$Y$2:$Y$504),실적!$Y$2:$Y$504)),"")} -> -0.14153436 | E16: =COUNTIFS(실적!$V$2:$V$504,A16,실적!$Y$2:$Y$504,">=0.5") -> 1 | F16: =IFERROR(E16/B16,"") -> 0.021276596 | G16: {=IFERROR(MEDIAN(IF((실적!$V$2:$V$504=A16)*ISNUMBER(실적!$N$2:$N$504),실적!$N$2:$N$504)),"")} -> 0.064786249
A17: Consumer Staples | B17: =COUNTIFS(실적!$V$2:$V$504,A17,실적!$Y$2:$Y$504,">-100") -> 33 | C17: =IFERROR(AVERAGEIFS(실적!$Y$2:$Y$504,실적!$V$2:$V$504,A17),"") -> 0.045557698 | D17: {=IFERROR(MEDIAN(IF((실적!$V$2:$V$504=A17)*ISNUMBER(실적!$Y$2:$Y$504),실적!$Y$2:$Y$504)),"")} -> 0.048042705 | E17: =COUNTIFS(실적!$V$2:$V$504,A17,실적!$Y$2:$Y$504,">=0.5") -> 1 | F17: =IFERROR(E17/B17,"") -> 0.03030303 | G17: {=IFERROR(MEDIAN(IF((실적!$V$2:$V$504=A17)*ISNUMBER(실적!$N$2:$N$504),실적!$N$2:$N$504)),"")} -> 0.052447501
A18: Energy | B18: =COUNTIFS(실적!$V$2:$V$504,A18,실적!$Y$2:$Y$504,">-100") -> 21 | C18: =IFERROR(AVERAGEIFS(실적!$Y$2:$Y$504,실적!$V$2:$V$504,A18),"") -> 0.38243912 | D18: {=IFERROR(MEDIAN(IF((실적!$V$2:$V$504=A18)*ISNUMBER(실적!$Y$2:$Y$504),실적!$Y$2:$Y$504)),"")} -> 0.29105415 | E18: =COUNTIFS(실적!$V$2:$V$504,A18,실적!$Y$2:$Y$504,">=0.5") -> 5 | F18: =IFERROR(E18/B18,"") -> 0.23809524 | G18: {=IFERROR(MEDIAN(IF((실적!$V$2:$V$504=A18)*ISNUMBER(실적!$N$2:$N$504),실적!$N$2:$N$504)),"")} -> 0.36825193
A19: Financials | B19: =COUNTIFS(실적!$V$2:$V$504,A19,실적!$Y$2:$Y$504,">-100") -> 76 | C19: =IFERROR(AVERAGEIFS(실적!$Y$2:$Y$504,실적!$V$2:$V$504,A19),"") -> 0.023087653 | D19: {=IFERROR(MEDIAN(IF((실적!$V$2:$V$504=A19)*ISNUMBER(실적!$Y$2:$Y$504),실적!$Y$2:$Y$504)),"")} -> 0.023124488 | E19: =COUNTIFS(실적!$V$2:$V$504,A19,실적!$Y$2:$Y$504,">=0.5") -> 1 | F19: =IFERROR(E19/B19,"") -> 0.013157895 | G19: {=IFERROR(MEDIAN(IF((실적!$V$2:$V$504=A19)*ISNUMBER(실적!$N$2:$N$504),실적!$N$2:$N$504)),"")} -> 0.10690975
A20: Health Care | B20: =COUNTIFS(실적!$V$2:$V$504,A20,실적!$Y$2:$Y$504,">-100") -> 60 | C20: =IFERROR(AVERAGEIFS(실적!$Y$2:$Y$504,실적!$V$2:$V$504,A20),"") -> 0.3226184 | D20: {=IFERROR(MEDIAN(IF((실적!$V$2:$V$504=A20)*ISNUMBER(실적!$Y$2:$Y$504),실적!$Y$2:$Y$504)),"")} -> 0.22579523 | E20: =COUNTIFS(실적!$V$2:$V$504,A20,실적!$Y$2:$Y$504,">=0.5") -> 10 | F20: =IFERROR(E20/B20,"") -> 0.16666667 | G20: {=IFERROR(MEDIAN(IF((실적!$V$2:$V$504=A20)*ISNUMBER(실적!$N$2:$N$504),실적!$N$2:$N$504)),"")} -> 0.072816706
A21: Industrials | B21: =COUNTIFS(실적!$V$2:$V$504,A21,실적!$Y$2:$Y$504,">-100") -> 81 | C21: =IFERROR(AVERAGEIFS(실적!$Y$2:$Y$504,실적!$V$2:$V$504,A21),"") -> 0.14173537 | D21: {=IFERROR(MEDIAN(IF((실적!$V$2:$V$504=A21)*ISNUMBER(실적!$Y$2:$Y$504),실적!$Y$2:$Y$504)),"")} -> 0.090670751 | E21: =COUNTIFS(실적!$V$2:$V$504,A21,실적!$Y$2:$Y$504,">=0.5") -> 11 | F21: =IFERROR(E21/B21,"") -> 0.13580247 | G21: {=IFERROR(MEDIAN(IF((실적!$V$2:$V$504=A21)*ISNUMBER(실적!$N$2:$N$504),실적!$N$2:$N$504)),"")} -> 0.10100727
A22: Information Technology | B22: =COUNTIFS(실적!$V$2:$V$504,A22,실적!$Y$2:$Y$504,">-100") -> 73 | C22: =IFERROR(AVERAGEIFS(실적!$Y$2:$Y$504,실적!$V$2:$V$504,A22),"") -> 0.88351517 | D22: {=IFERROR(MEDIAN(IF((실적!$V$2:$V$504=A22)*ISNUMBER(실적!$Y$2:$Y$504),실적!$Y$2:$Y$504)),"")} -> 0.27428378 | E22: =COUNTIFS(실적!$V$2:$V$504,A22,실적!$Y$2:$Y$504,">=0.5") -> 27 | F22: =IFERROR(E22/B22,"") -> 0.36986301 | G22: {=IFERROR(MEDIAN(IF((실적!$V$2:$V$504=A22)*ISNUMBER(실적!$N$2:$N$504),실적!$N$2:$N$504)),"")} -> 0.22477998
A23: Materials | B23: =COUNTIFS(실적!$V$2:$V$504,A23,실적!$Y$2:$Y$504,">-100") -> 25 | C23: =IFERROR(AVERAGEIFS(실적!$Y$2:$Y$504,실적!$V$2:$V$504,A23),"") -> 0.16038251 | D23: {=IFERROR(MEDIAN(IF((실적!$V$2:$V$504=A23)*ISNUMBER(실적!$Y$2:$Y$504),실적!$Y$2:$Y$504)),"")} -> 0.074913295 | E23: =COUNTIFS(실적!$V$2:$V$504,A23,실적!$Y$2:$Y$504,">=0.5") -> 3 | F23: =IFERROR(E23/B23,"") -> 0.12 | G23: {=IFERROR(MEDIAN(IF((실적!$V$2:$V$504=A23)*ISNUMBER(실적!$N$2:$N$504),실적!$N$2:$N$504)),"")} -> 0.1091646
A24: Real Estate | B24: =COUNTIFS(실적!$V$2:$V$504,A24,실적!$Y$2:$Y$504,">-100") -> 30 | C24: =IFERROR(AVERAGEIFS(실적!$Y$2:$Y$504,실적!$V$2:$V$504,A24),"") -> -0.027859196 | D24: {=IFERROR(MEDIAN(IF((실적!$V$2:$V$504=A24)*ISNUMBER(실적!$Y$2:$Y$504),실적!$Y$2:$Y$504)),"")} -> -0.043570897 | E24: =COUNTIFS(실적!$V$2:$V$504,A24,실적!$Y$2:$Y$504,">=0.5") -> 0 | F24: =IFERROR(E24/B24,"") -> 0 | G24: {=IFERROR(MEDIAN(IF((실적!$V$2:$V$504=A24)*ISNUMBER(실적!$N$2:$N$504),실적!$N$2:$N$504)),"")} -> 0.057094835
A25: Utilities | B25: =COUNTIFS(실적!$V$2:$V$504,A25,실적!$Y$2:$Y$504,">-100") -> 31 | C25: =IFERROR(AVERAGEIFS(실적!$Y$2:$Y$504,실적!$V$2:$V$504,A25),"") -> -0.065680422 | D25: {=IFERROR(MEDIAN(IF((실적!$V$2:$V$504=A25)*ISNUMBER(실적!$Y$2:$Y$504),실적!$Y$2:$Y$504)),"")} -> -0.063140853 | E25: =COUNTIFS(실적!$V$2:$V$504,A25,실적!$Y$2:$Y$504,">=0.5") -> 0 | F25: =IFERROR(E25/B25,"") -> 0 | G25: {=IFERROR(MEDIAN(IF((실적!$V$2:$V$504=A25)*ISNUMBER(실적!$N$2:$N$504),실적!$N$2:$N$504)),"")} -> 0.04964539
A26: ※ 섹터 행은 필터로 정렬 가능. 평균은 극단값 영향이 크므로 중앙값을 함께 볼 것
A28: 수익률 5분위별 특징 (1분위 = 수익률 상위 20%)
A29: 분위 | B29: 수익률 하한 | C29: 수익률 상한 | D29: 종목 수 | E29: 중앙값 수익률 | F29: 중앙값 매출 YoY(현재) | G29: 중앙값 영업이익 YoY(현재) | H29: 중앙값 최근 매출 QoQ(현재) | I29: 현재 선정(①②) 비율 | J29: 중앙값 매출 YoY(2025-09-24) | K29: 2025-09-24 선정(①②) 비율 | L29: 중앙값 매출 YoY 변화(%p)
A30: 1분위 | B30: =PERCENTILE(실적!$Y$2:$Y$504,0.8) -> 0.35182857 | C30: =PERCENTILE(실적!$Y$2:$Y$504,1) -> 17.196633 | D30: =COUNTIFS(실적!$Y$2:$Y$504,">="&B30,실적!$Y$2:$Y$504,"<="&C30) -> 100 | E30: {=IFERROR(MEDIAN(IF((ISNUMBER(실적!$Y$2:$Y$504)*(실적!$Y$2:$Y$504>=B30)*(실적!$Y$2:$Y$504<=C30))*ISNUMBER(실적!$Y$2:$Y$504),실적!$Y$2:$Y$504)),"")} -> 0.5600203 | F30: {=IFERROR(MEDIAN(IF((ISNUMBER(실적!$Y$2:$Y$504)*(실적!$Y$2:$Y$504>=B30)*(실적!$Y$2:$Y$504<=C30))*ISNUMBER(실적!$N$2:$N$504),실적!$N$2:$N$504)),"")} -> 0.190212 | G30: {=IFERROR(MEDIAN(IF((ISNUMBER(실적!$Y$2:$Y$504)*(실적!$Y$2:$Y$504>=B30)*(실적!$Y$2:$Y$504<=C30))*ISNUMBER(실적!$O$2:$O$504),실적!$O$2:$O$504)),"")} -> 0.32304217 | H30: {=IFERROR(MEDIAN(IF((ISNUMBER(실적!$Y$2:$Y$504)*(실적!$Y$2:$Y$504>=B30)*(실적!$Y$2:$Y$504<=C30))*ISNUMBER(실적!$P$2:$P$504),실적!$P$2:$P$504)),"")} -> 0.09730151 | I30: {=IFERROR(SUM((ISNUMBER(실적!$Y$2:$Y$504)*(실적!$Y$2:$Y$504>=B30)*(실적!$Y$2:$Y$504<=C30))*(실적!$T$2:$T$504<>""))/D30,"")} -> 0.56 | J30: {=IFERROR(MEDIAN(IF((ISNUMBER(실적!$Y$2:$Y$504)*(실적!$Y$2:$Y$504>=B30)*(실적!$Y$2:$Y$504<=C30))*ISNUMBER(실적!$AA$2:$AA$504),실적!$AA$2:$AA$504)),"")} -> 0.075575429 | K30: {=IFERROR(SUM((ISNUMBER(실적!$Y$2:$Y$504)*(실적!$Y$2:$Y$504>=B30)*(실적!$Y$2:$Y$504<=C30))*(실적!$AB$2:$AB$504<>""))/D30,"")} -> 0.28 | L30: {=IFERROR(MEDIAN(IF((ISNUMBER(실적!$Y$2:$Y$504)*(실적!$Y$2:$Y$504>=B30)*(실적!$Y$2:$Y$504<=C30))*ISNUMBER(실적!$AC$2:$AC$504),실적!$AC$2:$AC$504)),"")} -> 0.10526819
A31: 2분위 | B31: =PERCENTILE(실적!$Y$2:$Y$504,0.6) -> 0.12062516 | C31: =PERCENTILE(실적!$Y$2:$Y$504,0.8) -> 0.35182857 | D31: =COUNTIFS(실적!$Y$2:$Y$504,">="&B31,실적!$Y$2:$Y$504,"<"&C31) -> 100 | E31: {=IFERROR(MEDIAN(IF((ISNUMBER(실적!$Y$2:$Y$504)*(실적!$Y$2:$Y$504>=B31)*(실적!$Y$2:$Y$504<C31))*ISNUMBER(실적!$Y$2:$Y$504),실적!$Y$2:$Y$504)),"")} -> 0.2063321 | F31: {=IFERROR(MEDIAN(IF((ISNUMBER(실적!$Y$2:$Y$504)*(실적!$Y$2:$Y$504>=B31)*(실적!$Y$2:$Y$504<C31))*ISNUMBER(실적!$N$2:$N$504),실적!$N$2:$N$504)),"")} -> 0.10488887 | G31: {=IFERROR(MEDIAN(IF((ISNUMBER(실적!$Y$2:$Y$504)*(실적!$Y$2:$Y$504>=B31)*(실적!$Y$2:$Y$504<C31))*ISNUMBER(실적!$O$2:$O$504),실적!$O$2:$O$504)),"")} -> 0.23228676 | H31: {=IFERROR(MEDIAN(IF((ISNUMBER(실적!$Y$2:$Y$504)*(실적!$Y$2:$Y$504>=B31)*(실적!$Y$2:$Y$504<C31))*ISNUMBER(실적!$P$2:$P$504),실적!$P$2:$P$504)),"")} -> 0.070487467 | I31: {=IFERROR(SUM((ISNUMBER(실적!$Y$2:$Y$504)*(실적!$Y$2:$Y$504>=B31)*(실적!$Y$2:$Y$504<C31))*(실적!$T$2:$T$504<>""))/D31,"")} -> 0.4 | J31: {=IFERROR(MEDIAN(IF((ISNUMBER(실적!$Y$2:$Y$504)*(실적!$Y$2:$Y$504>=B31)*(실적!$Y$2:$Y$504<C31))*ISNUMBER(실적!$AA$2:$AA$504),실적!$AA$2:$AA$504)),"")} -> 0.061448241 | K31: {=IFERROR(SUM((ISNUMBER(실적!$Y$2:$Y$504)*(실적!$Y$2:$Y$504>=B31)*(실적!$Y$2:$Y$504<C31))*(실적!$AB$2:$AB$504<>""))/D31,"")} -> 0.23 | L31: {=IFERROR(MEDIAN(IF((ISNUMBER(실적!$Y$2:$Y$504)*(실적!$Y$2:$Y$504>=B31)*(실적!$Y$2:$Y$504<C31))*ISNUMBER(실적!$AC$2:$AC$504),실적!$AC$2:$AC$504)),"")} -> 0.046424762
A32: 3분위 | B32: =PERCENTILE(실적!$Y$2:$Y$504,0.4) -> -0.02499773 | C32: =PERCENTILE(실적!$Y$2:$Y$504,0.6) -> 0.12062516 | D32: =COUNTIFS(실적!$Y$2:$Y$504,">="&B32,실적!$Y$2:$Y$504,"<"&C32) -> 100 | E32: {=IFERROR(MEDIAN(IF((ISNUMBER(실적!$Y$2:$Y$504)*(실적!$Y$2:$Y$504>=B32)*(실적!$Y$2:$Y$504<C32))*ISNUMBER(실적!$Y$2:$Y$504),실적!$Y$2:$Y$504)),"")} -> 0.057288509 | F32: {=IFERROR(MEDIAN(IF((ISNUMBER(실적!$Y$2:$Y$504)*(실적!$Y$2:$Y$504>=B32)*(실적!$Y$2:$Y$504<C32))*ISNUMBER(실적!$N$2:$N$504),실적!$N$2:$N$504)),"")} -> 0.094227319 | G32: {=IFERROR(MEDIAN(IF((ISNUMBER(실적!$Y$2:$Y$504)*(실적!$Y$2:$Y$504>=B32)*(실적!$Y$2:$Y$504<C32))*ISNUMBER(실적!$O$2:$O$504),실적!$O$2:$O$504)),"")} -> 0.11423805 | H32: {=IFERROR(MEDIAN(IF((ISNUMBER(실적!$Y$2:$Y$504)*(실적!$Y$2:$Y$504>=B32)*(실적!$Y$2:$Y$504<C32))*ISNUMBER(실적!$P$2:$P$504),실적!$P$2:$P$504)),"")} -> 0.054581873 | I32: {=IFERROR(SUM((ISNUMBER(실적!$Y$2:$Y$504)*(실적!$Y$2:$Y$504>=B32)*(실적!$Y$2:$Y$504<C32))*(실적!$T$2:$T$504<>""))/D32,"")} -> 0.23 | J32: {=IFERROR(MEDIAN(IF((ISNUMBER(실적!$Y$2:$Y$504)*(실적!$Y$2:$Y$504>=B32)*(실적!$Y$2:$Y$504<C32))*ISNUMBER(실적!$AA$2:$AA$504),실적!$AA$2:$AA$504)),"")} -> 0.058899509 | K32: {=IFERROR(SUM((ISNUMBER(실적!$Y$2:$Y$504)*(실적!$Y$2:$Y$504>=B32)*(실적!$Y$2:$Y$504<C32))*(실적!$AB$2:$AB$504<>""))/D32,"")} -> 0.19 | L32: {=IFERROR(MEDIAN(IF((ISNUMBER(실적!$Y$2:$Y$504)*(실적!$Y$2:$Y$504>=B32)*(실적!$Y$2:$Y$504<C32))*ISNUMBER(실적!$AC$2:$AC$504),실적!$AC$2:$AC$504)),"")} -> 0.029301896
A33: 4분위 | B33: =PERCENTILE(실적!$Y$2:$Y$504,0.2) -> -0.15350808 | C33: =PERCENTILE(실적!$Y$2:$Y$504,0.4) -> -0.02499773 | D33: =COUNTIFS(실적!$Y$2:$Y$504,">="&B33,실적!$Y$2:$Y$504,"<"&C33) -> 100 | E33: {=IFERROR(MEDIAN(IF((ISNUMBER(실적!$Y$2:$Y$504)*(실적!$Y$2:$Y$504>=B33)*(실적!$Y$2:$Y$504<C33))*ISNUMBER(실적!$Y$2:$Y$504),실적!$Y$2:$Y$504)),"")} -> -0.080935444 | F33: {=IFERROR(MEDIAN(IF((ISNUMBER(실적!$Y$2:$Y$504)*(실적!$Y$2:$Y$504>=B33)*(실적!$Y$2:$Y$504<C33))*ISNUMBER(실적!$N$2:$N$504),실적!$N$2:$N$504)),"")} -> 0.066305667 | G33: {=IFERROR(MEDIAN(IF((ISNUMBER(실적!$Y$2:$Y$504)*(실적!$Y$2:$Y$504>=B33)*(실적!$Y$2:$Y$504<C33))*ISNUMBER(실적!$O$2:$O$504),실적!$O$2:$O$504)),"")} -> 0.10473791 | H33: {=IFERROR(MEDIAN(IF((ISNUMBER(실적!$Y$2:$Y$504)*(실적!$Y$2:$Y$504>=B33)*(실적!$Y$2:$Y$504<C33))*ISNUMBER(실적!$P$2:$P$504),실적!$P$2:$P$504)),"")} -> 0.03366442 | I33: {=IFERROR(SUM((ISNUMBER(실적!$Y$2:$Y$504)*(실적!$Y$2:$Y$504>=B33)*(실적!$Y$2:$Y$504<C33))*(실적!$T$2:$T$504<>""))/D33,"")} -> 0.21 | J33: {=IFERROR(MEDIAN(IF((ISNUMBER(실적!$Y$2:$Y$504)*(실적!$Y$2:$Y$504>=B33)*(실적!$Y$2:$Y$504<C33))*ISNUMBER(실적!$AA$2:$AA$504),실적!$AA$2:$AA$504)),"")} -> 0.075135925 | K33: {=IFERROR(SUM((ISNUMBER(실적!$Y$2:$Y$504)*(실적!$Y$2:$Y$504>=B33)*(실적!$Y$2:$Y$504<C33))*(실적!$AB$2:$AB$504<>""))/D33,"")} -> 0.21 | L33: {=IFERROR(MEDIAN(IF((ISNUMBER(실적!$Y$2:$Y$504)*(실적!$Y$2:$Y$504>=B33)*(실적!$Y$2:$Y$504<C33))*ISNUMBER(실적!$AC$2:$AC$504),실적!$AC$2:$AC$504)),"")} -> 0.005527118
A34: 5분위 | B34: =PERCENTILE(실적!$Y$2:$Y$504,0) -> -0.66377156 | C34: =PERCENTILE(실적!$Y$2:$Y$504,0.2) -> -0.15350808 | D34: =COUNTIFS(실적!$Y$2:$Y$504,">="&B34,실적!$Y$2:$Y$504,"<"&C34) -> 100 | E34: {=IFERROR(MEDIAN(IF((ISNUMBER(실적!$Y$2:$Y$504)*(실적!$Y$2:$Y$504>=B34)*(실적!$Y$2:$Y$504<C34))*ISNUMBER(실적!$Y$2:$Y$504),실적!$Y$2:$Y$504)),"")} -> -0.29315231 | F34: {=IFERROR(MEDIAN(IF((ISNUMBER(실적!$Y$2:$Y$504)*(실적!$Y$2:$Y$504>=B34)*(실적!$Y$2:$Y$504<C34))*ISNUMBER(실적!$N$2:$N$504),실적!$N$2:$N$504)),"")} -> 0.057612069 | G34: {=IFERROR(MEDIAN(IF((ISNUMBER(실적!$Y$2:$Y$504)*(실적!$Y$2:$Y$504>=B34)*(실적!$Y$2:$Y$504<C34))*ISNUMBER(실적!$O$2:$O$504),실적!$O$2:$O$504)),"")} -> 0.028207598 | H34: {=IFERROR(MEDIAN(IF((ISNUMBER(실적!$Y$2:$Y$504)*(실적!$Y$2:$Y$504>=B34)*(실적!$Y$2:$Y$504<C34))*ISNUMBER(실적!$P$2:$P$504),실적!$P$2:$P$504)),"")} -> 0.036633207 | I34: {=IFERROR(SUM((ISNUMBER(실적!$Y$2:$Y$504)*(실적!$Y$2:$Y$504>=B34)*(실적!$Y$2:$Y$504<C34))*(실적!$T$2:$T$504<>""))/D34,"")} -> 0.25 | J34: {=IFERROR(MEDIAN(IF((ISNUMBER(실적!$Y$2:$Y$504)*(실적!$Y$2:$Y$504>=B34)*(실적!$Y$2:$Y$504<C34))*ISNUMBER(실적!$AA$2:$AA$504),실적!$AA$2:$AA$504)),"")} -> 0.07033151 | K34: {=IFERROR(SUM((ISNUMBER(실적!$Y$2:$Y$504)*(실적!$Y$2:$Y$504>=B34)*(실적!$Y$2:$Y$504<C34))*(실적!$AB$2:$AB$504<>""))/D34,"")} -> 0.31 | L34: {=IFERROR(MEDIAN(IF((ISNUMBER(실적!$Y$2:$Y$504)*(실적!$Y$2:$Y$504>=B34)*(실적!$Y$2:$Y$504<C34))*ISNUMBER(실적!$AC$2:$AC$504),실적!$AC$2:$AC$504)),"")} -> -0.016505507
A35: ※ 영업이익 YoY 중앙값은 숫자 값만 사용 ('흑자전환'·'N/M' 등 제외). '현재' = 이 파일의 최근 5개 분기, 1년 전 = SEC 제출 자료 기준 당시 최근 5개 분기
A38: 1년 주가수익률 상위 30 종목
A39: 순위 | B39: 티커 | C39: 기업명 | D39: GICS 섹터 | E39: 1년 주가수익률 | F39: 매출 YoY(현재) | G39: 최근 QoQ(현재) | H39: 현재 선정 기준 | I39: 매출 YoY(2025-09-24) | J39: 2025-09-24 선정 기준 | K39: 주요 사업
A40: 1 | B40: SNDK | C40: =IF(INDEX(실적!$A$2:$A$504,MATCH($B40,실적!$B$2:$B$504,0))="","",INDEX(실적!$A$2:$A$504,MATCH($B40,실적!$B$2:$B$504,0))) -> Sandisk | D40: =IF(INDEX(실적!$V$2:$V$504,MATCH($B40,실적!$B$2:$B$504,0))="","",INDEX(실적!$V$2:$V$504,MATCH($B40,실적!$B$2:$B$504,0))) -> Information Technology | E40: =IF(INDEX(실적!$Y$2:$Y$504,MATCH($B40,실적!$B$2:$B$504,0))="","",INDEX(실적!$Y$2:$Y$504,MATCH($B40,실적!$B$2:$B$504,0))) -> 17.196633 | F40: =IF(INDEX(실적!$N$2:$N$504,MATCH($B40,실적!$B$2:$B$504,0))="","",INDEX(실적!$N$2:$N$504,MATCH($B40,실적!$B$2:$B$504,0))) -> 3.715939 | G40: =IF(INDEX(실적!$P$2:$P$504,MATCH($B40,실적!$B$2:$B$504,0))="","",INDEX(실적!$P$2:$P$504,MATCH($B40,실적!$B$2:$B$504,0))) -> 0.50672269 | H40: =IF(INDEX(실적!$T$2:$T$504,MATCH($B40,실적!$B$2:$B$504,0))="","",INDEX(실적!$T$2:$T$504,MATCH($B40,실적!$B$2:$B$504,0))) -> 최근 QoQ≥10% | I40: =IF(INDEX(실적!$AA$2:$AA$504,MATCH($B40,실적!$B$2:$B$504,0))="","",INDEX(실적!$AA$2:$AA$504,MATCH($B40,실적!$B$2:$B$504,0))) -> 0.11495601 | J40: =IF(INDEX(실적!$AB$2:$AB$504,MATCH($B40,실적!$B$2:$B$504,0))="","",INDEX(실적!$AB$2:$AB$504,MATCH($B40,실적!$B$2:$B$504,0))) -> 최근 QoQ≥10% | K40: =IF(INDEX(실적!$U$2:$U$504,MATCH($B40,실적!$B$2:$B$504,0))="","",INDEX(실적!$U$2:$U$504,MATCH($B40,실적!$B$2:$B$504,0))) -> 낸드 플래시 메모리·SSD 등 데이터 저장장치 제조 (WD에서 분사)
A41: 2 | B41: MRNA | C41: =IF(INDEX(실적!$A$2:$A$504,MATCH($B41,실적!$B$2:$B$504,0))="","",INDEX(실적!$A$2:$A$504,MATCH($B41,실적!$B$2:$B$504,0))) -> Moderna | D41: =IF(INDEX(실적!$V$2:$V$504,MATCH($B41,실적!$B$2:$B$504,0))="","",INDEX(실적!$V$2:$V$504,MATCH($B41,실적!$B$2:$B$504,0))) -> Health Care | E41: =IF(INDEX(실적!$Y$2:$Y$504,MATCH($B41,실적!$B$2:$B$504,0))="","",INDEX(실적!$Y$2:$Y$504,MATCH($B41,실적!$B$2:$B$504,0))) -> 6.0367079 | F41: =IF(INDEX(실적!$N$2:$N$504,MATCH($B41,실적!$B$2:$B$504,0))="","",INDEX(실적!$N$2:$N$504,MATCH($B41,실적!$B$2:$B$504,0))) -> 0.04379562 | G41: =IF(INDEX(실적!$P$2:$P$504,MATCH($B41,실적!$B$2:$B$504,0))="","",INDEX(실적!$P$2:$P$504,MATCH($B41,실적!$B$2:$B$504,0))) -> -0.63239075 | H41: =IF(INDEX(실적!$T$2:$T$504,MATCH($B41,실적!$B$2:$B$504,0))="","",INDEX(실적!$T$2:$T$504,MATCH($B41,실적!$B$2:$B$504,0))) | I41: =IF(INDEX(실적!$AA$2:$AA$504,MATCH($B41,실적!$B$2:$B$504,0))="","",INDEX(실적!$AA$2:$AA$504,MATCH($B41,실적!$B$2:$B$504,0))) -> -0.41078838 | J41: =IF(INDEX(실적!$AB$2:$AB$504,MATCH($B41,실적!$B$2:$B$504,0))="","",INDEX(실적!$AB$2:$AB$504,MATCH($B41,실적!$B$2:$B$504,0))) -> 최근 QoQ≥10% | K41: mRNA 백신·치료제 (코로나·RSV)
A42: 3 | B42: MU | C42: =IF(INDEX(실적!$A$2:$A$504,MATCH($B42,실적!$B$2:$B$504,0))="","",INDEX(실적!$A$2:$A$504,MATCH($B42,실적!$B$2:$B$504,0))) -> Micron Technology | D42: =IF(INDEX(실적!$V$2:$V$504,MATCH($B42,실적!$B$2:$B$504,0))="","",INDEX(실적!$V$2:$V$504,MATCH($B42,실적!$B$2:$B$504,0))) -> Information Technology | E42: =IF(INDEX(실적!$Y$2:$Y$504,MATCH($B42,실적!$B$2:$B$504,0))="","",INDEX(실적!$Y$2:$Y$504,MATCH($B42,실적!$B$2:$B$504,0))) -> 5.6284089 | F42: =IF(INDEX(실적!$N$2:$N$504,MATCH($B42,실적!$B$2:$B$504,0))="","",INDEX(실적!$N$2:$N$504,MATCH($B42,실적!$B$2:$B$504,0))) -> 3.4571551 | G42: =IF(INDEX(실적!$P$2:$P$504,MATCH($B42,실적!$B$2:$B$504,0))="","",INDEX(실적!$P$2:$P$504,MATCH($B42,실적!$B$2:$B$504,0))) -> 0.73746857 | H42: =IF(INDEX(실적!$T$2:$T$504,MATCH($B42,실적!$B$2:$B$504,0))="","",INDEX(실적!$T$2:$T$504,MATCH($B42,실적!$B$2:$B$504,0))) -> 최근 QoQ≥10% | I42: =IF(INDEX(실적!$AA$2:$AA$504,MATCH($B42,실적!$B$2:$B$504,0))="","",INDEX(실적!$AA$2:$AA$504,MATCH($B42,실적!$B$2:$B$504,0))) -> 0.36558508 | J42: =IF(INDEX(실적!$AB$2:$AB$504,MATCH($B42,실적!$B$2:$B$504,0))="","",INDEX(실적!$AB$2:$AB$504,MATCH($B42,실적!$B$2:$B$504,0))) -> 최근 QoQ≥10% | K42: =IF(INDEX(실적!$U$2:$U$504,MATCH($B42,실적!$B$2:$B$504,0))="","",INDEX(실적!$U$2:$U$504,MATCH($B42,실적!$B$2:$B$504,0))) -> D램·낸드 메모리 반도체 제조 (AI 서버용 HBM 포함)
A43: 4 | B43: LITE | C43: =IF(INDEX(실적!$A$2:$A$504,MATCH($B43,실적!$B$2:$B$504,0))="","",INDEX(실적!$A$2:$A$504,MATCH($B43,실적!$B$2:$B$504,0))) -> Lumentum | D43: =IF(INDEX(실적!$V$2:$V$504,MATCH($B43,실적!$B$2:$B$504,0))="","",INDEX(실적!$V$2:$V$504,MATCH($B43,실적!$B$2:$B$504,0))) -> Information Technology | E43: =IF(INDEX(실적!$Y$2:$Y$504,MATCH($B43,실적!$B$2:$B$504,0))="","",INDEX(실적!$Y$2:$Y$504,MATCH($B43,실적!$B$2:$B$504,0))) -> 5.1342062 | F43: =IF(INDEX(실적!$N$2:$N$504,MATCH($B43,실적!$B$2:$B$504,0))="","",INDEX(실적!$N$2:$N$504,MATCH($B43,실적!$B$2:$B$504,0))) -> 1.0934055 | G43: =IF(INDEX(실적!$P$2:$P$504,MATCH($B43,실적!$B$2:$B$504,0))="","",INDEX(실적!$P$2:$P$504,MATCH($B43,실적!$B$2:$B$504,0))) -> 0.24480455 | H43: =IF(INDEX(실적!$T$2:$T$504,MATCH($B43,실적!$B$2:$B$504,0))="","",INDEX(실적!$T$2:$T$504,MATCH($B43,실적!$B$2:$B$504,0))) -> 최근 QoQ≥10% | I43: =IF(INDEX(실적!$AA$2:$AA$504,MATCH($B43,실적!$B$2:$B$504,0))="","",INDEX(실적!$AA$2:$AA$504,MATCH($B43,실적!$B$2:$B$504,0))) -> 0.55919559 | J43: =IF(INDEX(실적!$AB$2:$AB$504,MATCH($B43,실적!$B$2:$B$504,0))="","",INDEX(실적!$AB$2:$AB$504,MATCH($B43,실적!$B$2:$B$504,0))) -> 최근 QoQ≥10% | K43: =IF(INDEX(실적!$U$2:$U$504,MATCH($B43,실적!$B$2:$B$504,0))="","",INDEX(실적!$U$2:$U$504,MATCH($B43,실적!$B$2:$B$504,0))) -> 광통신 부품·레이저 (데이터센터용 광트랜시버)
A44: 5 | B44: WDC | C44: =IF(INDEX(실적!$A$2:$A$504,MATCH($B44,실적!$B$2:$B$504,0))="","",INDEX(실적!$A$2:$A$504,MATCH($B44,실적!$B$2:$B$504,0))) -> Western Digital | D44: =IF(INDEX(실적!$V$2:$V$504,MATCH($B44,실적!$B$2:$B$504,0))="","",INDEX(실적!$V$2:$V$504,MATCH($B44,실적!$B$2:$B$504,0))) -> Information Technology | E44: =IF(INDEX(실적!$Y$2:$Y$504,MATCH($B44,실적!$B$2:$B$504,0))="","",INDEX(실적!$Y$2:$Y$504,MATCH($B44,실적!$B$2:$B$504,0))) -> 3.3184429 | F44: =IF(INDEX(실적!$N$2:$N$504,MATCH($B44,실적!$B$2:$B$504,0))="","",INDEX(실적!$N$2:$N$504,MATCH($B44,실적!$B$2:$B$504,0))) -> 0.43838772 | G44: =IF(INDEX(실적!$P$2:$P$504,MATCH($B44,실적!$B$2:$B$504,0))="","",INDEX(실적!$P$2:$P$504,MATCH($B44,실적!$B$2:$B$504,0))) -> 0.12286485 | H44: =IF(INDEX(실적!$T$2:$T$504,MATCH($B44,실적!$B$2:$B$504,0))="","",INDEX(실적!$T$2:$T$504,MATCH($B44,실적!$B$2:$B$504,0))) -> 최근 QoQ≥10% | I44: =IF(INDEX(실적!$AA$2:$AA$504,MATCH($B44,실적!$B$2:$B$504,0))="","",INDEX(실적!$AA$2:$AA$504,MATCH($B44,실적!$B$2:$B$504,0))) -> 0.2999002 | J44: =IF(INDEX(실적!$AB$2:$AB$504,MATCH($B44,실적!$B$2:$B$504,0))="","",INDEX(실적!$AB$2:$AB$504,MATCH($B44,실적!$B$2:$B$504,0))) -> 최근 QoQ≥10% | K44: =IF(INDEX(실적!$U$2:$U$504,MATCH($B44,실적!$B$2:$B$504,0))="","",INDEX(실적!$U$2:$U$504,MATCH($B44,실적!$B$2:$B$504,0))) -> 하드디스크(HDD) 데이터 저장장치
A45: 6 | B45: DELL | C45: =IF(INDEX(실적!$A$2:$A$504,MATCH($B45,실적!$B$2:$B$504,0))="","",INDEX(실적!$A$2:$A$504,MATCH($B45,실적!$B$2:$B$504,0))) -> Dell Technologies | D45: =IF(INDEX(실적!$V$2:$V$504,MATCH($B45,실적!$B$2:$B$504,0))="","",INDEX(실적!$V$2:$V$504,MATCH($B45,실적!$B$2:$B$504,0))) -> Information Technology | E45: =IF(INDEX(실적!$Y$2:$Y$504,MATCH($B45,실적!$B$2:$B$504,0))="","",INDEX(실적!$Y$2:$Y$504,MATCH($B45,실적!$B$2:$B$504,0))) -> 3.1625407 | F45: =IF(INDEX(실적!$N$2:$N$504,MATCH($B45,실적!$B$2:$B$504,0))="","",INDEX(실적!$N$2:$N$504,MATCH($B45,실적!$B$2:$B$504,0))) -> 0.57747851 | G45: =IF(INDEX(실적!$P$2:$P$504,MATCH($B45,실적!$B$2:$B$504,0))="","",INDEX(실적!$P$2:$P$504,MATCH($B45,실적!$B$2:$B$504,0))) -> 0.071369919 | H45: =IF(INDEX(실적!$T$2:$T$504,MATCH($B45,실적!$B$2:$B$504,0))="","",INDEX(실적!$T$2:$T$504,MATCH($B45,실적!$B$2:$B$504,0))) | I45: =IF(INDEX(실적!$AA$2:$AA$504,MATCH($B45,실적!$B$2:$B$504,0))="","",INDEX(실적!$AA$2:$AA$504,MATCH($B45,실적!$B$2:$B$504,0))) -> 0.18980261 | J45: =IF(INDEX(실적!$AB$2:$AB$504,MATCH($B45,실적!$B$2:$B$504,0))="","",INDEX(실적!$AB$2:$AB$504,MATCH($B45,실적!$B$2:$B$504,0))) -> 최근 QoQ≥10% | K45: PC·서버(AI 서버)·스토리지
A46: 7 | B46: STX | C46: =IF(INDEX(실적!$A$2:$A$504,MATCH($B46,실적!$B$2:$B$504,0))="","",INDEX(실적!$A$2:$A$504,MATCH($B46,실적!$B$2:$B$504,0))) -> Seagate Technology | D46: =IF(INDEX(실적!$V$2:$V$504,MATCH($B46,실적!$B$2:$B$504,0))="","",INDEX(실적!$V$2:$V$504,MATCH($B46,실적!$B$2:$B$504,0))) -> Information Technology | E46: =IF(INDEX(실적!$Y$2:$Y$504,MATCH($B46,실적!$B$2:$B$504,0))="","",INDEX(실적!$Y$2:$Y$504,MATCH($B46,실적!$B$2:$B$504,0))) -> 3.1299061 | F46: =IF(INDEX(실적!$N$2:$N$504,MATCH($B46,실적!$B$2:$B$504,0))="","",INDEX(실적!$N$2:$N$504,MATCH($B46,실적!$B$2:$B$504,0))) -> 0.48486088 | G46: =IF(INDEX(실적!$P$2:$P$504,MATCH($B46,실적!$B$2:$B$504,0))="","",INDEX(실적!$P$2:$P$504,MATCH($B46,실적!$B$2:$B$504,0))) -> 0.16613111 | H46: =IF(INDEX(실적!$T$2:$T$504,MATCH($B46,실적!$B$2:$B$504,0))="","",INDEX(실적!$T$2:$T$504,MATCH($B46,실적!$B$2:$B$504,0))) -> 최근 QoQ≥10% | I46: =IF(INDEX(실적!$AA$2:$AA$504,MATCH($B46,실적!$B$2:$B$504,0))="","",INDEX(실적!$AA$2:$AA$504,MATCH($B46,실적!$B$2:$B$504,0))) -> 0.29517753 | J46: =IF(INDEX(실적!$AB$2:$AB$504,MATCH($B46,실적!$B$2:$B$504,0))="","",INDEX(실적!$AB$2:$AB$504,MATCH($B46,실적!$B$2:$B$504,0))) -> 최근 QoQ≥10% | K46: =IF(INDEX(실적!$U$2:$U$504,MATCH($B46,실적!$B$2:$B$504,0))="","",INDEX(실적!$U$2:$U$504,MATCH($B46,실적!$B$2:$B$504,0))) -> 하드디스크(HDD) 등 데이터 저장장치
A47: 8 | B47: BE | C47: =IF(INDEX(실적!$A$2:$A$504,MATCH($B47,실적!$B$2:$B$504,0))="","",INDEX(실적!$A$2:$A$504,MATCH($B47,실적!$B$2:$B$504,0))) -> Bloom Energy | D47: =IF(INDEX(실적!$V$2:$V$504,MATCH($B47,실적!$B$2:$B$504,0))="","",INDEX(실적!$V$2:$V$504,MATCH($B47,실적!$B$2:$B$504,0))) -> Industrials | E47: =IF(INDEX(실적!$Y$2:$Y$504,MATCH($B47,실적!$B$2:$B$504,0))="","",INDEX(실적!$Y$2:$Y$504,MATCH($B47,실적!$B$2:$B$504,0))) -> 2.9778838 | F47: =IF(INDEX(실적!$N$2:$N$504,MATCH($B47,실적!$B$2:$B$504,0))="","",INDEX(실적!$N$2:$N$504,MATCH($B47,실적!$B$2:$B$504,0))) -> 1.6551682 | G47: =IF(INDEX(실적!$P$2:$P$504,MATCH($B47,실적!$B$2:$B$504,0))="","",INDEX(실적!$P$2:$P$504,MATCH($B47,실적!$B$2:$B$504,0))) -> 0.41849321 | H47: =IF(INDEX(실적!$T$2:$T$504,MATCH($B47,실적!$B$2:$B$504,0))="","",INDEX(실적!$T$2:$T$504,MATCH($B47,실적!$B$2:$B$504,0))) -> 최근 QoQ≥10% | I47: =IF(INDEX(실적!$AA$2:$AA$504,MATCH($B47,실적!$B$2:$B$504,0))="","",INDEX(실적!$AA$2:$AA$504,MATCH($B47,실적!$B$2:$B$504,0))) -> 0.1950013 | J47: =IF(INDEX(실적!$AB$2:$AB$504,MATCH($B47,실적!$B$2:$B$504,0))="","",INDEX(실적!$AB$2:$AB$504,MATCH($B47,실적!$B$2:$B$504,0))) -> 최근 QoQ≥10% | K47: =IF(INDEX(실적!$U$2:$U$504,MATCH($B47,실적!$B$2:$B$504,0))="","",INDEX(실적!$U$2:$U$504,MATCH($B47,실적!$B$2:$B$504,0))) -> 고체산화물 연료전지 기반 현장 발전 시스템 (데이터센터 전력 공급)
A48: 9 | B48: INTC | C48: =IF(INDEX(실적!$A$2:$A$504,MATCH($B48,실적!$B$2:$B$504,0))="","",INDEX(실적!$A$2:$A$504,MATCH($B48,실적!$B$2:$B$504,0))) -> Intel | D48: =IF(INDEX(실적!$V$2:$V$504,MATCH($B48,실적!$B$2:$B$504,0))="","",INDEX(실적!$V$2:$V$504,MATCH($B48,실적!$B$2:$B$504,0))) -> Information Technology | E48: =IF(INDEX(실적!$Y$2:$Y$504,MATCH($B48,실적!$B$2:$B$504,0))="","",INDEX(실적!$Y$2:$Y$504,MATCH($B48,실적!$B$2:$B$504,0))) -> 2.9269699 | F48: =IF(INDEX(실적!$N$2:$N$504,MATCH($B48,실적!$B$2:$B$504,0))="","",INDEX(실적!$N$2:$N$504,MATCH($B48,실적!$B$2:$B$504,0))) -> 0.25421884 | G48: =IF(INDEX(실적!$P$2:$P$504,MATCH($B48,실적!$B$2:$B$504,0))="","",INDEX(실적!$P$2:$P$504,MATCH($B48,실적!$B$2:$B$504,0))) -> 0.18789129 | H48: =IF(INDEX(실적!$T$2:$T$504,MATCH($B48,실적!$B$2:$B$504,0))="","",INDEX(실적!$T$2:$T$504,MATCH($B48,실적!$B$2:$B$504,0))) -> 최근 QoQ≥10% | I48: =IF(INDEX(실적!$AA$2:$AA$504,MATCH($B48,실적!$B$2:$B$504,0))="","",INDEX(실적!$AA$2:$AA$504,MATCH($B48,실적!$B$2:$B$504,0))) -> 0.0020260267 | J48: =IF(INDEX(실적!$AB$2:$AB$504,MATCH($B48,실적!$B$2:$B$504,0))="","",INDEX(실적!$AB$2:$AB$504,MATCH($B48,실적!$B$2:$B$504,0))) | K48: =IF(INDEX(실적!$U$2:$U$504,MATCH($B48,실적!$B$2:$B$504,0))="","",INDEX(실적!$U$2:$U$504,MATCH($B48,실적!$B$2:$B$504,0))) -> PC·서버용 CPU 반도체 및 파운드리
A49: 10 | B49: AMD | C49: =IF(INDEX(실적!$A$2:$A$504,MATCH($B49,실적!$B$2:$B$504,0))="","",INDEX(실적!$A$2:$A$504,MATCH($B49,실적!$B$2:$B$504,0))) -> Advanced Micro Devices | D49: =IF(INDEX(실적!$V$2:$V$504,MATCH($B49,실적!$B$2:$B$504,0))="","",INDEX(실적!$V$2:$V$504,MATCH($B49,실적!$B$2:$B$504,0))) -> Information Technology | E49: =IF(INDEX(실적!$Y$2:$Y$504,MATCH($B49,실적!$B$2:$B$504,0))="","",INDEX(실적!$Y$2:$Y$504,MATCH($B49,실적!$B$2:$B$504,0))) -> 2.8203008 | F49: =IF(INDEX(실적!$N$2:$N$504,MATCH($B49,실적!$B$2:$B$504,0))="","",INDEX(실적!$N$2:$N$504,MATCH($B49,실적!$B$2:$B$504,0))) -> 0.50110605 | G49: =IF(INDEX(실적!$P$2:$P$504,MATCH($B49,실적!$B$2:$B$504,0))="","",INDEX(실적!$P$2:$P$504,MATCH($B49,실적!$B$2:$B$504,0))) -> 0.12513411 | H49: =IF(INDEX(실적!$T$2:$T$504,MATCH($B49,실적!$B$2:$B$504,0))="","",INDEX(실적!$T$2:$T$504,MATCH($B49,실적!$B$2:$B$504,0))) -> 최근 QoQ≥10% | I49: =IF(INDEX(실적!$AA$2:$AA$504,MATCH($B49,실적!$B$2:$B$504,0))="","",INDEX(실적!$AA$2:$AA$504,MATCH($B49,실적!$B$2:$B$504,0))) -> 0.31705227 | J49: =IF(INDEX(실적!$AB$2:$AB$504,MATCH($B49,실적!$B$2:$B$504,0))="","",INDEX(실적!$AB$2:$AB$504,MATCH($B49,실적!$B$2:$B$504,0))) | K49: =IF(INDEX(실적!$U$2:$U$504,MATCH($B49,실적!$B$2:$B$504,0))="","",INDEX(실적!$U$2:$U$504,MATCH($B49,실적!$B$2:$B$504,0))) -> CPU·GPU·AI 가속기 등 반도체 설계
A50: 11 | B50: MRVL | C50: =IF(INDEX(실적!$A$2:$A$504,MATCH($B50,실적!$B$2:$B$504,0))="","",INDEX(실적!$A$2:$A$504,MATCH($B50,실적!$B$2:$B$504,0))) -> Marvell Technology | D50: =IF(INDEX(실적!$V$2:$V$504,MATCH($B50,실적!$B$2:$B$504,0))="","",INDEX(실적!$V$2:$V$504,MATCH($B50,실적!$B$2:$B$504,0))) -> Information Technology | E50: =IF(INDEX(실적!$Y$2:$Y$504,MATCH($B50,실적!$B$2:$B$504,0))="","",INDEX(실적!$Y$2:$Y$504,MATCH($B50,실적!$B$2:$B$504,0))) -> 2.2575852 | F50: =IF(INDEX(실적!$N$2:$N$504,MATCH($B50,실적!$B$2:$B$504,0))="","",INDEX(실적!$N$2:$N$504,MATCH($B50,실적!$B$2:$B$504,0))) -> 0.36548527 | G50: =IF(INDEX(실적!$P$2:$P$504,MATCH($B50,실적!$B$2:$B$504,0))="","",INDEX(실적!$P$2:$P$504,MATCH($B50,실적!$B$2:$B$504,0))) -> 0.13297212 | H50: =IF(INDEX(실적!$T$2:$T$504,MATCH($B50,실적!$B$2:$B$504,0))="","",INDEX(실적!$T$2:$T$504,MATCH($B50,실적!$B$2:$B$504,0))) -> QoQ 가속 + 최근 QoQ≥10% | I50: =IF(INDEX(실적!$AA$2:$AA$504,MATCH($B50,실적!$B$2:$B$504,0))="","",INDEX(실적!$AA$2:$AA$504,MATCH($B50,실적!$B$2:$B$504,0))) -> 0.57600754 | J50: =IF(INDEX(실적!$AB$2:$AB$504,MATCH($B50,실적!$B$2:$B$504,0))="","",INDEX(실적!$AB$2:$AB$504,MATCH($B50,실적!$B$2:$B$504,0))) | K50: =IF(INDEX(실적!$U$2:$U$504,MATCH($B50,실적!$B$2:$B$504,0))="","",INDEX(실적!$U$2:$U$504,MATCH($B50,실적!$B$2:$B$504,0))) -> 데이터센터용 맞춤형 AI 칩·광통신·네트워크 반도체
A51: 12 | B51: TER | C51: =IF(INDEX(실적!$A$2:$A$504,MATCH($B51,실적!$B$2:$B$504,0))="","",INDEX(실적!$A$2:$A$504,MATCH($B51,실적!$B$2:$B$504,0))) -> Teradyne | D51: =IF(INDEX(실적!$V$2:$V$504,MATCH($B51,실적!$B$2:$B$504,0))="","",INDEX(실적!$V$2:$V$504,MATCH($B51,실적!$B$2:$B$504,0))) -> Information Technology | E51: =IF(INDEX(실적!$Y$2:$Y$504,MATCH($B51,실적!$B$2:$B$504,0))="","",INDEX(실적!$Y$2:$Y$504,MATCH($B51,실적!$B$2:$B$504,0))) -> 1.9212522 | F51: =IF(INDEX(실적!$N$2:$N$504,MATCH($B51,실적!$B$2:$B$504,0))="","",INDEX(실적!$N$2:$N$504,MATCH($B51,실적!$B$2:$B$504,0))) -> 1.0389631 | G51: =IF(INDEX(실적!$P$2:$P$504,MATCH($B51,실적!$B$2:$B$504,0))="","",INDEX(실적!$P$2:$P$504,MATCH($B51,실적!$B$2:$B$504,0))) -> 0.036254361 | H51: =IF(INDEX(실적!$T$2:$T$504,MATCH($B51,실적!$B$2:$B$504,0))="","",INDEX(실적!$T$2:$T$504,MATCH($B51,실적!$B$2:$B$504,0))) | I51: =IF(INDEX(실적!$AA$2:$AA$504,MATCH($B51,실적!$B$2:$B$504,0))="","",INDEX(실적!$AA$2:$AA$504,MATCH($B51,실적!$B$2:$B$504,0))) -> -0.10697938 | J51: =IF(INDEX(실적!$AB$2:$AB$504,MATCH($B51,실적!$B$2:$B$504,0))="","",INDEX(실적!$AB$2:$AB$504,MATCH($B51,실적!$B$2:$B$504,0))) | K51: 반도체·전자기기 자동 테스트 장비(ATE) 및 협동로봇
A52: 13 | B52: COHR | C52: =IF(INDEX(실적!$A$2:$A$504,MATCH($B52,실적!$B$2:$B$504,0))="","",INDEX(실적!$A$2:$A$504,MATCH($B52,실적!$B$2:$B$504,0))) -> Coherent Corp. | D52: =IF(INDEX(실적!$V$2:$V$504,MATCH($B52,실적!$B$2:$B$504,0))="","",INDEX(실적!$V$2:$V$504,MATCH($B52,실적!$B$2:$B$504,0))) -> Information Technology | E52: =IF(INDEX(실적!$Y$2:$Y$504,MATCH($B52,실적!$B$2:$B$504,0))="","",INDEX(실적!$Y$2:$Y$504,MATCH($B52,실적!$B$2:$B$504,0))) -> 1.8220053 | F52: =IF(INDEX(실적!$N$2:$N$504,MATCH($B52,실적!$B$2:$B$504,0))="","",INDEX(실적!$N$2:$N$504,MATCH($B52,실적!$B$2:$B$504,0))) -> 0.33744269 | G52: =IF(INDEX(실적!$P$2:$P$504,MATCH($B52,실적!$B$2:$B$504,0))="","",INDEX(실적!$P$2:$P$504,MATCH($B52,실적!$B$2:$B$504,0))) -> 0.13285697 | H52: =IF(INDEX(실적!$T$2:$T$504,MATCH($B52,실적!$B$2:$B$504,0))="","",INDEX(실적!$T$2:$T$504,MATCH($B52,실적!$B$2:$B$504,0))) -> QoQ 가속 + 최근 QoQ≥10% | I52: =IF(INDEX(실적!$AA$2:$AA$504,MATCH($B52,실적!$B$2:$B$504,0))="","",INDEX(실적!$AA$2:$AA$504,MATCH($B52,실적!$B$2:$B$504,0))) -> 0.16363376 | J52: =IF(INDEX(실적!$AB$2:$AB$504,MATCH($B52,실적!$B$2:$B$504,0))="","",INDEX(실적!$AB$2:$AB$504,MATCH($B52,실적!$B$2:$B$504,0))) | K52: =IF(INDEX(실적!$U$2:$U$504,MATCH($B52,실적!$B$2:$B$504,0))="","",INDEX(실적!$U$2:$U$504,MATCH($B52,실적!$B$2:$B$504,0))) -> 레이저·광트랜시버 등 광학·광전자 부품
A53: 14 | B53: ILMN | C53: =IF(INDEX(실적!$A$2:$A$504,MATCH($B53,실적!$B$2:$B$504,0))="","",INDEX(실적!$A$2:$A$504,MATCH($B53,실적!$B$2:$B$504,0))) -> Illumina, Inc. | D53: =IF(INDEX(실적!$V$2:$V$504,MATCH($B53,실적!$B$2:$B$504,0))="","",INDEX(실적!$V$2:$V$504,MATCH($B53,실적!$B$2:$B$504,0))) -> Health Care | E53: =IF(INDEX(실적!$Y$2:$Y$504,MATCH($B53,실적!$B$2:$B$504,0))="","",INDEX(실적!$Y$2:$Y$504,MATCH($B53,실적!$B$2:$B$504,0))) -> 1.7050101 | F53: =IF(INDEX(실적!$N$2:$N$504,MATCH($B53,실적!$B$2:$B$504,0))="","",INDEX(실적!$N$2:$N$504,MATCH($B53,실적!$B$2:$B$504,0))) -> 0.04803074 | G53: =IF(INDEX(실적!$P$2:$P$504,MATCH($B53,실적!$B$2:$B$504,0))="","",INDEX(실적!$P$2:$P$504,MATCH($B53,실적!$B$2:$B$504,0))) -> -0.058671268 | H53: =IF(INDEX(실적!$T$2:$T$504,MATCH($B53,실적!$B$2:$B$504,0))="","",INDEX(실적!$T$2:$T$504,MATCH($B53,실적!$B$2:$B$504,0))) | I53: =IF(INDEX(실적!$AA$2:$AA$504,MATCH($B53,실적!$B$2:$B$504,0))="","",INDEX(실적!$AA$2:$AA$504,MATCH($B53,실적!$B$2:$B$504,0))) -> -0.047661871 | J53: =IF(INDEX(실적!$AB$2:$AB$504,MATCH($B53,실적!$B$2:$B$504,0))="","",INDEX(실적!$AB$2:$AB$504,MATCH($B53,실적!$B$2:$B$504,0))) | K53: 유전체 분석(DNA 시퀀싱) 장비·시약
A54: 15 | B54: CIEN | C54: =IF(INDEX(실적!$A$2:$A$504,MATCH($B54,실적!$B$2:$B$504,0))="","",INDEX(실적!$A$2:$A$504,MATCH($B54,실적!$B$2:$B$504,0))) -> Ciena | D54: =IF(INDEX(실적!$V$2:$V$504,MATCH($B54,실적!$B$2:$B$504,0))="","",INDEX(실적!$V$2:$V$504,MATCH($B54,실적!$B$2:$B$504,0))) -> Information Technology | E54: =IF(INDEX(실적!$Y$2:$Y$504,MATCH($B54,실적!$B$2:$B$504,0))="","",INDEX(실적!$Y$2:$Y$504,MATCH($B54,실적!$B$2:$B$504,0))) -> 1.5712325 | F54: =IF(INDEX(실적!$N$2:$N$504,MATCH($B54,실적!$B$2:$B$504,0))="","",INDEX(실적!$N$2:$N$504,MATCH($B54,실적!$B$2:$B$504,0))) -> 0.37046872 | G54: =IF(INDEX(실적!$P$2:$P$504,MATCH($B54,실적!$B$2:$B$504,0))="","",INDEX(실적!$P$2:$P$504,MATCH($B54,실적!$B$2:$B$504,0))) -> 0.063912591 | H54: =IF(INDEX(실적!$T$2:$T$504,MATCH($B54,실적!$B$2:$B$504,0))="","",INDEX(실적!$T$2:$T$504,MATCH($B54,실적!$B$2:$B$504,0))) | I54: =IF(INDEX(실적!$AA$2:$AA$504,MATCH($B54,실적!$B$2:$B$504,0))="","",INDEX(실적!$AA$2:$AA$504,MATCH($B54,실적!$B$2:$B$504,0))) -> 0.2940408 | J54: =IF(INDEX(실적!$AB$2:$AB$504,MATCH($B54,실적!$B$2:$B$504,0))="","",INDEX(실적!$AB$2:$AB$504,MATCH($B54,실적!$B$2:$B$504,0))) | K54: 광통신 네트워크 장비 (데이터센터 연결·해저케이블)
A55: 16 | B55: HPE | C55: =IF(INDEX(실적!$A$2:$A$504,MATCH($B55,실적!$B$2:$B$504,0))="","",INDEX(실적!$A$2:$A$504,MATCH($B55,실적!$B$2:$B$504,0))) -> Hewlett Packard Enterprise | D55: =IF(INDEX(실적!$V$2:$V$504,MATCH($B55,실적!$B$2:$B$504,0))="","",INDEX(실적!$V$2:$V$504,MATCH($B55,실적!$B$2:$B$504,0))) -> Information Technology | E55: =IF(INDEX(실적!$Y$2:$Y$504,MATCH($B55,실적!$B$2:$B$504,0))="","",INDEX(실적!$Y$2:$Y$504,MATCH($B55,실적!$B$2:$B$504,0))) -> 1.548242 | F55: =IF(INDEX(실적!$N$2:$N$504,MATCH($B55,실적!$B$2:$B$504,0))="","",INDEX(실적!$N$2:$N$504,MATCH($B55,실적!$B$2:$B$504,0))) -> 0.33679947 | G55: =IF(INDEX(실적!$P$2:$P$504,MATCH($B55,실적!$B$2:$B$504,0))="","",INDEX(실적!$P$2:$P$504,MATCH($B55,실적!$B$2:$B$504,0))) -> 0.14375351 | H55: =IF(INDEX(실적!$T$2:$T$504,MATCH($B55,실적!$B$2:$B$504,0))="","",INDEX(실적!$T$2:$T$504,MATCH($B55,실적!$B$2:$B$504,0))) -> 최근 QoQ≥10% | I55: =IF(INDEX(실적!$AA$2:$AA$504,MATCH($B55,실적!$B$2:$B$504,0))="","",INDEX(실적!$AA$2:$AA$504,MATCH($B55,실적!$B$2:$B$504,0))) -> 0.1849546 | J55: =IF(INDEX(실적!$AB$2:$AB$504,MATCH($B55,실적!$B$2:$B$504,0))="","",INDEX(실적!$AB$2:$AB$504,MATCH($B55,실적!$B$2:$B$504,0))) -> 최근 QoQ≥10% | K55: =IF(INDEX(실적!$U$2:$U$504,MATCH($B55,실적!$B$2:$B$504,0))="","",INDEX(실적!$U$2:$U$504,MATCH($B55,실적!$B$2:$B$504,0))) -> 서버·스토리지·네트워크(주니퍼) 기업 IT 인프라
A56: 17 | B56: LRCX | C56: =IF(INDEX(실적!$A$2:$A$504,MATCH($B56,실적!$B$2:$B$504,0))="","",INDEX(실적!$A$2:$A$504,MATCH($B56,실적!$B$2:$B$504,0))) -> Lam Research | D56: =IF(INDEX(실적!$V$2:$V$504,MATCH($B56,실적!$B$2:$B$504,0))="","",INDEX(실적!$V$2:$V$504,MATCH($B56,실적!$B$2:$B$504,0))) -> Information Technology | E56: =IF(INDEX(실적!$Y$2:$Y$504,MATCH($B56,실적!$B$2:$B$504,0))="","",INDEX(실적!$Y$2:$Y$504,MATCH($B56,실적!$B$2:$B$504,0))) -> 1.3946384 | F56: =IF(INDEX(실적!$N$2:$N$504,MATCH($B56,실적!$B$2:$B$504,0))="","",INDEX(실적!$N$2:$N$504,MATCH($B56,실적!$B$2:$B$504,0))) -> 0.29988922 | G56: =IF(INDEX(실적!$P$2:$P$504,MATCH($B56,실적!$B$2:$B$504,0))="","",INDEX(실적!$P$2:$P$504,MATCH($B56,실적!$B$2:$B$504,0))) -> 0.15077494 | H56: =IF(INDEX(실적!$T$2:$T$504,MATCH($B56,실적!$B$2:$B$504,0))="","",INDEX(실적!$T$2:$T$504,MATCH($B56,실적!$B$2:$B$504,0))) -> 최근 QoQ≥10% | I56: =IF(INDEX(실적!$AA$2:$AA$504,MATCH($B56,실적!$B$2:$B$504,0))="","",INDEX(실적!$AA$2:$AA$504,MATCH($B56,실적!$B$2:$B$504,0))) -> 0.33575711 | J56: =IF(INDEX(실적!$AB$2:$AB$504,MATCH($B56,실적!$B$2:$B$504,0))="","",INDEX(실적!$AB$2:$AB$504,MATCH($B56,실적!$B$2:$B$504,0))) | K56: =IF(INDEX(실적!$U$2:$U$504,MATCH($B56,실적!$B$2:$B$504,0))="","",INDEX(실적!$U$2:$U$504,MATCH($B56,실적!$B$2:$B$504,0))) -> 반도체 식각·증착 장비
A57: 18 | B57: AMAT | C57: =IF(INDEX(실적!$A$2:$A$504,MATCH($B57,실적!$B$2:$B$504,0))="","",INDEX(실적!$A$2:$A$504,MATCH($B57,실적!$B$2:$B$504,0))) -> Applied Materials | D57: =IF(INDEX(실적!$V$2:$V$504,MATCH($B57,실적!$B$2:$B$504,0))="","",INDEX(실적!$V$2:$V$504,MATCH($B57,실적!$B$2:$B$504,0))) -> Information Technology | E57: =IF(INDEX(실적!$Y$2:$Y$504,MATCH($B57,실적!$B$2:$B$504,0))="","",INDEX(실적!$Y$2:$Y$504,MATCH($B57,실적!$B$2:$B$504,0))) -> 1.3549444 | F57: =IF(INDEX(실적!$N$2:$N$504,MATCH($B57,실적!$B$2:$B$504,0))="","",INDEX(실적!$N$2:$N$504,MATCH($B57,실적!$B$2:$B$504,0))) -> 0.24828814 | G57: =IF(INDEX(실적!$P$2:$P$504,MATCH($B57,실적!$B$2:$B$504,0))="","",INDEX(실적!$P$2:$P$504,MATCH($B57,실적!$B$2:$B$504,0))) -> 0.15233881 | H57: =IF(INDEX(실적!$T$2:$T$504,MATCH($B57,실적!$B$2:$B$504,0))="","",INDEX(실적!$T$2:$T$504,MATCH($B57,실적!$B$2:$B$504,0))) -> QoQ 가속 + 최근 QoQ≥10% | I57: =IF(INDEX(실적!$AA$2:$AA$504,MATCH($B57,실적!$B$2:$B$504,0))="","",INDEX(실적!$AA$2:$AA$504,MATCH($B57,실적!$B$2:$B$504,0))) -> 0.077308941 | J57: =IF(INDEX(실적!$AB$2:$AB$504,MATCH($B57,실적!$B$2:$B$504,0))="","",INDEX(실적!$AB$2:$AB$504,MATCH($B57,실적!$B$2:$B$504,0))) | K57: =IF(INDEX(실적!$U$2:$U$504,MATCH($B57,실적!$B$2:$B$504,0))="","",INDEX(실적!$U$2:$U$504,MATCH($B57,실적!$B$2:$B$504,0))) -> 반도체·디스플레이 제조 장비
A58: 19 | B58: CRWD | C58: =IF(INDEX(실적!$A$2:$A$504,MATCH($B58,실적!$B$2:$B$504,0))="","",INDEX(실적!$A$2:$A$504,MATCH($B58,실적!$B$2:$B$504,0))) -> CrowdStrike | D58: =IF(INDEX(실적!$V$2:$V$504,MATCH($B58,실적!$B$2:$B$504,0))="","",INDEX(실적!$V$2:$V$504,MATCH($B58,실적!$B$2:$B$504,0))) -> Information Technology | E58: =IF(INDEX(실적!$Y$2:$Y$504,MATCH($B58,실적!$B$2:$B$504,0))="","",INDEX(실적!$Y$2:$Y$504,MATCH($B58,실적!$B$2:$B$504,0))) -> 1.2042701 | F58: =IF(INDEX(실적!$N$2:$N$504,MATCH($B58,실적!$B$2:$B$504,0))="","",INDEX(실적!$N$2:$N$504,MATCH($B58,실적!$B$2:$B$504,0))) -> 0.25830402 | G58: =IF(INDEX(실적!$P$2:$P$504,MATCH($B58,실적!$B$2:$B$504,0))="","",INDEX(실적!$P$2:$P$504,MATCH($B58,실적!$B$2:$B$504,0))) -> 0.061537396 | H58: =IF(INDEX(실적!$T$2:$T$504,MATCH($B58,실적!$B$2:$B$504,0))="","",INDEX(실적!$T$2:$T$504,MATCH($B58,실적!$B$2:$B$504,0))) -> QoQ 가속 | I58: =IF(INDEX(실적!$AA$2:$AA$504,MATCH($B58,실적!$B$2:$B$504,0))="","",INDEX(실적!$AA$2:$AA$504,MATCH($B58,실적!$B$2:$B$504,0))) -> 0.21276684 | J58: =IF(INDEX(실적!$AB$2:$AB$504,MATCH($B58,실적!$B$2:$B$504,0))="","",INDEX(실적!$AB$2:$AB$504,MATCH($B58,실적!$B$2:$B$504,0))) | K58: =IF(INDEX(실적!$U$2:$U$504,MATCH($B58,실적!$B$2:$B$504,0))="","",INDEX(실적!$U$2:$U$504,MATCH($B58,실적!$B$2:$B$504,0))) -> 클라우드 기반 엔드포인트 사이버보안 플랫폼
A59: 20 | B59: VLO | C59: =IF(INDEX(실적!$A$2:$A$504,MATCH($B59,실적!$B$2:$B$504,0))="","",INDEX(실적!$A$2:$A$504,MATCH($B59,실적!$B$2:$B$504,0))) -> Valero Energy | D59: =IF(INDEX(실적!$V$2:$V$504,MATCH($B59,실적!$B$2:$B$504,0))="","",INDEX(실적!$V$2:$V$504,MATCH($B59,실적!$B$2:$B$504,0))) -> Energy | E59: =IF(INDEX(실적!$Y$2:$Y$504,MATCH($B59,실적!$B$2:$B$504,0))="","",INDEX(실적!$Y$2:$Y$504,MATCH($B59,실적!$B$2:$B$504,0))) -> 1.200082 | F59: =IF(INDEX(실적!$N$2:$N$504,MATCH($B59,실적!$B$2:$B$504,0))="","",INDEX(실적!$N$2:$N$504,MATCH($B59,실적!$B$2:$B$504,0))) -> 0.48803908 | G59: =IF(INDEX(실적!$P$2:$P$504,MATCH($B59,실적!$B$2:$B$504,0))="","",INDEX(실적!$P$2:$P$504,MATCH($B59,실적!$B$2:$B$504,0))) -> 0.37352151 | H59: =IF(INDEX(실적!$T$2:$T$504,MATCH($B59,실적!$B$2:$B$504,0))="","",INDEX(실적!$T$2:$T$504,MATCH($B59,실적!$B$2:$B$504,0))) -> 최근 QoQ≥10% | I59: =IF(INDEX(실적!$AA$2:$AA$504,MATCH($B59,실적!$B$2:$B$504,0))="","",INDEX(실적!$AA$2:$AA$504,MATCH($B59,실적!$B$2:$B$504,0))) -> -0.13340099 | J59: =IF(INDEX(실적!$AB$2:$AB$504,MATCH($B59,실적!$B$2:$B$504,0))="","",INDEX(실적!$AB$2:$AB$504,MATCH($B59,실적!$B$2:$B$504,0))) | K59: =IF(INDEX(실적!$U$2:$U$504,MATCH($B59,실적!$B$2:$B$504,0))="","",INDEX(실적!$U$2:$U$504,MATCH($B59,실적!$B$2:$B$504,0))) -> 석유 정제 및 재생연료(에탄올·재생디젤) 생산
A60: 21 | B60: FTNT | C60: =IF(INDEX(실적!$A$2:$A$504,MATCH($B60,실적!$B$2:$B$504,0))="","",INDEX(실적!$A$2:$A$504,MATCH($B60,실적!$B$2:$B$504,0))) -> Fortinet | D60: =IF(INDEX(실적!$V$2:$V$504,MATCH($B60,실적!$B$2:$B$504,0))="","",INDEX(실적!$V$2:$V$504,MATCH($B60,실적!$B$2:$B$504,0))) -> Information Technology | E60: =IF(INDEX(실적!$Y$2:$Y$504,MATCH($B60,실적!$B$2:$B$504,0))="","",INDEX(실적!$Y$2:$Y$504,MATCH($B60,실적!$B$2:$B$504,0))) -> 1.1380383 | F60: =IF(INDEX(실적!$N$2:$N$504,MATCH($B60,실적!$B$2:$B$504,0))="","",INDEX(실적!$N$2:$N$504,MATCH($B60,실적!$B$2:$B$504,0))) -> 0.25638037 | G60: =IF(INDEX(실적!$P$2:$P$504,MATCH($B60,실적!$B$2:$B$504,0))="","",INDEX(실적!$P$2:$P$504,MATCH($B60,실적!$B$2:$B$504,0))) -> 0.10721237 | H60: =IF(INDEX(실적!$T$2:$T$504,MATCH($B60,실적!$B$2:$B$504,0))="","",INDEX(실적!$T$2:$T$504,MATCH($B60,실적!$B$2:$B$504,0))) -> 최근 QoQ≥10% | I60: =IF(INDEX(실적!$AA$2:$AA$504,MATCH($B60,실적!$B$2:$B$504,0))="","",INDEX(실적!$AA$2:$AA$504,MATCH($B60,실적!$B$2:$B$504,0))) -> 0.13644286 | J60: =IF(INDEX(실적!$AB$2:$AB$504,MATCH($B60,실적!$B$2:$B$504,0))="","",INDEX(실적!$AB$2:$AB$504,MATCH($B60,실적!$B$2:$B$504,0))) | K60: =IF(INDEX(실적!$U$2:$U$504,MATCH($B60,실적!$B$2:$B$504,0))="","",INDEX(실적!$U$2:$U$504,MATCH($B60,실적!$B$2:$B$504,0))) -> 방화벽·네트워크 보안 장비 및 소프트웨어
A61: 22 | B61: FIX | C61: =IF(INDEX(실적!$A$2:$A$504,MATCH($B61,실적!$B$2:$B$504,0))="","",INDEX(실적!$A$2:$A$504,MATCH($B61,실적!$B$2:$B$504,0))) -> Comfort Systems USA | D61: =IF(INDEX(실적!$V$2:$V$504,MATCH($B61,실적!$B$2:$B$504,0))="","",INDEX(실적!$V$2:$V$504,MATCH($B61,실적!$B$2:$B$504,0))) -> Industrials | E61: =IF(INDEX(실적!$Y$2:$Y$504,MATCH($B61,실적!$B$2:$B$504,0))="","",INDEX(실적!$Y$2:$Y$504,MATCH($B61,실적!$B$2:$B$504,0))) -> 1.0543047 | F61: =IF(INDEX(실적!$N$2:$N$504,MATCH($B61,실적!$B$2:$B$504,0))="","",INDEX(실적!$N$2:$N$504,MATCH($B61,실적!$B$2:$B$504,0))) -> 0.50261236 | G61: =IF(INDEX(실적!$P$2:$P$504,MATCH($B61,실적!$B$2:$B$504,0))="","",INDEX(실적!$P$2:$P$504,MATCH($B61,실적!$B$2:$B$504,0))) -> 0.13971295 | H61: =IF(INDEX(실적!$T$2:$T$504,MATCH($B61,실적!$B$2:$B$504,0))="","",INDEX(실적!$T$2:$T$504,MATCH($B61,실적!$B$2:$B$504,0))) -> 최근 QoQ≥10% | I61: =IF(INDEX(실적!$AA$2:$AA$504,MATCH($B61,실적!$B$2:$B$504,0))="","",INDEX(실적!$AA$2:$AA$504,MATCH($B61,실적!$B$2:$B$504,0))) -> 0.20053638 | J61: =IF(INDEX(실적!$AB$2:$AB$504,MATCH($B61,실적!$B$2:$B$504,0))="","",INDEX(실적!$AB$2:$AB$504,MATCH($B61,실적!$B$2:$B$504,0))) -> 최근 QoQ≥10% | K61: =IF(INDEX(실적!$U$2:$U$504,MATCH($B61,실적!$B$2:$B$504,0))="","",INDEX(실적!$U$2:$U$504,MATCH($B61,실적!$B$2:$B$504,0))) -> 기계·전기 설비(HVAC) 시공 및 유지보수
A62: 23 | B62: KEYS | C62: =IF(INDEX(실적!$A$2:$A$504,MATCH($B62,실적!$B$2:$B$504,0))="","",INDEX(실적!$A$2:$A$504,MATCH($B62,실적!$B$2:$B$504,0))) -> Keysight Technologies | D62: =IF(INDEX(실적!$V$2:$V$504,MATCH($B62,실적!$B$2:$B$504,0))="","",INDEX(실적!$V$2:$V$504,MATCH($B62,실적!$B$2:$B$504,0))) -> Information Technology | E62: =IF(INDEX(실적!$Y$2:$Y$504,MATCH($B62,실적!$B$2:$B$504,0))="","",INDEX(실적!$Y$2:$Y$504,MATCH($B62,실적!$B$2:$B$504,0))) -> 1.0260306 | F62: =IF(INDEX(실적!$N$2:$N$504,MATCH($B62,실적!$B$2:$B$504,0))="","",INDEX(실적!$N$2:$N$504,MATCH($B62,실적!$B$2:$B$504,0))) -> 0.36538462 | G62: =IF(INDEX(실적!$P$2:$P$504,MATCH($B62,실적!$B$2:$B$504,0))="","",INDEX(실적!$P$2:$P$504,MATCH($B62,실적!$B$2:$B$504,0))) -> 0.075131043 | H62: =IF(INDEX(실적!$T$2:$T$504,MATCH($B62,실적!$B$2:$B$504,0))="","",INDEX(실적!$T$2:$T$504,MATCH($B62,실적!$B$2:$B$504,0))) | I62: =IF(INDEX(실적!$AA$2:$AA$504,MATCH($B62,실적!$B$2:$B$504,0))="","",INDEX(실적!$AA$2:$AA$504,MATCH($B62,실적!$B$2:$B$504,0))) -> 0.11092851 | J62: =IF(INDEX(실적!$AB$2:$AB$504,MATCH($B62,실적!$B$2:$B$504,0))="","",INDEX(실적!$AB$2:$AB$504,MATCH($B62,실적!$B$2:$B$504,0))) | K62: 전자 계측·시험 장비 및 설계 소프트웨어
A63: 24 | B63: MPC | C63: =IF(INDEX(실적!$A$2:$A$504,MATCH($B63,실적!$B$2:$B$504,0))="","",INDEX(실적!$A$2:$A$504,MATCH($B63,실적!$B$2:$B$504,0))) -> Marathon Petroleum | D63: =IF(INDEX(실적!$V$2:$V$504,MATCH($B63,실적!$B$2:$B$504,0))="","",INDEX(실적!$V$2:$V$504,MATCH($B63,실적!$B$2:$B$504,0))) -> Energy | E63: =IF(INDEX(실적!$Y$2:$Y$504,MATCH($B63,실적!$B$2:$B$504,0))="","",INDEX(실적!$Y$2:$Y$504,MATCH($B63,실적!$B$2:$B$504,0))) -> 1.0112895 | F63: =IF(INDEX(실적!$N$2:$N$504,MATCH($B63,실적!$B$2:$B$504,0))="","",INDEX(실적!$N$2:$N$504,MATCH($B63,실적!$B$2:$B$504,0))) -> 0.53832954 | G63: =IF(INDEX(실적!$P$2:$P$504,MATCH($B63,실적!$B$2:$B$504,0))="","",INDEX(실적!$P$2:$P$504,MATCH($B63,실적!$B$2:$B$504,0))) -> 0.5202924 | H63: =IF(INDEX(실적!$T$2:$T$504,MATCH($B63,실적!$B$2:$B$504,0))="","",INDEX(실적!$T$2:$T$504,MATCH($B63,실적!$B$2:$B$504,0))) -> 최근 QoQ≥10% | I63: =IF(INDEX(실적!$AA$2:$AA$504,MATCH($B63,실적!$B$2:$B$504,0))="","",INDEX(실적!$AA$2:$AA$504,MATCH($B63,실적!$B$2:$B$504,0))) -> -0.10853511 | J63: =IF(INDEX(실적!$AB$2:$AB$504,MATCH($B63,실적!$B$2:$B$504,0))="","",INDEX(실적!$AB$2:$AB$504,MATCH($B63,실적!$B$2:$B$504,0))) -> QoQ 가속 | K63: =IF(INDEX(실적!$U$2:$U$504,MATCH($B63,실적!$B$2:$B$504,0))="","",INDEX(실적!$U$2:$U$504,MATCH($B63,실적!$B$2:$B$504,0))) -> 석유 정제·마케팅 및 미드스트림(MPLX)
A64: 25 | B64: PANW | C64: =IF(INDEX(실적!$A$2:$A$504,MATCH($B64,실적!$B$2:$B$504,0))="","",INDEX(실적!$A$2:$A$504,MATCH($B64,실적!$B$2:$B$504,0))) -> Palo Alto Networks | D64: =IF(INDEX(실적!$V$2:$V$504,MATCH($B64,실적!$B$2:$B$504,0))="","",INDEX(실적!$V$2:$V$504,MATCH($B64,실적!$B$2:$B$504,0))) -> Information Technology | E64: =IF(INDEX(실적!$Y$2:$Y$504,MATCH($B64,실적!$B$2:$B$504,0))="","",INDEX(실적!$Y$2:$Y$504,MATCH($B64,실적!$B$2:$B$504,0))) -> 0.95964126 | F64: =IF(INDEX(실적!$N$2:$N$504,MATCH($B64,실적!$B$2:$B$504,0))="","",INDEX(실적!$N$2:$N$504,MATCH($B64,실적!$B$2:$B$504,0))) -> 0.34447818 | G64: =IF(INDEX(실적!$P$2:$P$504,MATCH($B64,실적!$B$2:$B$504,0))="","",INDEX(실적!$P$2:$P$504,MATCH($B64,실적!$B$2:$B$504,0))) -> 0.13590939 | H64: =IF(INDEX(실적!$T$2:$T$504,MATCH($B64,실적!$B$2:$B$504,0))="","",INDEX(실적!$T$2:$T$504,MATCH($B64,실적!$B$2:$B$504,0))) -> 최근 QoQ≥10% | I64: =IF(INDEX(실적!$AA$2:$AA$504,MATCH($B64,실적!$B$2:$B$504,0))="","",INDEX(실적!$AA$2:$AA$504,MATCH($B64,실적!$B$2:$B$504,0))) -> 0.15839233 | J64: =IF(INDEX(실적!$AB$2:$AB$504,MATCH($B64,실적!$B$2:$B$504,0))="","",INDEX(실적!$AB$2:$AB$504,MATCH($B64,실적!$B$2:$B$504,0))) -> 최근 QoQ≥10% | K64: =IF(INDEX(실적!$U$2:$U$504,MATCH($B64,실적!$B$2:$B$504,0))="","",INDEX(실적!$U$2:$U$504,MATCH($B64,실적!$B$2:$B$504,0))) -> 네트워크·클라우드 사이버보안 솔루션
A65: 26 | B65: FLEX | C65: =IF(INDEX(실적!$A$2:$A$504,MATCH($B65,실적!$B$2:$B$504,0))="","",INDEX(실적!$A$2:$A$504,MATCH($B65,실적!$B$2:$B$504,0))) -> Flex Ltd. | D65: =IF(INDEX(실적!$V$2:$V$504,MATCH($B65,실적!$B$2:$B$504,0))="","",INDEX(실적!$V$2:$V$504,MATCH($B65,실적!$B$2:$B$504,0))) -> Information Technology | E65: =IF(INDEX(실적!$Y$2:$Y$504,MATCH($B65,실적!$B$2:$B$504,0))="","",INDEX(실적!$Y$2:$Y$504,MATCH($B65,실적!$B$2:$B$504,0))) -> 0.95032998 | F65: =IF(INDEX(실적!$N$2:$N$504,MATCH($B65,실적!$B$2:$B$504,0))="","",INDEX(실적!$N$2:$N$504,MATCH($B65,실적!$B$2:$B$504,0))) -> 0.16864645 | G65: =IF(INDEX(실적!$P$2:$P$504,MATCH($B65,실적!$B$2:$B$504,0))="","",INDEX(실적!$P$2:$P$504,MATCH($B65,실적!$B$2:$B$504,0))) -> 0.059365259 | H65: =IF(INDEX(실적!$T$2:$T$504,MATCH($B65,실적!$B$2:$B$504,0))="","",INDEX(실적!$T$2:$T$504,MATCH($B65,실적!$B$2:$B$504,0))) -> QoQ 가속 | I65: =IF(INDEX(실적!$AA$2:$AA$504,MATCH($B65,실적!$B$2:$B$504,0))="","",INDEX(실적!$AA$2:$AA$504,MATCH($B65,실적!$B$2:$B$504,0))) -> 0.041336712 | J65: =IF(INDEX(실적!$AB$2:$AB$504,MATCH($B65,실적!$B$2:$B$504,0))="","",INDEX(실적!$AB$2:$AB$504,MATCH($B65,실적!$B$2:$B$504,0))) | K65: =IF(INDEX(실적!$U$2:$U$504,MATCH($B65,실적!$B$2:$B$504,0))="","",INDEX(실적!$U$2:$U$504,MATCH($B65,실적!$B$2:$B$504,0))) -> 전자제품 위탁생산(EMS) 및 데이터센터 전력 장비
A66: 27 | B66: GLW | C66: =IF(INDEX(실적!$A$2:$A$504,MATCH($B66,실적!$B$2:$B$504,0))="","",INDEX(실적!$A$2:$A$504,MATCH($B66,실적!$B$2:$B$504,0))) -> Corning Inc. | D66: =IF(INDEX(실적!$V$2:$V$504,MATCH($B66,실적!$B$2:$B$504,0))="","",INDEX(실적!$V$2:$V$504,MATCH($B66,실적!$B$2:$B$504,0))) -> Information Technology | E66: =IF(INDEX(실적!$Y$2:$Y$504,MATCH($B66,실적!$B$2:$B$504,0))="","",INDEX(실적!$Y$2:$Y$504,MATCH($B66,실적!$B$2:$B$504,0))) -> 0.93317482 | F66: =IF(INDEX(실적!$N$2:$N$504,MATCH($B66,실적!$B$2:$B$504,0))="","",INDEX(실적!$N$2:$N$504,MATCH($B66,실적!$B$2:$B$504,0))) -> 0.16649404 | G66: =IF(INDEX(실적!$P$2:$P$504,MATCH($B66,실적!$B$2:$B$504,0))="","",INDEX(실적!$P$2:$P$504,MATCH($B66,실적!$B$2:$B$504,0))) -> 0.0871139 | H66: =IF(INDEX(실적!$T$2:$T$504,MATCH($B66,실적!$B$2:$B$504,0))="","",INDEX(실적!$T$2:$T$504,MATCH($B66,실적!$B$2:$B$504,0))) | I66: =IF(INDEX(실적!$AA$2:$AA$504,MATCH($B66,실적!$B$2:$B$504,0))="","",INDEX(실적!$AA$2:$AA$504,MATCH($B66,실적!$B$2:$B$504,0))) -> 0.18794217 | J66: =IF(INDEX(실적!$AB$2:$AB$504,MATCH($B66,실적!$B$2:$B$504,0))="","",INDEX(실적!$AB$2:$AB$504,MATCH($B66,실적!$B$2:$B$504,0))) -> 최근 QoQ≥10% | K66: 특수유리·광섬유·디스플레이 유리
A67: 28 | B67: FCX | C67: =IF(INDEX(실적!$A$2:$A$504,MATCH($B67,실적!$B$2:$B$504,0))="","",INDEX(실적!$A$2:$A$504,MATCH($B67,실적!$B$2:$B$504,0))) -> Freeport-McMoRan | D67: =IF(INDEX(실적!$V$2:$V$504,MATCH($B67,실적!$B$2:$B$504,0))="","",INDEX(실적!$V$2:$V$504,MATCH($B67,실적!$B$2:$B$504,0))) -> Materials | E67: =IF(INDEX(실적!$Y$2:$Y$504,MATCH($B67,실적!$B$2:$B$504,0))="","",INDEX(실적!$Y$2:$Y$504,MATCH($B67,실적!$B$2:$B$504,0))) -> 0.92673215 | F67: =IF(INDEX(실적!$N$2:$N$504,MATCH($B67,실적!$B$2:$B$504,0))="","",INDEX(실적!$N$2:$N$504,MATCH($B67,실적!$B$2:$B$504,0))) -> -0.072935901 | G67: =IF(INDEX(실적!$P$2:$P$504,MATCH($B67,실적!$B$2:$B$504,0))="","",INDEX(실적!$P$2:$P$504,MATCH($B67,실적!$B$2:$B$504,0))) -> 0.12752647 | H67: =IF(INDEX(실적!$T$2:$T$504,MATCH($B67,실적!$B$2:$B$504,0))="","",INDEX(실적!$T$2:$T$504,MATCH($B67,실적!$B$2:$B$504,0))) -> 최근 QoQ≥10% | I67: =IF(INDEX(실적!$AA$2:$AA$504,MATCH($B67,실적!$B$2:$B$504,0))="","",INDEX(실적!$AA$2:$AA$504,MATCH($B67,실적!$B$2:$B$504,0))) -> 0.1446256 | J67: =IF(INDEX(실적!$AB$2:$AB$504,MATCH($B67,실적!$B$2:$B$504,0))="","",INDEX(실적!$AB$2:$AB$504,MATCH($B67,실적!$B$2:$B$504,0))) -> 최근 QoQ≥10% | K67: =IF(INDEX(실적!$U$2:$U$504,MATCH($B67,실적!$B$2:$B$504,0))="","",INDEX(실적!$U$2:$U$504,MATCH($B67,실적!$B$2:$B$504,0))) -> 구리·금·몰리브덴 광산
A68: 29 | B68: PSX | C68: =IF(INDEX(실적!$A$2:$A$504,MATCH($B68,실적!$B$2:$B$504,0))="","",INDEX(실적!$A$2:$A$504,MATCH($B68,실적!$B$2:$B$504,0))) -> Phillips 66 | D68: =IF(INDEX(실적!$V$2:$V$504,MATCH($B68,실적!$B$2:$B$504,0))="","",INDEX(실적!$V$2:$V$504,MATCH($B68,실적!$B$2:$B$504,0))) -> Energy | E68: =IF(INDEX(실적!$Y$2:$Y$504,MATCH($B68,실적!$B$2:$B$504,0))="","",INDEX(실적!$Y$2:$Y$504,MATCH($B68,실적!$B$2:$B$504,0))) -> 0.87773629 | F68: =IF(INDEX(실적!$N$2:$N$504,MATCH($B68,실적!$B$2:$B$504,0))="","",INDEX(실적!$N$2:$N$504,MATCH($B68,실적!$B$2:$B$504,0))) -> 0.53059448 | G68: =IF(INDEX(실적!$P$2:$P$504,MATCH($B68,실적!$B$2:$B$504,0))="","",INDEX(실적!$P$2:$P$504,MATCH($B68,실적!$B$2:$B$504,0))) -> 0.56742471 | H68: =IF(INDEX(실적!$T$2:$T$504,MATCH($B68,실적!$B$2:$B$504,0))="","",INDEX(실적!$T$2:$T$504,MATCH($B68,실적!$B$2:$B$504,0))) -> 최근 QoQ≥10% | I68: =IF(INDEX(실적!$AA$2:$AA$504,MATCH($B68,실적!$B$2:$B$504,0))="","",INDEX(실적!$AA$2:$AA$504,MATCH($B68,실적!$B$2:$B$504,0))) -> -0.12604579 | J68: =IF(INDEX(실적!$AB$2:$AB$504,MATCH($B68,실적!$B$2:$B$504,0))="","",INDEX(실적!$AB$2:$AB$504,MATCH($B68,실적!$B$2:$B$504,0))) | K68: =IF(INDEX(실적!$U$2:$U$504,MATCH($B68,실적!$B$2:$B$504,0))="","",INDEX(실적!$U$2:$U$504,MATCH($B68,실적!$B$2:$B$504,0))) -> 석유 정제·화학·미드스트림·마케팅
A69: 30 | B69: MRK | C69: =IF(INDEX(실적!$A$2:$A$504,MATCH($B69,실적!$B$2:$B$504,0))="","",INDEX(실적!$A$2:$A$504,MATCH($B69,실적!$B$2:$B$504,0))) -> Merck & Co. | D69: =IF(INDEX(실적!$V$2:$V$504,MATCH($B69,실적!$B$2:$B$504,0))="","",INDEX(실적!$V$2:$V$504,MATCH($B69,실적!$B$2:$B$504,0))) -> Health Care | E69: =IF(INDEX(실적!$Y$2:$Y$504,MATCH($B69,실적!$B$2:$B$504,0))="","",INDEX(실적!$Y$2:$Y$504,MATCH($B69,실적!$B$2:$B$504,0))) -> 0.858667 | F69: =IF(INDEX(실적!$N$2:$N$504,MATCH($B69,실적!$B$2:$B$504,0))="","",INDEX(실적!$N$2:$N$504,MATCH($B69,실적!$B$2:$B$504,0))) -> 0.050676958 | G69: =IF(INDEX(실적!$P$2:$P$504,MATCH($B69,실적!$B$2:$B$504,0))="","",INDEX(실적!$P$2:$P$504,MATCH($B69,실적!$B$2:$B$504,0))) -> 0.019710181 | H69: =IF(INDEX(실적!$T$2:$T$504,MATCH($B69,실적!$B$2:$B$504,0))="","",INDEX(실적!$T$2:$T$504,MATCH($B69,실적!$B$2:$B$504,0))) | I69: =IF(INDEX(실적!$AA$2:$AA$504,MATCH($B69,실적!$B$2:$B$504,0))="","",INDEX(실적!$AA$2:$AA$504,MATCH($B69,실적!$B$2:$B$504,0))) -> -0.018992056 | J69: =IF(INDEX(실적!$AB$2:$AB$504,MATCH($B69,실적!$B$2:$B$504,0))="","",INDEX(실적!$AB$2:$AB$504,MATCH($B69,실적!$B$2:$B$504,0))) | K69: 항암 면역치료제(키트루다)·백신·동물의약품

Sheet 메모
A1: 데이터 출처 | B1: Yahoo Finance via yfinance (yf.Ticker(t).quarterly_income_stmt: Total Revenue / Operating Income)
A2: 종목 리스트 출처 | B2: https://en.wikipedia.org/wiki/List_of_S%26P_500_companies
A3: 수집 일시 | B3: 2026-09-24 18:32:58 KST
A4: 수집 성공 / 전체 | B4: 503 / 503
A5: 단위 | B5: 매출·영업이익: 백만 달러(USD mn), 성장률: %
A6: 영업이익 YoY 규칙 | B6: Q-4 영업이익 ≤ 0 → Q0 > 0 이면 '흑자전환', 아니면 'N/M' / Q-4 > 0 이고 Q0 < 0 → '적자전환'
A7: 행 정렬 기준 | B7: ① 초록: QoQ 가속(QoQ(Q0)>QoQ(Q-1)>QoQ(Q-2)>QoQ(Q-3)) 이면서 최근 QoQ≥10% (11개) → ② 노랑: 둘 중 하나만 해당 (가속 11개, QoQ≥10% 143개) — ①②는 최근 QoQ 내림차순 → ③ 나머지: 매출 YoY 내림차순(계산 불가는 맨 아래). 주요 사업은 ①② 기업에 기재 (sp500_business_ko.csv, 없으면 Yahoo 업종)
A9: 수집 실패 티커 (0개)
A10: 티커 | B10: 기업명 | C10: 오류
A11: (없음)
A13: 데이터 누락 티커 (74개)
A14: 티커 | B14: 기업명 | C14: 누락 내용
A15: BX | B15: Blackstone Inc. | C15: 영업이익 없음: Q0,Q-1,Q-2,Q-3,Q-4
A16: ES | B16: Eversource Energy | C16: Yahoo에 값 없는 최신 분기 열 제외: 2026-06-30
A17: BRK-B | B17: Berkshire Hathaway | C17: 영업이익 없음: Q0,Q-1,Q-2,Q-3,Q-4; Q0~Q-4 간격 456일(1년 아님, YoY 해석 주의)
A18: CTVA | B18: Corteva | C18: Yahoo에 값 없는 최신 분기 열 제외: 2026-06-30
A19: AEE | B19: Ameren | C19: Yahoo에 값 없는 최신 분기 열 제외: 2026-06-30
A20: LEN | B20: Lennar | C20: Yahoo에 값 없는 최신 분기 열 제외: 2026-08-31
A21: APH | B21: Amphenol | C21: Yahoo에 값 없는 최신 분기 열 제외: 2026-06-30
A22: GS | B22: Goldman Sachs | C22: 영업이익 없음: Q0,Q-1,Q-2,Q-3,Q-4
A23: FERG | B23: Ferguson Enterprises | C23: Q0~Q-4 간격 426일(1년 아님, YoY 해석 주의)
A24: DTE | B24: DTE Energy | C24: Yahoo에 값 없는 최신 분기 열 제외: 2026-06-30
A25: FITB | B25: Fifth Third Bancorp | C25: 영업이익 없음: Q0,Q-1,Q-2,Q-3,Q-4
... A88: KIM | B88: Kimco Realty | C88: 매출 없음: Q-1,Q-2,Q-3,Q-4
A90: 기업별 실제 분기 종료일
A91: 티커 | B91: 기업명 | C91: Q0 종료일 | D91: Q-1 종료일 | E91: Q-2 종료일 | F91: Q-3 종료일 | G91: Q-4 종료일 | H91: 비고
A92: A | B92: Agilent Technologies | C92: 2026-07-31 | D92: 2026-04-30 | E92: 2026-01-31 | F92: 2025-10-31 | G92: 2025-07-31
A93: AAPL | B93: Apple Inc. | C93: 2026-06-30 | D93: 2026-03-31 | E93: 2025-12-31 | F93: 2025-09-30 | G93: 2025-06-30
A94: ABBV | B94: AbbVie | C94: 2026-06-30 | D94: 2026-03-31 | E94: 2025-12-31 | F94: 2025-09-30 | G94: 2025-06-30
A95: ABNB | B95: Airbnb | C95: 2026-06-30 | D95: 2026-03-31 | E95: 2025-12-31 | F95: 2025-09-30 | G95: 2025-06-30
A96: ABT | B96: Abbott Laboratories | C96: 2026-03-31 | D96: 2025-12-31 | E96: 2025-09-30 | F96: 2025-06-30 | G96: 2025-03-31 | H96: Yahoo에 값 없는 최신 분기 열 제외: 2026-06-30
A97: ACGL | B97: Arch Capital Group | C97: 2026-06-30 | D97: 2026-03-31 | E97: 2025-12-31 | F97: 2025-09-30 | G97: 2025-06-30
A98: ACN | B98: Accenture | C98: 2026-05-31 | D98: 2026-02-28 | E98: 2025-11-30 | F98: 2025-08-31 | G98: 2025-05-31
A99: ADBE | B99: Adobe Inc. | C99: 2026-08-31 | D99: 2026-05-31 | E99: 2026-02-28 | F99: 2025-11-30 | G99: 2025-08-31
A100: ADI | B100: Analog Devices | C100: 2026-07-31 | D100: 2026-04-30 | E100: 2026-01-31 | F100: 2025-10-31 | G100: 2025-07-31
A101: ADM | B101: Archer Daniels Midland | C101: 2026-06-30 | D101: 2026-03-31 | E101: 2025-12-31 | F101: 2025-09-30 | G101: 2025-06-30
A102: ADP | B102: Automatic Data Processing | C102: 2026-06-30 | D102: 2026-03-31 | E102: 2025-12-31 | F102: 2025-09-30 | G102: 2025-06-30
A103: ADSK | B103: Autodesk | C103: 2026-07-31 | D103: 2026-04-30 | E103: 2026-01-31 | F103: 2025-10-31 | G103: 2025-07-31
A104: AEE | B104: Ameren | C104: 2026-03-31 | D104: 2025-12-31 | E104: 2025-09-30 | F104: 2025-06-30 | G104: 2025-03-31 | H104: Yahoo에 값 없는 최신 분기 열 제외: 2026-06-30
A105: AEP | B105: American Electric Power | C105: 2026-06-30 | D105: 2026-03-31 | E105: 2025-12-31 | F105: 2025-09-30 | G105: 2025-06-30
A106: AES | B106: AES Corporation | C106: 2026-06-30 | D106: 2026-03-31 | E106: 2025-12-31 | F106: 2025-09-30 | G106: 2025-06-30
A107: AFL | B107: Aflac | C107: 2026-06-30 | D107: 2026-03-31 | E107: 2025-12-31 | F107: 2025-09-30 | G107: 2025-06-30
A108: AIG | B108: American International Group | C108: 2026-06-30 | D108: 2026-03-31 | E108: 2025-12-31 | F108: 2025-09-30 | G108: 2025-06-30
A109: AIZ | B109: Assurant | C109: 2026-06-30 | D109: 2026-03-31 | E109: 2025-12-31 | F109: 2025-09-30 | G109: 2025-06-30
A110: AJG | B110: Arthur J. Gallagher & Co. | C110: 2026-06-30 | D110: 2026-03-31 | E110: 2025-12-31 | F110: 2025-09-30 | G110: 2025-06-30
A111: AKAM | B111: Akamai Technologies | C111: 2026-06-30 | D111: 2026-03-31 | E111: 2025-12-31 | F111: 2025-09-30 | G111: 2025-06-30
A112: ALB | B112: Albemarle Corporation | C112: 2026-06-30 | D112: 2026-03-31 | E112: 2025-12-31 | F112: 2025-09-30 | G112: 2025-06-30
A113: ALGN | B113: Align Technology | C113: 2026-06-30 | D113: 2026-03-31 | E113: 2025-12-31 | F113: 2025-09-30 | G113: 2025-06-30
A114: ALL | B114: Allstate | C114: 2026-06-30 | D114: 2026-03-31 | E114: 2025-12-31 | F114: 2025-09-30 | G114: 2025-06-30
A115: ALLE | B115: Allegion | C115: 2026-06-30 | D115: 2026-03-31 | E115: 2025-12-31 | F115: 2025-09-30 | G115: 2025-06-30
A116: AMAT | B116: Applied Materials | C116: 2026-07-31 | D116: 2026-04-30 | E116: 2026-01-31 | F116: 2025-10-31 | G116: 2025-07-31
... A122: AMT | B122: American Tower | C122: 2026-06-30 | D122: 2026-03-31 | E122: 2025-12-31 | F122: 2025-09-30 | G122: 2025-06-30
A123: AMZN | B123: Amazon | C123: 2026-03-31 | D123: 2025-12-31 | E123: 2025-09-30 | F123: 2025-06-30 | G123: 2025-03-31 | H123: Yahoo에 값 없는 최신 분기 열 제외: 2026-06-30
A124: ANET | B124: Arista Networks | C124: 2026-06-30 | D124: 2026-03-31 | E124: 2025-12-31 | F124: 2025-09-30 | G124: 2025-06-30
A125: AON | B125: Aon plc | C125: 2026-06-30 | D125: 2026-03-31 | E125: 2025-12-31 | F125: 2025-09-30 | G125: 2025-06-30
A126: AOS | B126: A. O. Smith | C126: 2026-06-30 | D126: 2026-03-31 | E126: 2025-12-31 | F126: 2025-09-30 | G126: 2025-06-30
A127: APA | B127: APA Corporation | C127: 2026-06-30 | D127: 2026-03-31 | E127: 2025-12-31 | F127: 2025-09-30 | G127: 2025-06-30
A128: APD | B128: Air Products | C128: 2026-06-30 | D128: 2026-03-31 | E128: 2025-12-31 | F128: 2025-09-30 | G128: 2025-06-30
A129: APH | B129: Amphenol | C129: 2026-03-31 | D129: 2025-12-31 | E129: 2025-09-30 | F129: 2025-06-30 | G129: 2025-03-31 | H129: Yahoo에 값 없는 최신 분기 열 제외: 2026-06-30
A130: APO | B130: Apollo Global Management | C130: 2026-06-30 | D130: 2026-03-31 | E130: 2025-12-31 | F130: 2025-09-30 | G130: 2025-06-30
A131: APP | B131: AppLovin | C131: 2026-06-30 | D131: 2026-03-31 | E131: 2025-12-31 | F131: 2025-09-30 | G131: 2025-06-30
A132: APTV | B132: Aptiv | C132: 2026-06-30 | D132: 2026-03-31 | E132: 2025-12-31 | F132: 2025-09-30 | G132: 2025-06-30
A133: ARE | B133: Alexandria Real Estate Equities | C133: 2026-06-30 | D133: 2026-03-31 | E133: 2025-12-31 | F133: 2025-09-30 | G133: 2025-06-30
A134: ARES | B134: Ares Management | C134: 2026-06-30 | D134: 2026-03-31 | E134: 2025-12-31 | F134: 2025-09-30 | G134: 2025-06-30
A135: ATO | B135: Atmos Energy | C135: 2026-06-30 | D135: 2026-03-31 | E135: 2025-12-31 | F135: 2025-09-30 | G135: 2025-06-30
A136: AVGO | B136: Broadcom | C136: 2026-07-31 | D136: 2026-04-30 | E136: 2026-01-31 | F136: 2025-10-31 | G136: 2025-07-31
A137: AVY | B137: Avery Dennison | C137: 2026-06-30 | D137: 2026-03-31 | E137: 2025-12-31 | F137: 2025-09-30 | G137: 2025-06-30
A138: AWK | B138: American Water Works | C138: 2026-06-30 | D138: 2026-03-31 | E138: 2025-12-31 | F138: 2025-09-30 | G138: 2025-06-30
A139: AXON | B139: Axon Enterprise | C139: 2026-06-30 | D139: 2026-03-31 | E139: 2025-12-31 | F139: 2025-09-30 | G139: 2025-06-30
A140: AXP | B140: American Express | C140: 2026-06-30 | D140: 2026-03-31 | E140: 2025-12-31 | F140: 2025-09-30 | G140: 2025-06-30
A141: AZO | B141: AutoZone | C141: 2026-05-31 | D141: 2026-02-28 | E141: 2025-11-30 | F141: 2025-08-31 | G141: 2025-05-31
A142: BA | B142: Boeing | C142: 2026-03-31 | D142: 2025-12-31 | E142: 2025-09-30 | F142: 2025-06-30 | G142: 2025-03-31 | H142: Yahoo에 값 없는 최신 분기 열 제외: 2026-06-30
A143: BAC | B143: Bank of America | C143: 2026-03-31 | D143: 2025-12-31 | E143: 2025-09-30 | F143: 2025-06-30 | G143: 2025-03-31 | H143: Yahoo에 값 없는 최신 분기 열 제외: 2026-06-30
A144: BALL | B144: Ball Corporation | C144: 2026-06-30 | D144: 2026-03-31 | E144: 2025-12-31 | F144: 2025-09-30 | G144: 2025-06-30
A145: BAX | B145: Baxter International | C145: 2026-06-30 | D145: 2026-03-31 | E145: 2025-12-31 | F145: 2025-09-30 | G145: 2025-06-30
A146: BBY | B146: Best Buy | C146: 2026-07-31 | D146: 2026-04-30 | E146: 2026-01-31 | F146: 2025-10-31 | G146: 2025-07-31
A147: BDX | B147: Becton Dickinson | C147: 2026-06-30 | D147: 2026-03-31 | E147: 2025-12-31 | F147: 2025-09-30 | G147: 2025-06-30
A148: BE | B148: Bloom Energy | C148: 2026-06-30 | D148: 2026-03-31 | E148: 2025-12-31 | F148: 2025-09-30 | G148: 2025-06-30
A149: BEN | B149: Franklin Resources | C149: 2026-06-30 | D149: 2026-03-31 | E149: 2025-12-31 | F149: 2025-09-30 | G149: 2025-06-30
A150: BF-B | B150: Brown–Forman | C150: 2026-07-31 | D150: 2026-04-30 | E150: 2026-01-31 | F150: 2025-10-31 | G150: 2025-07-31
A151: BG | B151: Bunge Global | C151: 2026-06-30 | D151: 2026-03-31 | E151: 2025-12-31 | F151: 2025-09-30 | G151: 2025-06-30
A152: BIIB | B152: Biogen | C152: 2026-06-30 | D152: 2026-03-31 | E152: 2025-12-31 | F152: 2025-09-30 | G152: 2025-06-30
A153: BKNG | B153: Booking Holdings | C153: 2026-06-30 | D153: 2026-03-31 | E153: 2025-12-31 | F153: 2025-09-30 | G153: 2025-06-30
A154: BKR | B154: Baker Hughes | C154: 2026-06-30 | D154: 2026-03-31 | E154: 2025-12-31 | F154: 2025-09-30 | G154: 2025-06-30
A155: BLK | B155: BlackRock | C155: 2026-06-30 | D155: 2026-03-31 | E155: 2025-12-31 | F155: 2025-09-30 | G155: 2025-06-30
A156: BMY | B156: Bristol Myers Squibb | C156: 2026-06-30 | D156: 2026-03-31 | E156: 2025-12-31 | F156: 2025-09-30 | G156: 2025-06-30
A157: BNY | B157: BNY Mellon | C157: 2026-03-31 | D157: 2025-12-31 | E157: 2025-09-30 | F157: 2025-06-30 | G157: 2025-03-31 | H157: Yahoo에 값 없는 최신 분기 열 제외: 2026-06-30
A158: BR | B158: Broadridge Financial Solutions | C158: 2026-06-30 | D158: 2026-03-31 | E158: 2025-12-31 | F158: 2025-09-30 | G158: 2025-06-30
A159: BRK-B | B159: Berkshire Hathaway | C159: 2026-06-30 | D159: 2026-03-31 | E159: 2025-12-31 | F159: 2025-06-30 | G159: 2025-03-31
A160: BRO | B160: Brown & Brown | C160: 2026-06-30 | D160: 2026-03-31 | E160: 2025-12-31 | F160: 2025-09-30 | G160: 2025-06-30
A161: BSX | B161: Boston Scientific | C161: 2026-06-30 | D161: 2026-03-31 | E161: 2025-12-31 | F161: 2025-09-30 | G161: 2025-06-30
A162: BX | B162: Blackstone Inc. | C162: 2026-06-30 | D162: 2026-03-31 | E162: 2025-12-31 | F162: 2025-09-30 | G162: 2025-06-30
A163: BXP | B163: BXP, Inc. | C163: 2026-06-30 | D163: 2026-03-31 | E163: 2025-12-31 | F163: 2025-09-30 | G163: 2025-06-30
A164: C | B164: Citigroup | C164: 2026-06-30 | D164: 2026-03-31 | E164: 2025-12-31 | F164: 2025-09-30 | G164: 2025-06-30
A165: CAH | B165: Cardinal Health | C165: 2026-06-30 | D165: 2026-03-31 | E165: 2025-12-31 | F165: 2025-09-30 | G165: 2025-06-30
A166: CARR | B166: Carrier Global | C166: 2026-06-30 | D166: 2026-03-31 | E166: 2025-12-31 | F166: 2025-09-30 | G166: 2025-06-30
A167: CASY | B167: Casey's | C167: 2026-07-31 | D167: 2026-04-30 | E167: 2026-01-31 | F167: 2025-10-31 | G167: 2025-07-31
A168: CAT | B168: Caterpillar Inc. | C168: 2026-06-30 | D168: 2026-03-31 | E168: 2025-12-31 | F168: 2025-09-30 | G168: 2025-06-30
A169: CB | B169: Chubb Limited | C169: 2026-06-30 | D169: 2026-03-31 | E169: 2025-12-31 | F169: 2025-09-30 | G169: 2025-06-30
... A178: CFG | B178: Citizens Financial Group | C178: 2026-06-30 | D178: 2026-03-31 | E178: 2025-12-31 | F178: 2025-09-30 | G178: 2025-06-30
...
